Workbook

Sheet 📊 All Years
B1: 📊 All-Years Dashboard | May 2026 – Jun 2028 — Expense Tracker
B2: Auto-updates from all month tabs · Adjust paychecks & budgets in each tab · Negative = overspent
B4: Month | C4: Paycheck $ | D4: Carry-Over | E4: Total Avail | F4: Going Out $ | G4: Invested | H4: Ally Added | I4: Left Over $ | J4: Ally Balance
B6: ── 2026 (May – Dec) ──
B7: May 2026 | C7: ='May 2026'!D6+'May 2026'!H6 | D7: ='May 2026'!D9 | E7: ='May 2026'!H8 | F7: ='May 2026'!D64 | G7: ='May 2026'!D54 | H7: ='May 2026'!D53 | I7: ='May 2026'!D65 | J7: ='May 2026'!F53
B8: Jun 2026 | C8: ='Jun 2026'!D6+'Jun 2026'!H6 | D8: ='Jun 2026'!D9 | E8: ='Jun 2026'!H8 | F8: ='Jun 2026'!D64 | G8: ='Jun 2026'!D54 | H8: ='Jun 2026'!D53 | I8: ='Jun 2026'!D65 | J8: ='Jun 2026'!F53
B9: Jul 2026 | C9: ='Jul 2026'!D6+'Jul 2026'!H6 | D9: ='Jul 2026'!D9 | E9: ='Jul 2026'!H8 | F9: ='Jul 2026'!D64 | G9: ='Jul 2026'!D54 | H9: ='Jul 2026'!D53 | I9: ='Jul 2026'!D65 | J9: ='Jul 2026'!F53
B10: Aug 2026 | C10: ='Aug 2026'!D6+'Aug 2026'!H6 | D10: ='Aug 2026'!D9 | E10: ='Aug 2026'!H8 | F10: ='Aug 2026'!D64 | G10: ='Aug 2026'!D54 | H10: ='Aug 2026'!D53 | I10: ='Aug 2026'!D65 | J10: ='Aug 2026'!F53
B11: Sep 2026 | C11: ='Sep 2026'!D6+'Sep 2026'!H6 | D11: ='Sep 2026'!D9 | E11: ='Sep 2026'!H8 | F11: ='Sep 2026'!D64 | G11: ='Sep 2026'!D54 | H11: ='Sep 2026'!D53 | I11: ='Sep 2026'!D65 | J11: ='Sep 2026'!F53
B12: Oct 2026 | C12: ='Oct 2026'!D6+'Oct 2026'!H6 | D12: ='Oct 2026'!D9 | E12: ='Oct 2026'!H8 | F12: ='Oct 2026'!D64 | G12: ='Oct 2026'!D54 | H12: ='Oct 2026'!D53 | I12: ='Oct 2026'!D65 | J12: ='Oct 2026'!F53
B13: Nov 2026 | C13: ='Nov 2026'!D6+'Nov 2026'!H6 | D13: ='Nov 2026'!D9 | E13: ='Nov 2026'!H8 | F13: ='Nov 2026'!D64 | G13: ='Nov 2026'!D54 | H13: ='Nov 2026'!D53 | I13: ='Nov 2026'!D65 | J13: ='Nov 2026'!F53
B14: Dec 2026 | C14: ='Dec 2026'!D6+'Dec 2026'!H6 | D14: ='Dec 2026'!D9 | E14: ='Dec 2026'!H8 | F14: ='Dec 2026'!D64 | G14: ='Dec 2026'!D54 | H14: ='Dec 2026'!D53 | I14: ='Dec 2026'!D65 | J14: ='Dec 2026'!F53
B15: 2026 Total | C15: =SUM(C7:C14) | E15: =SUM(E7:E14) | F15: =SUM(F7:F14) | G15: =SUM(G7:G14) | H15: =SUM(H7:H14) | I15: =SUM(I7:I14) | J15: =MAX(J7:J14)
B17: ── 2027 (Full Year) ──
B18: Jan 2027 | C18: ='Jan 2027'!D6+'Jan 2027'!H6 | D18: ='Jan 2027'!D9 | E18: ='Jan 2027'!H8 | F18: ='Jan 2027'!D64 | G18: ='Jan 2027'!D54 | H18: ='Jan 2027'!D53 | I18: ='Jan 2027'!D65 | J18: ='Jan 2027'!F53
B19: Feb 2027 | C19: ='Feb 2027'!D6+'Feb 2027'!H6 | D19: ='Feb 2027'!D9 | E19: ='Feb 2027'!H8 | F19: ='Feb 2027'!D64 | G19: ='Feb 2027'!D54 | H19: ='Feb 2027'!D53 | I19: ='Feb 2027'!D65 | J19: ='Feb 2027'!F53
B20: Mar 2027 | C20: ='Mar 2027'!D6+'Mar 2027'!H6 | D20: ='Mar 2027'!D9 | E20: ='Mar 2027'!H8 | F20: ='Mar 2027'!D64 | G20: ='Mar 2027'!D54 | H20: ='Mar 2027'!D53 | I20: ='Mar 2027'!D65 | J20: ='Mar 2027'!F53
B21: Apr 2027 | C21: ='Apr 2027'!D6+'Apr 2027'!H6 | D21: ='Apr 2027'!D9 | E21: ='Apr 2027'!H8 | F21: ='Apr 2027'!D64 | G21: ='Apr 2027'!D54 | H21: ='Apr 2027'!D53 | I21: ='Apr 2027'!D65 | J21: ='Apr 2027'!F53
B22: May 2027 | C22: ='May 2027'!D6+'May 2027'!H6 | D22: ='May 2027'!D9 | E22: ='May 2027'!H8 | F22: ='May 2027'!D64 | G22: ='May 2027'!D54 | H22: ='May 2027'!D53 | I22: ='May 2027'!D65 | J22: ='May 2027'!F53
B23: Jun 2027 | C23: ='Jun 2027'!D6+'Jun 2027'!H6 | D23: ='Jun 2027'!D9 | E23: ='Jun 2027'!H8 | F23: ='Jun 2027'!D64 | G23: ='Jun 2027'!D54 | H23: ='Jun 2027'!D53 | I23: ='Jun 2027'!D65 | J23: ='Jun 2027'!F53
B24: Jul 2027 | C24: ='Jul 2027'!D6+'Jul 2027'!H6 | D24: ='Jul 2027'!D9 | E24: ='Jul 2027'!H8 | F24: ='Jul 2027'!D64 | G24: ='Jul 2027'!D54 | H24: ='Jul 2027'!D53 | I24: ='Jul 2027'!D65 | J24: ='Jul 2027'!F53
B25: Aug 2027 | C25: ='Aug 2027'!D6+'Aug 2027'!H6 | D25: ='Aug 2027'!D9 | E25: ='Aug 2027'!H8 | F25: ='Aug 2027'!D64 | G25: ='Aug 2027'!D54 | H25: ='Aug 2027'!D53 | I25: ='Aug 2027'!D65 | J25: ='Aug 2027'!F53
B26: Sep 2027 | C26: ='Sep 2027'!D6+'Sep 2027'!H6 | D26: ='Sep 2027'!D9 | E26: ='Sep 2027'!H8 | F26: ='Sep 2027'!D64 | G26: ='Sep 2027'!D54 | H26: ='Sep 2027'!D53 | I26: ='Sep 2027'!D65 | J26: ='Sep 2027'!F53
B27: Oct 2027 | C27: ='Oct 2027'!D6+'Oct 2027'!H6 | D27: ='Oct 2027'!D9 | E27: ='Oct 2027'!H8 | F27: ='Oct 2027'!D64 | G27: ='Oct 2027'!D54 | H27: ='Oct 2027'!D53 | I27: ='Oct 2027'!D65 | J27: ='Oct 2027'!F53
B28: Nov 2027 | C28: ='Nov 2027'!D6+'Nov 2027'!H6 | D28: ='Nov 2027'!D9 | E28: ='Nov 2027'!H8 | F28: ='Nov 2027'!D64 | G28: ='Nov 2027'!D54 | H28: ='Nov 2027'!D53 | I28: ='Nov 2027'!D65 | J28: ='Nov 2027'!F53
B29: Dec 2027 | C29: ='Dec 2027'!D6+'Dec 2027'!H6 | D29: ='Dec 2027'!D9 | E29: ='Dec 2027'!H8 | F29: ='Dec 2027'!D64 | G29: ='Dec 2027'!D54 | H29: ='Dec 2027'!D53 | I29: ='Dec 2027'!D65 | J29: ='Dec 2027'!F53
B30: 2027 Total | C30: =SUM(C18:C29) | E30: =SUM(E18:E29) | F30: =SUM(F18:F29) | G30: =SUM(G18:G29) | H30: =SUM(H18:H29) | I30: =SUM(I18:I29) | J30: =MAX(J18:J29)
B32: ── 2028 (Jan – Jun) ──
B33: Jan 2028 | C33: ='Jan 2028'!D6+'Jan 2028'!H6 | D33: ='Jan 2028'!D9 | E33: ='Jan 2028'!H8 | F33: ='Jan 2028'!D64 | G33: ='Jan 2028'!D54 | H33: ='Jan 2028'!D53 | I33: ='Jan 2028'!D65 | J33: ='Jan 2028'!F53
B34: Feb 2028 | C34: ='Feb 2028'!D6+'Feb 2028'!H6 | D34: ='Feb 2028'!D9 | E34: ='Feb 2028'!H8 | F34: ='Feb 2028'!D64 | G34: ='Feb 2028'!D54 | H34: ='Feb 2028'!D53 | I34: ='Feb 2028'!D65 | J34: ='Feb 2028'!F53
B35: Mar 2028 | C35: ='Mar 2028'!D6+'Mar 2028'!H6 | D35: ='Mar 2028'!D9 | E35: ='Mar 2028'!H8 | F35: ='Mar 2028'!D64 | G35: ='Mar 2028'!D54 | H35: ='Mar 2028'!D53 | I35: ='Mar 2028'!D65 | J35: ='Mar 2028'!F53
B36: Apr 2028 | C36: ='Apr 2028'!D6+'Apr 2028'!H6 | D36: ='Apr 2028'!D9 | E36: ='Apr 2028'!H8 | F36: ='Apr 2028'!D64 | G36: ='Apr 2028'!D54 | H36: ='Apr 2028'!D53 | I36: ='Apr 2028'!D65 | J36: ='Apr 2028'!F53
B37: May 2028 | C37: ='May 2028'!D6+'May 2028'!H6 | D37: ='May 2028'!D9 | E37: ='May 2028'!H8 | F37: ='May 2028'!D64 | G37: ='May 2028'!D54 | H37: ='May 2028'!D53 | I37: ='May 2028'!D65 | J37: ='May 2028'!F53
B38: Jun 2028 | C38: ='Jun 2028'!D6+'Jun 2028'!H6 | D38: ='Jun 2028'!D9 | E38: ='Jun 2028'!H8 | F38: ='Jun 2028'!D64 | G38: ='Jun 2028'!D54 | H38: ='Jun 2028'!D53 | I38: ='Jun 2028'!D65 | J38: ='Jun 2028'!F53
B39: 2028 Total | C39: =SUM(C33:C38) | E39: =SUM(E33:E38) | F39: =SUM(F33:F38) | G39: =SUM(G33:G38) | H39: =SUM(H33:H38) | I39: =SUM(I33:I38) | J39: =MAX(J33:J38)
B41: All-Years Grand Total | C41: =SUM(C5:C39) | E41: =SUM(E5:E39) | F41: =SUM(F5:F39) | G41: =SUM(G5:G39) | H41: =SUM(H5:H39) | I41: =SUM(I5:I39)

Sheet 📈 Projections 2026
B1: 📈 2026 Month-by-Month Comparison & Year-End Projection
B2: Actuals through current month · Remaining months = pre-planned expenses only · Year-end = Dec leftover
B3: Category / Metric | C3: May | D3: Jun | E3: Jul | F3: Aug | G3: Sep | H3: Oct | I3: Nov | J3: Dec | K3: Avg/Mo | L3: Year-End Proj | M3: Budget
B4: 📥 INCOME
B5: Paycheck Income (excl. carry-over) | C5: ='May 2026'!D6+'May 2026'!H6 -> 4167.35 | D5: ='Jun 2026'!D6+'Jun 2026'!H6 -> 3959.1 | E5: ='Jul 2026'!D6+'Jul 2026'!H6 -> 4270.42 | F5: ='Aug 2026'!D6+'Aug 2026'!H6 -> 5000 | G5: ='Sep 2026'!D6+'Sep 2026'!H6 -> 5000 | H5: ='Oct 2026'!D6+'Oct 2026'!H6 -> 5000 | I5: ='Nov 2026'!D6+'Nov 2026'!H6 -> 5000 | J5: ='Dec 2026'!D6+'Dec 2026'!H6 -> 5000 | K5: =IFERROR(AVERAGEIF(C5:J5,">0"),0) -> 4674.6088 | L5: =SUM(C5:J5) -> 37396.87
B6: Carry-Over from Prior Month | C6: ='May 2026'!D9 -> 109.97 | D6: ='Jun 2026'!D9 -> 153.26 | E6: ='Jul 2026'!D9 -> 1989.775 | F6: ='Aug 2026'!D9 -> 4823.25 | G6: ='Sep 2026'!D9 -> 8202.305 | H6: ='Oct 2026'!D9 -> 11835.36 | I6: ='Nov 2026'!D9 -> 15383.415 | J6: ='Dec 2026'!D9 -> 19016.47 | K6: =IFERROR(AVERAGEIF(C6:J6,">0"),0) -> 7689.2256 | L6: =SUM(C6:J6) -> 61513.805
B7: Total Available (incl. carry-over) | C7: ='May 2026'!H8 -> 4277.32 | D7: ='Jun 2026'!H8 -> 4112.36 | E7: ='Jul 2026'!H8 -> 6260.195 | F7: ='Aug 2026'!H8 -> 9823.25 | G7: ='Sep 2026'!H8 -> 13202.305 | H7: ='Oct 2026'!H8 -> 16835.36 | I7: ='Nov 2026'!H8 -> 20383.415 | J7: ='Dec 2026'!H8 -> 24016.47 | K7: =IFERROR(AVERAGEIF(C7:J7,">0"),0) -> 12363.834 | L7: =SUM(C7:J7) -> 98910.675
B9: 🧾 SPENDING (YOUR SHARE)
B10: Groceries | C10: ='May 2026'!D12 -> 267.61 | D10: ='Jun 2026'!D12 -> 90.37 | E10: ='Jul 2026'!D12 -> 0 | F10: ='Aug 2026'!D12 -> 0 | G10: ='Sep 2026'!D12 -> 0 | H10: ='Oct 2026'!D12 -> 0 | I10: ='Nov 2026'!D12 -> 0 | J10: ='Dec 2026'!D12 -> 0 | K10: =IFERROR(AVERAGEIF(C10:J10,">0"),0) -> 178.99 | L10: =SUM(C10:J10) -> 357.98 | M10: ='Dec 2026'!D12 -> 0
B11: Utilities | C11: ='May 2026'!D13 -> 21.185 | D11: ='Jun 2026'!D13 -> 120.625 | E11: ='Jul 2026'!D13 -> 20.625 | F11: ='Aug 2026'!D13 -> 105.625 | G11: ='Sep 2026'!D13 -> 20.625 | H11: ='Oct 2026'!D13 -> 105.625 | I11: ='Nov 2026'!D13 -> 20.625 | J11: ='Dec 2026'!D13 -> 105.625 | K11: =IFERROR(AVERAGEIF(C11:J11,">0"),0) -> 65.07 | L11: =SUM(C11:J11) -> 520.56 | M11: ='Dec 2026'!D13 -> 105.625
B12: Gas / Transport | C12: ='May 2026'!D14 -> 232.935 | D12: ='Jun 2026'!D14 -> 81.27 | E12: ='Jul 2026'!D14 -> 65 | F12: ='Aug 2026'!D14 -> 65 | G12: ='Sep 2026'!D14 -> 65 | H12: ='Oct 2026'!D14 -> 65 | I12: ='Nov 2026'!D14 -> 65 | J12: ='Dec 2026'!D14 -> 65 | K12: =IFERROR(AVERAGEIF(C12:J12,">0"),0) -> 88.025625 | L12: =SUM(C12:J12) -> 704.205 | M12: ='Dec 2026'!D14 -> 65
B13: Dining / Takeout | C13: ='May 2026'!D15 -> 583.64 | D13: ='Jun 2026'!D15 -> 115.05 | E13: ='Jul 2026'!D15 -> 0 | F13: ='Aug 2026'!D15 -> 0 | G13: ='Sep 2026'!D15 -> 0 | H13: ='Oct 2026'!D15 -> 0 | I13: ='Nov 2026'!D15 -> 0 | J13: ='Dec 2026'!D15 -> 0 | K13: =IFERROR(AVERAGEIF(C13:J13,">0"),0) -> 349.345 | L13: =SUM(C13:J13) -> 698.69 | M13: ='Dec 2026'!D15 -> 0
B14: Entertainment | C14: ='May 2026'!D16 -> 117 | D14: ='Jun 2026'!D16 -> 0 | E14: ='Jul 2026'!D16 -> 0 | F14: ='Aug 2026'!D16 -> 0 | G14: ='Sep 2026'!D16 -> 0 | H14: ='Oct 2026'!D16 -> 0 | I14: ='Nov 2026'!D16 -> 0 | J14: ='Dec 2026'!D16 -> 0 | K14: =IFERROR(AVERAGEIF(C14:J14,">0"),0) -> 117 | L14: =SUM(C14:J14) -> 117 | M14: ='Dec 2026'!D16 -> 0
B15: Health | C15: ='May 2026'!D17 -> 189.5 | D15: ='Jun 2026'!D17 -> 13 | E15: ='Jul 2026'!D17 -> 105 | F15: ='Aug 2026'!D17 -> 105 | G15: ='Sep 2026'!D17 -> 105 | H15: ='Oct 2026'!D17 -> 105 | I15: ='Nov 2026'!D17 -> 105 | J15: ='Dec 2026'!D17 -> 105 | K15: =IFERROR(AVERAGEIF(C15:J15,">0"),0) -> 104.0625 | L15: =SUM(C15:J15) -> 832.5 | M15: ='Dec 2026'!D17 -> 105
B16: Shopping | C16: ='May 2026'!D18 -> 222.9125 | D16: ='Jun 2026'!D18 -> 0 | E16: ='Jul 2026'!D18 -> 0 | F16: ='Aug 2026'!D18 -> 0 | G16: ='Sep 2026'!D18 -> 0 | H16: ='Oct 2026'!D18 -> 0 | I16: ='Nov 2026'!D18 -> 0 | J16: ='Dec 2026'!D18 -> 0 | K16: =IFERROR(AVERAGEIF(C16:J16,">0"),0) -> 222.9125 | L16: =SUM(C16:J16) -> 222.9125 | M16: ='Dec 2026'!D18 -> 0
B17: Subscriptions | C17: ='May 2026'!D19 -> 71.57 | D17: ='Jun 2026'!D19 -> 71.57 | E17: ='Jul 2026'!D19 -> 65.62 | F17: ='Aug 2026'!D19 -> 65.62 | G17: ='Sep 2026'!D19 -> 65.62 | H17: ='Oct 2026'!D19 -> 65.62 | I17: ='Nov 2026'!D19 -> 65.62 | J17: ='Dec 2026'!D19 -> 65.62 | K17: =IFERROR(AVERAGEIF(C17:J17,">0"),0) -> 67.1075 | L17: =SUM(C17:J17) -> 536.86 | M17: ='Dec 2026'!D19 -> 65.62
B18: Cash | C18: ='May 2026'!D20 -> 140 | D18: ='Jun 2026'!D20 -> 0 | E18: ='Jul 2026'!D20 -> 0 | F18: ='Aug 2026'!D20 -> 0 | G18: ='Sep 2026'!D20 -> 0 | H18: ='Oct 2026'!D20 -> 0 | I18: ='Nov 2026'!D20 -> 0 | J18: ='Dec 2026'!D20 -> 0 | K18: =IFERROR(AVERAGEIF(C18:J18,">0"),0) -> 140 | L18: =SUM(C18:J18) -> 140 | M18: ='Dec 2026'!D20 -> 0
B19: Personal / Misc | C19: ='May 2026'!D21 -> 11.75 | D19: ='Jun 2026'!D21 -> 40 | E19: ='Jul 2026'!D21 -> 0 | F19: ='Aug 2026'!D21 -> 0 | G19: ='Sep 2026'!D21 -> 0 | H19: ='Oct 2026'!D21 -> 0 | I19: ='Nov 2026'!D21 -> 0 | J19: ='Dec 2026'!D21 -> 0 | K19: =IFERROR(AVERAGEIF(C19:J19,">0"),0) -> 25.875 | L19: =SUM(C19:J19) -> 51.75 | M19: ='Dec 2026'!D21 -> 0
B20: Other | C20: ='May 2026'!D22 -> 0 | D20: ='Jun 2026'!D22 -> 179.99 | E20: ='Jul 2026'!D22 -> 70 | F20: ='Aug 2026'!D22 -> 169 | G20: ='Sep 2026'!D22 -> 0 | H20: ='Oct 2026'!D22 -> 0 | I20: ='Nov 2026'!D22 -> 0 | J20: ='Dec 2026'!D22 -> 0 | K20: =IFERROR(AVERAGEIF(C20:J20,">0"),0) -> 139.66333 | L20: =SUM(C20:J20) -> 418.99 | M20: ='Dec 2026'!D22 -> 0
B21: Travel | C21: ='May 2026'!D23 -> 334.69 | D21: ='Jun 2026'!D23 -> 0 | E21: ='Jul 2026'!D23 -> 0 | F21: ='Aug 2026'!D23 -> 0 | G21: ='Sep 2026'!D23 -> 0 | H21: ='Oct 2026'!D23 -> 0 | I21: ='Nov 2026'!D23 -> 0 | J21: ='Dec 2026'!D23 -> 0 | K21: =IFERROR(AVERAGEIF(C21:J21,">0"),0) -> 334.69 | L21: =SUM(C21:J21) -> 334.69 | M21: ='Dec 2026'!D23 -> 0
B22: Investment (excl. Ally) | C22: ='May 2026'!D61 -> 867.78 | D22: ='Jun 2026'!D60 -> 1013.285 | E22: ='Jul 2026'!D60 -> 1090.075 | F22: ='Aug 2026'!D60 -> 1175.075 | G22: ='Sep 2026'!D60 -> 1090.075 | H22: ='Oct 2026'!D60 -> 1175.075 | I22: ='Nov 2026'!D60 -> 1090.075 | J22: ='Dec 2026'!D60 -> 1175.075 | K22: =SUM(C22:J22) -> 8676.515 | L22: =IFERROR(AVERAGEIF(C22:J22,">0"),0) -> 1084.5644 | M22: ='Dec 2026'!D61
B23: TOTAL GOING OUT | C23: ='May 2026'!D63 -> 800 | D23: ='Jun 2026'!D63 -> 300 | E23: ='Jul 2026'!D63 -> 0 | F23: ='Aug 2026'!D63 -> 0 | G23: ='Sep 2026'!D63 -> 0 | H23: ='Oct 2026'!D63 -> 0 | I23: ='Nov 2026'!D63 -> 0 | J23: ='Dec 2026'!D63 -> 0 | K23: =IFERROR(AVERAGEIF(C23:J23,">0"),0) -> 550 | L23: =SUM(C23:J23) -> 1100 | M23: ='Dec 2026'!D63 -> 0
B24: 💵 MONEY LEFT OVER | C24: ='May 2026'!D65 -> 153.26 | D24: ='Jun 2026'!D65 -> 1989.775 | E24: ='Jul 2026'!D65 -> 4823.25 | F24: ='Aug 2026'!D65 -> 8202.305 | G24: ='Sep 2026'!D65 -> 11835.36 | H24: ='Oct 2026'!D65 -> 15383.415 | I24: ='Nov 2026'!D65 -> 19016.47 | J24: ='Dec 2026'!D65 -> 22564.525 | K24: =IFERROR(AVERAGEIF(C24:J24,">0"),0) -> 10496.045 | L24: =SUM(C24:J24) -> 83968.36 | M24: ='Dec 2026'!D64 -> 1451.945
C25: ='May 2026'!D65 -> 153.26 | D25: ='Jun 2026'!D65 -> 1989.775 | E25: ='Jul 2026'!D65 -> 4823.25 | F25: ='Aug 2026'!D65 -> 8202.305 | G25: ='Sep 2026'!D65 -> 11835.36 | H25: ='Oct 2026'!D65 -> 15383.415 | I25: ='Nov 2026'!D65 -> 19016.47 | J25: ='Dec 2026'!D65 -> 22564.525 | K25: =IFERROR(AVERAGEIF(C25:J25,">0"),0) -> 10496.045 | L25: =SUM(C25:J25) -> 83968.36 | M25: ='Dec 2026'!D65 -> 22564.525
B26: 💳 CREDIT CARD CHARGES
B27: CFF | C27: ='May 2026'!D30 -> 94.11 | D27: ='Jun 2026'!D30 -> 54.98 | E27: ='Jul 2026'!D30 -> 15.98 | F27: ='Aug 2026'!D30 -> 15.98 | G27: ='Sep 2026'!D30 -> 15.98 | H27: ='Oct 2026'!D30 -> 15.98 | I27: ='Nov 2026'!D30 -> 15.98 | J27: ='Dec 2026'!D30 -> 15.98 | K27: =IFERROR(AVERAGEIF(C27:J27,">0"),0) -> 30.62125 | L27: =IFERROR(AVERAGEIF(C27:J27,">0"),0) -> 30.62125
B28: CFU | C28: ='May 2026'!D31 -> 0 | D28: ='Jun 2026'!D31 -> 0 | E28: ='Jul 2026'!D31 -> 0 | F28: ='Aug 2026'!D31 -> 0 | G28: ='Sep 2026'!D31 -> 0 | H28: ='Oct 2026'!D31 -> 0 | I28: ='Nov 2026'!D31 -> 0 | J28: ='Dec 2026'!D31 -> 0 | K28: =IFERROR(AVERAGEIF(C28:J28,">0"),0) -> 0 | L28: =IFERROR(AVERAGEIF(C28:J28,">0"),0) -> 0
B29: CSP | C29: ='May 2026'!D32 -> 0 | D29: ='Jun 2026'!D32 -> 0 | E29: ='Jul 2026'!D32 -> 0 | F29: ='Aug 2026'!D32 -> 0 | G29: ='Sep 2026'!D32 -> 0 | H29: ='Oct 2026'!D32 -> 0 | I29: ='Nov 2026'!D32 -> 0 | J29: ='Dec 2026'!D32 -> 0 | K29: =IFERROR(AVERAGEIF(C29:J29,">0"),0) -> 0 | L29: =IFERROR(AVERAGEIF(C29:J29,">0"),0) -> 0
B30: Discover | C30: ='May 2026'!D33 -> 736.26 | D30: ='Jun 2026'!D33 -> 77.35 | E30: ='Jul 2026'!D33 -> 41.25 | F30: ='Aug 2026'!D33 -> 41.25 | G30: ='Sep 2026'!D33 -> 41.25 | H30: ='Oct 2026'!D33 -> 41.25 | I30: ='Nov 2026'!D33 -> 41.25 | J30: ='Dec 2026'!D33 -> 41.25 | K30: =IFERROR(AVERAGEIF(C30:J30,">0"),0) -> 132.63875 | L30: =IFERROR(AVERAGEIF(C30:J30,">0"),0) -> 132.63875
B31: Citi | C31: ='May 2026'!D34 -> 178.04 | D31: ='Jun 2026'!D34 -> 32.54 | E31: ='Jul 2026'!D34 -> 0 | F31: ='Aug 2026'!D34 -> 0 | G31: ='Sep 2026'!D34 -> 0 | H31: ='Oct 2026'!D34 -> 0 | I31: ='Nov 2026'!D34 -> 0 | J31: ='Dec 2026'!D34 -> 0 | K31: =IFERROR(AVERAGEIF(C31:J31,">0"),0) -> 105.29 | L31: =IFERROR(AVERAGEIF(C31:J31,">0"),0) -> 105.29
B32: Capital One | C32: ='May 2026'!D35 -> 231.88 | D32: ='Jun 2026'!D35 -> 85.56 | E32: ='Jul 2026'!D35 -> 21.99 | F32: ='Aug 2026'!D35 -> 21.99 | G32: ='Sep 2026'!D35 -> 21.99 | H32: ='Oct 2026'!D35 -> 21.99 | I32: ='Nov 2026'!D35 -> 21.99 | J32: ='Dec 2026'!D35 -> 21.99 | K32: =IFERROR(AVERAGEIF(C32:J32,">0"),0) -> 56.1725 | L32: =IFERROR(AVERAGEIF(C32:J32,">0"),0) -> 56.1725
B33: WF | C33: ='May 2026'!D36 -> 11.75 | D33: ='Jun 2026'!D36 -> 0 | E33: ='Jul 2026'!D36 -> 0 | F33: ='Aug 2026'!D36 -> 0 | G33: ='Sep 2026'!D36 -> 0 | H33: ='Oct 2026'!D36 -> 0 | I33: ='Nov 2026'!D36 -> 0 | J33: ='Dec 2026'!D36 -> 0 | K33: =IFERROR(AVERAGEIF(C33:J33,">0"),0) -> 11.75 | L33: =IFERROR(AVERAGEIF(C33:J33,">0"),0) -> 11.75
B34: Amazon Card | C34: ='May 2026'!D37 -> 7.65 | D34: ='Jun 2026'!D37 -> 7.65 | E34: ='Jul 2026'!D37 -> 7.65 | F34: ='Aug 2026'!D37 -> 7.65 | G34: ='Sep 2026'!D37 -> 7.65 | H34: ='Oct 2026'!D37 -> 7.65 | I34: ='Nov 2026'!D37 -> 7.65 | J34: ='Dec 2026'!D37 -> 7.65 | K34: =IFERROR(AVERAGEIF(C34:J34,">0"),0) -> 7.65 | L34: =IFERROR(AVERAGEIF(C34:J34,">0"),0) -> 7.65
B35: Robinhood | C35: ='May 2026'!D38 -> 991.59 | D35: ='Jun 2026'!D38 -> 446.22 | E35: ='Jul 2026'!D38 -> 195 | F35: ='Aug 2026'!D38 -> 294 | G35: ='Sep 2026'!D38 -> 125 | H35: ='Oct 2026'!D38 -> 125 | I35: ='Nov 2026'!D38 -> 125 | J35: ='Dec 2026'!D38 -> 125 | K35: =IFERROR(AVERAGEIF(C35:J35,">0"),0) -> 303.35125 | L35: =IFERROR(AVERAGEIF(C35:J35,">0"),0) -> 303.35125
B36: Cash | C36: ='May 2026'!D39 -> 205 | D36: ='Jun 2026'!D39 -> 105 | E36: ='Jul 2026'!D39 -> 65 | F36: ='Aug 2026'!D39 -> 65 | G36: ='Sep 2026'!D39 -> 65 | H36: ='Oct 2026'!D39 -> 65 | I36: ='Nov 2026'!D39 -> 65 | J36: ='Dec 2026'!D39 -> 65 | K36: =IFERROR(AVERAGEIF(C36:J36,">0"),0) -> 87.5 | L36: =IFERROR(AVERAGEIF(C36:J36,">0"),0) -> 87.5
B37: Other | C37: ='May 2026'!D40 -> 0 | D37: ='Jun 2026'!D40 -> 0 | E37: ='Jul 2026'!D40 -> 0 | F37: ='Aug 2026'!D40 -> 0 | G37: ='Sep 2026'!D40 -> 0 | H37: ='Oct 2026'!D40 -> 0 | I37: ='Nov 2026'!D40 -> 0 | J37: ='Dec 2026'!D40 -> 0 | K37: =IFERROR(AVERAGEIF(C37:J37,">0"),0) -> 0 | L37: =IFERROR(AVERAGEIF(C37:J37,">0"),0) -> 0
B38: TOTAL CC CHARGES | C38: ='May 2026'!D41 -> 2456.28 | D38: ='Jun 2026'!D41 -> 809.3 | E38: ='Jul 2026'!D41 -> 346.87 | F38: ='Aug 2026'!D41 -> 445.87 | G38: ='Sep 2026'!D41 -> 276.87 | H38: ='Oct 2026'!D41 -> 276.87 | I38: ='Nov 2026'!D41 -> 276.87 | J38: ='Dec 2026'!D41 -> 276.87 | K38: =SUM(C38:J38) -> 5165.8 | L38: =IFERROR(AVERAGEIF(C38:J38,">0"),0) -> 645.725
B40: 📈 INVESTMENTS & SAVINGS
B41: Robinhood — Added | C41: ='May 2026'!D45 -> 300 | D41: ='Jun 2026'!D45 -> 300 | E41: ='Jul 2026'!D45 -> 0 | F41: ='Aug 2026'!D45 -> 0 | G41: ='Sep 2026'!D45 -> 0 | H41: ='Oct 2026'!D45 -> 0 | I41: ='Nov 2026'!D45 -> 0 | J41: ='Dec 2026'!D45 -> 0 | K41: =IFERROR(AVERAGEIF(C41:J41,">0"),0) -> 300 | L41: =IFERROR(AVERAGEIF(C41:J41,">0"),0) -> 300
B42: Vanguard IRA — Added | C42: ='May 2026'!D46 -> 500 | D42: ='Jun 2026'!D46 -> 0 | E42: ='Jul 2026'!D46 -> 0 | F42: ='Aug 2026'!D46 -> 0 | G42: ='Sep 2026'!D46 -> 0 | H42: ='Oct 2026'!D46 -> 0 | I42: ='Nov 2026'!D46 -> 0 | J42: ='Dec 2026'!D46 -> 0 | K42: =IFERROR(AVERAGEIF(C42:J42,">0"),0) -> 500 | L42: =IFERROR(AVERAGEIF(C42:J42,">0"),0) -> 500
B43: Ally Wants — Added | C43: ='May 2026'!D49 -> 120 | D43: ='Jun 2026'!D49 -> 120 | E43: ='Jul 2026'!D49 -> 120 | F43: ='Aug 2026'!D49 -> 120 | G43: ='Sep 2026'!D49 -> 120 | H43: ='Oct 2026'!D49 -> 120 | I43: ='Nov 2026'!D49 -> 120 | J43: ='Dec 2026'!D49 -> 120 | K43: =IFERROR(AVERAGEIF(C43:J43,">0"),0) -> 120 | L43: =IFERROR(AVERAGEIF(C43:J43,">0"),0) -> 120
B44: Ally Vacation — Added | C44: ='May 2026'!D50 -> 200 | D44: ='Jun 2026'!D50 -> 200 | E44: ='Jul 2026'!D50 -> 200 | F44: ='Aug 2026'!D50 -> 200 | G44: ='Sep 2026'!D50 -> 200 | H44: ='Oct 2026'!D50 -> 200 | I44: ='Nov 2026'!D50 -> 200 | J44: ='Dec 2026'!D50 -> 200 | K44: =IFERROR(AVERAGEIF(C44:J44,">0"),0) -> 200 | L44: =IFERROR(AVERAGEIF(C44:J44,">0"),0) -> 200
B45: Ally Car Fund — Added | C45: ='May 2026'!D51 -> 400 | D45: ='Jun 2026'!D51 -> 400 | E45: ='Jul 2026'!D51 -> 400 | F45: ='Aug 2026'!D51 -> 400 | G45: ='Sep 2026'!D51 -> 400 | H45: ='Oct 2026'!D51 -> 400 | I45: ='Nov 2026'!D51 -> 400 | J45: ='Dec 2026'!D51 -> 400 | K45: =IFERROR(AVERAGEIF(C45:J45,">0"),0) -> 400 | L45: =IFERROR(AVERAGEIF(C45:J45,">0"),0) -> 400
B46: Ally Emergency — Added | C46: ='May 2026'!D52 -> 140 | D46: ='Jun 2026'!D52 -> 140 | E46: ='Jul 2026'!D52 -> 140 | F46: ='Aug 2026'!D52 -> 140 | G46: ='Sep 2026'!D52 -> 140 | H46: ='Oct 2026'!D52 -> 140 | I46: ='Nov 2026'!D52 -> 140 | J46: ='Dec 2026'!D52 -> 140 | K46: =IFERROR(AVERAGEIF(C46:J46,">0"),0) -> 140 | L46: =IFERROR(AVERAGEIF(C46:J46,">0"),0) -> 140
B47: Wants Balance | C47: ='May 2026'!F49 -> 3600 | D47: ='Jun 2026'!F49 -> 3720 | E47: ='Jul 2026'!F49 -> 3840 | F47: ='Aug 2026'!F49 -> 3960 | G47: ='Sep 2026'!F49 -> 4080 | H47: ='Oct 2026'!F49 -> 4200 | I47: ='Nov 2026'!F49 -> 4320 | J47: ='Dec 2026'!F49 -> 4440 | K47: =IFERROR(AVERAGEIF(C47:J47,">0"),0) -> 4020 | L47: =IFERROR(MAX(C47:J47),0) -> 4440
B48: Vacation Balance | C48: ='May 2026'!F50 -> 7650 | D48: ='Jun 2026'!F50 -> 7850 | E48: ='Jul 2026'!F50 -> 8050 | F48: ='Aug 2026'!F50 -> 8250 | G48: ='Sep 2026'!F50 -> 8450 | H48: ='Oct 2026'!F50 -> 8650 | I48: ='Nov 2026'!F50 -> 8850 | J48: ='Dec 2026'!F50 -> 9050 | K48: =IFERROR(AVERAGEIF(C48:J48,">0"),0) -> 8350 | L48: =IFERROR(MAX(C48:J48),0) -> 9050
B49: Car Fund Balance | C49: ='May 2026'!F51 -> 10000 | D49: ='Jun 2026'!F51 -> 10400 | E49: ='Jul 2026'!F51 -> 10800 | F49: ='Aug 2026'!F51 -> 11200 | G49: ='Sep 2026'!F51 -> 11600 | H49: ='Oct 2026'!F51 -> 12000 | I49: ='Nov 2026'!F51 -> 12400 | J49: ='Dec 2026'!F51 -> 12800 | K49: =IFERROR(AVERAGEIF(C49:J49,">0"),0) -> 11400 | L49: =IFERROR(MAX(C49:J49),0) -> 12800
B50: Emergency Fund Balance | C50: ='May 2026'!F52 -> 6186.75 | D50: ='Jun 2026'!F52 -> 6326.75 | E50: ='Jul 2026'!F52 -> 6466.75 | F50: ='Aug 2026'!F52 -> 6606.75 | G50: ='Sep 2026'!F52 -> 6746.75 | H50: ='Oct 2026'!F52 -> 6886.75 | I50: ='Nov 2026'!F52 -> 7026.75 | J50: ='Dec 2026'!F52 -> 7166.75 | K50: =IFERROR(AVERAGEIF(C50:J50,">0"),0) -> 6676.75 | L50: =IFERROR(MAX(C50:J50),0) -> 7166.75
B51: Ally Total Balance | C51: ='May 2026'!F53 -> 27436.75 | D51: ='Jun 2026'!F53 -> 28296.75 | E51: ='Jul 2026'!F53 -> 29156.75 | F51: ='Aug 2026'!F53 -> 30016.75 | G51: ='Sep 2026'!F53 -> 30876.75 | H51: ='Oct 2026'!F53 -> 31736.75 | I51: ='Nov 2026'!F53 -> 32596.75 | J51: ='Dec 2026'!F53 -> 33456.75 | K51: =IFERROR(AVERAGEIF(C51:J51,">0"),0) -> 30446.75 | L51: =IFERROR(MAX(C51:J51),0) -> 33456.75
B53: 🎯 BUDGET vs ACTUAL (YOUR SHARE)
B54: Set monthly budget targets in each month tab (col F of Category Summary). Negative = over budget.
B55: Groceries — vs Budget | C55: ='May 2026'!D12-'May 2026'!F12 -> -32.39 | D55: ='Jun 2026'!D12-'May 2026'!F12 -> -209.63 | E55: ='Jul 2026'!D12-'May 2026'!F12 -> -300 | F55: ='Aug 2026'!D12-'May 2026'!F12 -> -300 | G55: ='Sep 2026'!D12-'May 2026'!F12 -> -300 | H55: ='Oct 2026'!D12-'May 2026'!F12 -> -300 | I55: ='Nov 2026'!D12-'May 2026'!F12 -> -300 | J55: ='Dec 2026'!D12-'May 2026'!F12 -> -300 | K55: =AVERAGEIF(C55:J55,"<>0") -> -255.2525 | L55: =SUM(C55:J55) -> -2042.02 | M55: ='May 2026'!F12 -> 300
B56: Utilities — vs Budget | C56: ='May 2026'!D13-'May 2026'!F13 -> -28.815 | D56: ='Jun 2026'!D13-'May 2026'!F13 -> 70.625 | E56: ='Jul 2026'!D13-'May 2026'!F13 -> -29.375 | F56: ='Aug 2026'!D13-'May 2026'!F13 -> 55.625 | G56: ='Sep 2026'!D13-'May 2026'!F13 -> -29.375 | H56: ='Oct 2026'!D13-'May 2026'!F13 -> 55.625 | I56: ='Nov 2026'!D13-'May 2026'!F13 -> -29.375 | J56: ='Dec 2026'!D13-'May 2026'!F13 -> 55.625 | K56: =AVERAGEIF(C56:J56,"<>0") -> 15.07 | L56: =SUM(C56:J56) -> 120.56 | M56: ='May 2026'!F13 -> 50
B57: Gas / Transport — vs Budget | C57: ='May 2026'!D14-'May 2026'!F14 -> -17.065 | D57: ='Jun 2026'!D14-'May 2026'!F14 -> -168.73 | E57: ='Jul 2026'!D14-'May 2026'!F14 -> -185 | F57: ='Aug 2026'!D14-'May 2026'!F14 -> -185 | G57: ='Sep 2026'!D14-'May 2026'!F14 -> -185 | H57: ='Oct 2026'!D14-'May 2026'!F14 -> -185 | I57: ='Nov 2026'!D14-'May 2026'!F14 -> -185 | J57: ='Dec 2026'!D14-'May 2026'!F14 -> -185 | K57: =AVERAGEIF(C57:J57,"<>0") -> -161.97438 | L57: =SUM(C57:J57) -> -1295.795 | M57: ='May 2026'!F14 -> 250
B58: Dining / Takeout — vs Budget | C58: ='May 2026'!D15-'May 2026'!F15 -> 283.64 | D58: ='Jun 2026'!D15-'May 2026'!F15 -> -184.95 | E58: ='Jul 2026'!D15-'May 2026'!F15 -> -300 | F58: ='Aug 2026'!D15-'May 2026'!F15 -> -300 | G58: ='Sep 2026'!D15-'May 2026'!F15 -> -300 | H58: ='Oct 2026'!D15-'May 2026'!F15 -> -300 | I58: ='Nov 2026'!D15-'May 2026'!F15 -> -300 | J58: ='Dec 2026'!D15-'May 2026'!F15 -> -300 | K58: =AVERAGEIF(C58:J58,"<>0") -> -212.66375 | L58: =SUM(C58:J58) -> -1701.31 | M58: ='May 2026'!F15 -> 300
B59: Entertainment — vs Budget | C59: ='May 2026'!D16-'May 2026'!F16 -> -33 | D59: ='Jun 2026'!D16-'May 2026'!F16 -> -150 | E59: ='Jul 2026'!D16-'May 2026'!F16 -> -150 | F59: ='Aug 2026'!D16-'May 2026'!F16 -> -150 | G59: ='Sep 2026'!D16-'May 2026'!F16 -> -150 | H59: ='Oct 2026'!D16-'May 2026'!F16 -> -150 | I59: ='Nov 2026'!D16-'May 2026'!F16 -> -150 | J59: ='Dec 2026'!D16-'May 2026'!F16 -> -150 | K59: =AVERAGEIF(C59:J59,"<>0") -> -135.375 | L59: =SUM(C59:J59) -> -1083 | M59: ='May 2026'!F16 -> 150
B60: Health — vs Budget | C60: ='May 2026'!D17-'May 2026'!F17 -> -10.5 | D60: ='Jun 2026'!D17-'May 2026'!F17 -> -187 | E60: ='Jul 2026'!D17-'May 2026'!F17 -> -95 | F60: ='Aug 2026'!D17-'May 2026'!F17 -> -95 | G60: ='Sep 2026'!D17-'May 2026'!F17 -> -95 | H60: ='Oct 2026'!D17-'May 2026'!F17 -> -95 | I60: ='Nov 2026'!D17-'May 2026'!F17 -> -95 | J60: ='Dec 2026'!D17-'May 2026'!F17 -> -95 | K60: =AVERAGEIF(C60:J60,"<>0") -> -95.9375 | L60: =SUM(C60:J60) -> -767.5 | M60: ='May 2026'!F17 -> 200
B61: Shopping — vs Budget | C61: ='May 2026'!D18-'May 2026'!F18 -> 22.9125 | D61: ='Jun 2026'!D18-'May 2026'!F18 -> -200 | E61: ='Jul 2026'!D18-'May 2026'!F18 -> -200 | F61: ='Aug 2026'!D18-'May 2026'!F18 -> -200 | G61: ='Sep 2026'!D18-'May 2026'!F18 -> -200 | H61: ='Oct 2026'!D18-'May 2026'!F18 -> -200 | I61: ='Nov 2026'!D18-'May 2026'!F18 -> -200 | J61: ='Dec 2026'!D18-'May 2026'!F18 -> -200 | K61: =AVERAGEIF(C61:J61,"<>0") -> -172.13594 | L61: =SUM(C61:J61) -> -1377.0875 | M61: ='May 2026'!F18 -> 200
B62: Subscriptions — vs Budget | C62: ='May 2026'!D19-'May 2026'!F19 -> -28.43 | D62: ='Jun 2026'!D19-'May 2026'!F19 -> -28.43 | E62: ='Jul 2026'!D19-'May 2026'!F19 -> -34.38 | F62: ='Aug 2026'!D19-'May 2026'!F19 -> -34.38 | G62: ='Sep 2026'!D19-'May 2026'!F19 -> -34.38 | H62: ='Oct 2026'!D19-'May 2026'!F19 -> -34.38 | I62: ='Nov 2026'!D19-'May 2026'!F19 -> -34.38 | J62: ='Dec 2026'!D19-'May 2026'!F19 -> -34.38 | K62: =AVERAGEIF(C62:J62,"<>0") -> -32.8925 | L62: =SUM(C62:J62) -> -263.14 | M62: ='May 2026'!F19 -> 100
B63: Cash — vs Budget | C63: ='May 2026'!D20-'May 2026'!F20 -> -10 | D63: ='Jun 2026'!D20-'May 2026'!F20 -> -150 | E63: ='Jul 2026'!D20-'May 2026'!F20 -> -150 | F63: ='Aug 2026'!D20-'May 2026'!F20 -> -150 | G63: ='Sep 2026'!D20-'May 2026'!F20 -> -150 | H63: ='Oct 2026'!D20-'May 2026'!F20 -> -150 | I63: ='Nov 2026'!D20-'May 2026'!F20 -> -150 | J63: ='Dec 2026'!D20-'May 2026'!F20 -> -150 | K63: =AVERAGEIF(C63:J63,"<>0") -> -132.5 | L63: =SUM(C63:J63) -> -1060 | M63: ='May 2026'!F20 -> 150
B64: Personal / Misc — vs Budget | C64: ='May 2026'!D21-'May 2026'!F21 -> -38.25 | D64: ='Jun 2026'!D21-'May 2026'!F21 -> -10 | E64: ='Jul 2026'!D21-'May 2026'!F21 -> -50 | F64: ='Aug 2026'!D21-'May 2026'!F21 -> -50 | G64: ='Sep 2026'!D21-'May 2026'!F21 -> -50 | H64: ='Oct 2026'!D21-'May 2026'!F21 -> -50 | I64: ='Nov 2026'!D21-'May 2026'!F21 -> -50 | J64: ='Dec 2026'!D21-'May 2026'!F21 -> -50 | K64: =AVERAGEIF(C64:J64,"<>0") -> -43.53125 | L64: =SUM(C64:J64) -> -348.25 | M64: ='May 2026'!F21 -> 50
B65: Other — vs Budget | C65: ='May 2026'!D22-'May 2026'!F22 -> -350 | D65: ='Jun 2026'!D22-'May 2026'!F22 -> -170.01 | E65: ='Jul 2026'!D22-'May 2026'!F22 -> -280 | F65: ='Aug 2026'!D22-'May 2026'!F22 -> -181 | G65: ='Sep 2026'!D22-'May 2026'!F22 -> -350 | H65: ='Oct 2026'!D22-'May 2026'!F22 -> -350 | I65: ='Nov 2026'!D22-'May 2026'!F22 -> -350 | J65: ='Dec 2026'!D22-'May 2026'!F22 -> -350 | K65: =AVERAGEIF(C65:J65,"<>0") -> -297.62625 | L65: =SUM(C65:J65) -> -2381.01 | M65: ='May 2026'!F22 -> 350

Sheet May 2026
B2: 💰 May 2026 — Expense Tracker
B3: LEFT: summaries auto-update | RIGHT: log every transaction | Blue cells = enter data
B5: ⚙️ SETTINGS
B6: Paycheck #1 (mid-mo) | D6: 2135.21 | F6: Paycheck #2 (end-mo) | H6: 2032.14
B7: Full Monthly Rent | D7: 2221.4 | F7: Your Rent Split % | H7: 0.5
B8: Monthly Savings Goal | D8: 500 | F8: Total Monthly Income | H8: =D6+H6+D9 -> 4277.32
B9: Carried Over (prior month) | D9: 109.97
B10: 📊 CATEGORY SUMMARY | J10: 📋 EXPENSE LOG — Enter every transaction here
B11: Category | D11: Your Share $ | E11: % Income | F11: Budget $ | G11: vs Budget | J11: # | K11: Date | L11: Description | M11: Category | N11: Credit Card | O11: Total $ | P11: Split % | Q11: Your Share $ | R11: Notes / Memo | S11: Recurring?
B12: Groceries | D12: =SUMIF(M12:M131,B12,Q12:Q131) -> 267.61 | E12: =IFERROR(D12/(H8),0) -> 0.062564877 | F12: 300 | G12: =IF(D12=0,"",D12-F12) -> -32.39 | J12: 1 | K12: 46143 | L12: Car Insurance | M12: Gas / Transport | N12: Cash | O12: 65 | P12: 1 | Q12: =IFERROR(IF(O12="",0,O12*P12),0) -> 65 | R12: Auto-pay | S12: Y
B13: Utilities | D13: =SUMIF(M12:M131,B13,Q12:Q131) -> 21.185 | E13: =IFERROR(D13/(H8),0) -> 0.0049528677 | F13: 50 | G13: =IF(D13=0,"",D13-F13) -> -28.815 | J13: 2 | K13: 46143 | L13: Stronghold | M13: Health | N13: Robinhood | O13: 105 | P13: 1 | Q13: =IFERROR(IF(O13="",0,O13*P13),0) -> 105 | R13: Auto-pay | S13: Y
B14: Gas / Transport | D14: =SUMIF(M12:M131,B14,Q12:Q131) -> 232.935 | E14: =IFERROR(D14/(H8),0) -> 0.054458165 | F14: 250 | G14: =IF(D14=0,"",D14-F14) -> -17.065 | J14: 3 | K14: 46143 | L14: Spectrum Internet | M14: Utilities | N14: Discover | O14: 41.25 | P14: 0.5 | Q14: =IFERROR(IF(O14="",0,O14*P14),0) -> 20.625 | R14: Auto-pay | S14: Y
B15: Dining / Takeout | D15: =SUMIF(M12:M131,B15,Q12:Q131) -> 583.64 | E15: =IFERROR(D15/(H8),0) -> 0.13644993 | F15: 300 | G15: =IF(D15=0,"",D15-F15) -> 283.64 | J15: 4 | K15: 46143 | L15: Amazon Prime | M15: Subscriptions | N15: Amazon Card | O15: 7.65 | P15: 1 | Q15: =IFERROR(IF(O15="",0,O15*P15),0) -> 7.65 | R15: Auto-pay | S15: Y
B16: Entertainment | D16: =SUMIF(M12:M131,B16,Q12:Q131) -> 117 | E16: =IFERROR(D16/(H8),0) -> 0.027353577 | F16: 150 | G16: =IF(D16=0,"",D16-F16) -> -33 | J16: 5 | K16: 46143 | L16: Spotify | M16: Subscriptions | N16: Capital One | O16: 21.99 | P16: 1 | Q16: =IFERROR(IF(O16="",0,O16*P16),0) -> 21.99 | R16: Auto-pay | S16: Y
B17: Health | D17: =SUMIF(M12:M131,B17,Q12:Q131) -> 189.5 | E17: =IFERROR(D17/(H8),0) -> 0.044303442 | F17: 200 | G17: =IF(D17=0,"",D17-F17) -> -10.5 | J17: 6 | K17: 46143 | L17: Electricity | M17: Utilities | P17: 0.5 | Q17: =IFERROR(IF(O17="",0,O17*P17),0) -> 0 | R17: She pays | S17: Y
B18: Shopping | D18: =SUMIF(M12:M131,B18,Q12:Q131) -> 222.9125 | E18: =IFERROR(D18/(H8),0) -> 0.052114993 | F18: 200 | G18: =IF(D18=0,"",D18-F18) -> 22.9125 | J18: 7 | K18: 46143 | L18: Twitch Sub | M18: Subscriptions | N18: CFF | O18: 5.99 | P18: 1 | Q18: =IFERROR(IF(O18="",0,O18*P18),0) -> 5.99 | R18: Auto-pay | S18: Y
B19: Subscriptions | D19: =SUMIF(M12:M131,B19,Q12:Q131) -> 71.57 | E19: =IFERROR(D19/(H8),0) -> 0.01673244 | F19: 100 | G19: =IF(D19=0,"",D19-F19) -> -28.43 | J19: 8 | K19: 46143 | L19: Claude AI | M19: Subscriptions | N19: Robinhood | O19: 20 | P19: 1 | Q19: =IFERROR(IF(O19="",0,O19*P19),0) -> 20 | R19: Auto-pay | S19: Y
B20: Cash | D20: =SUMIF(M12:M131,B20,Q12:Q131) -> 140 | E20: =IFERROR(D20/(H8),0) -> 0.032730775 | F20: 150 | G20: =IF(D20=0,"",D20-F20) -> -10 | J20: 9 | K20: 46143 | L20: Discord | M20: Subscriptions | N20: CFF | O20: 9.99 | P20: 1 | Q20: =IFERROR(IF(O20="",0,O20*P20),0) -> 9.99 | R20: Auto-pay | S20: Y
B21: Personal / Misc | D21: =SUMIF(M12:M131,B21,Q12:Q131) -> 11.75 | E21: =IFERROR(D21/(H8),0) -> 0.0027470472 | F21: 50 | G21: =IF(D21=0,"",D21-F21) -> -38.25 | J21: 10 | K21: 46143 | L21: Ervin Gas | M21: Gas / Transport | N21: Citi | O21: 65.59 | P21: 1 | Q21: =IFERROR(IF(O21="",0,O21*P21),0) -> 65.59
B22: Other | D22: =SUMIF(M12:M131,B22,Q12:Q131) -> 0 | E22: =IFERROR(D22/(H8),0) -> 0 | F22: 350 | G22: =IF(D22=0,"",D22-F22) | J22: 11 | K22: 46148 | L22: Sharon Gas | M22: Gas / Transport | N22: Citi | O22: 27.47 | P22: 0.5 | Q22: =IFERROR(IF(O22="",0,O22*P22),0) -> 13.735
B23: Travel | D23: =SUMIF($M$12:$M$131,B23,$Q$12:$Q$131) -> 334.69 | E23: =IFERROR(D23/(H8),0) -> 0.078247594 | F23: 150 | G23: =IF(D23=0,"",D23-F23) -> 184.69 | J23: 12 | K23: 46144 | L23: Ralphs 1 | M23: Groceries | N23: CFF | O23: 23.95 | P23: 0.5 | Q23: =IFERROR(IF(O23="",0,O23*P23),0) -> 11.975
B24: Adjusted Rent | D24: =D61 -> 867.78 | E24: =IFERROR(D24/(H8),0) -> 0.20287937 | J24: 13 | K24: 46144 | L24: Costco | M24: Groceries | N24: Robinhood | O24: 76.07 | P24: 0.5 | Q24: =IFERROR(IF(O24="",0,O24*P24),0) -> 38.035
B25: Investment | D25: =D63 -> 800 | E25: =IFERROR(D25/(H8),0) -> 0.187033 | J25: 14 | K25: 46148 | L25: Albertsons | M25: Groceries | N25: Capital One | O25: 15.26 | P25: 0.5 | Q25: =IFERROR(IF(O25="",0,O25*P25),0) -> 7.63
B26: TOTAL Going Out | D26: =D64 -> 4124.06 | E26: =IFERROR(D26/(H8),0) -> 0.96416915 | J26: 15 | K26: 46151 | L26: TJs | M26: Groceries | O26: 13.96 | P26: 0.5 | Q26: =IFERROR(IF(O26="",0,O26*P26),0) -> 6.98
B27: 💵 Money Left Over | D27: =D65 -> 153.26 | E27: =IFERROR(D27/(H8),0) -> 0.035830847 | J27: 16 | K27: 46154 | L27: Costco + Ralph's | M27: Groceries | N27: Robinhood | O27: 51.3 | P27: 0.5 | Q27: =IFERROR(IF(O27="",0,O27*P27),0) -> 25.65
J28: 17 | K28: 46154 | L28: Stater Bros | M28: Groceries | N28: Capital One | O28: 6.98 | P28: 0.5 | Q28: =IFERROR(IF(O28="",0,O28*P28),0) -> 3.49
B29: Card | D29: Total This Month $ | J29: 18 | K29: 46152 | L29: Jons | M29: Groceries | O29: 10.77 | P29: 0.5 | Q29: =IFERROR(IF(O29="",0,O29*P29),0) -> 5.385
B30: CFF | D30: =SUMIF(N12:N131,B30,O12:O131) -> 94.11 | J30: 19 | K30: 46154 | L30: Target | M30: Groceries | N30: Robinhood | O30: 13.81 | P30: 0.5 | Q30: =IFERROR(IF(O30="",0,O30*P30),0) -> 6.905
B31: CFU | D31: =SUMIF(N12:N131,B31,O12:O131) -> 0 | J31: 20 | K31: 46155 | L31: Grocery Outlet | M31: Groceries | N31: Capital One | O31: 9.25 | P31: 0.5 | Q31: =IFERROR(IF(O31="",0,O31*P31),0) -> 4.625
B32: CSP | D32: =SUMIF(N12:N131,B32,O12:O131) -> 0 | J32: 21 | K32: 46144 | L32: Tacos Ervin | M32: Dining / Takeout | N32: Discover | O32: 59.19 | P32: 0.5 | Q32: =IFERROR(IF(O32="",0,O32*P32),0) -> 29.595
B33: Discover | D33: =SUMIF(N12:N131,B33,O12:O131) -> 736.26 | J33: 22 | K33: 46144 | L33: Tacos and proof Sharon | M33: Dining / Takeout | O33: =(5+11.21+6+13) -> 35.21 | P33: 0.5 | Q33: =IFERROR(IF(O33="",0,O33*P33),0) -> 17.605
B34: Citi | D34: =SUMIF(N12:N131,B34,O12:O131) -> 178.04 | J34: 23 | K34: 46147 | L34: Izakaya | M34: Dining / Takeout | N34: Discover | O34: 100.32 | P34: 0.5 | Q34: =IFERROR(IF(O34="",0,O34*P34),0) -> 50.16
B35: Capital One | D35: =SUMIF(N12:N131,B35,O12:O131) -> 231.88 | J35: 24 | K35: 46149 | L35: Paris baguette | M35: Dining / Takeout | N35: Discover | O35: 12.8 | P35: 1 | Q35: =IFERROR(IF(O35="",0,O35*P35),0) -> 12.8
B36: WF | D36: =SUMIF(N12:N131,B36,O12:O131) -> 11.75 | J36: 25 | K36: 46150 | L36: Dominoes | M36: Dining / Takeout | N36: Discover | O36: 13.17 | P36: 0.5 | Q36: =IFERROR(IF(O36="",0,O36*P36),0) -> 6.585
B37: Amazon Card | D37: =SUMIF(N12:N131,B37,O12:O131) -> 7.65 | J37: 26 | K37: 46150 | L37: Chilis | M37: Dining / Takeout | N37: Discover | O37: 52 | P37: 0.5 | Q37: =IFERROR(IF(O37="",0,O37*P37),0) -> 26
B38: Robinhood | D38: =SUMIF(N12:N131,B38,O12:O131) -> 991.59 | J38: 27 | K38: 46151 | L38: Toontown market foods | M38: Dining / Takeout | N38: Discover | O38: 36.55 | P38: 0.5 | Q38: =IFERROR(IF(O38="",0,O38*P38),0) -> 18.275
B39: Cash | D39: =SUMIF(N12:N131,B39,O12:O131) -> 205 | J39: 28 | K39: 46151 | L39: Smoke queen | M39: Dining / Takeout | N39: Discover | O39: 107.87 | P39: 0.5 | Q39: =IFERROR(IF(O39="",0,O39*P39),0) -> 53.935
B40: Other | D40: =SUMIF(N12:N131,B40,O12:O131) -> 0 | J40: 29 | K40: 46152 | L40: Coffee Disney | M40: Dining / Takeout | N40: Discover | O40: 8.25 | P40: 1 | Q40: =IFERROR(IF(O40="",0,O40*P40),0) -> 8.25
B41: TOTAL CC CHARGES | D41: =SUM(D30:D40) -> 2456.28 | J41: 30 | K41: 46152 | L41: Sundae churros | M41: Dining / Takeout | N41: Discover | O41: 12.16 | P41: 0.5 | Q41: =IFERROR(IF(O41="",0,O41*P41),0) -> 6.08
J42: 31 | K42: 46152 | L42: Chicken Bao | M42: Dining / Takeout | O42: 16.15 | P42: 0.5 | Q42: =IFERROR(IF(O42="",0,O42*P42),0) -> 8.075
B43: 📈 INVESTMENTS | J43: 32 | K43: 46154 | L43: Canes | M43: Dining / Takeout | N43: Discover | O43: 15.02 | P43: 0.5 | Q43: =IFERROR(IF(O43="",0,O43*P43),0) -> 7.51
B44: Account | D44: Added This Month $ | F44: Invested $ | J44: 33 | K44: 46143 | L44: Roy Last day Turon | M44: Dining / Takeout | N44: Robinhood | O44: 52.11 | P44: 1 | Q44: =IFERROR(IF(O44="",0,O44*P44),0) -> 52.11
B45: Robinhood Brokerage | D45: 300 | F45: 0 | J45: 34 | K45: 46147 | L45: Oven Thermometer | M45: Shopping | N45: CFF | O45: 27.43 | P45: 1 | Q45: =IFERROR(IF(O45="",0,O45*P45),0) -> 27.43
B46: Vanguard IRA | D46: 500 | J46: 35 | K46: 46144 | L46: LA TACO | M46: Subscriptions | N46: Robinhood | O46: 5.95 | P46: 1 | Q46: =IFERROR(IF(O46="",0,O46*P46),0) -> 5.95
B47: 🏦 Ally Savings Buckets | J47: 36 | K47: 46147 | L47: Flowers | M47: Shopping | N47: Capital One | O47: 21.95 | P47: 1 | Q47: =IFERROR(IF(O47="",0,O47*P47),0) -> 21.95
B48: Bucket | D48: Added This Month $ | F48: Balance $ | J48: 37 | K48: 46144 | L48: Steam Games | M48: Shopping | N48: Robinhood | O48: 4.95 | P48: 1 | Q48: =IFERROR(IF(O48="",0,O48*P48),0) -> 4.95
B49: Wants | D49: 120 | F49: 3600 | J49: 38 | K49: 46149 | L49: Remote + Soap | M49: Shopping | N49: CFF | O49: 26.75 | P49: 0.79 | Q49: =IFERROR(IF(O49="",0,O49*P49),0) -> 21.1325
B50: Vacation | D50: 200 | F50: 7650 | J50: 39 | K50: 46153 | L50: Concert tickets | M50: Entertainment | O50: 234 | P50: 0.5 | Q50: =IFERROR(IF(O50="",0,O50*P50),0) -> 117
B51: Car Fund | D51: 400 | F51: 10000 | J51: 40 | K51: 46150 | L51: h18 | M51: Health | N51: Robinhood | O51: 22 | P51: 1 | Q51: =IFERROR(IF(O51="",0,O51*P51),0) -> 22
B52: Emergency Fund | D52: 140 | F52: =6116.51+70.24 -> 6186.75 | J52: 41 | K52: 46152 | L52: Disney parking | M52: Gas / Transport | O52: 40 | P52: 0.5 | Q52: =IFERROR(IF(O52="",0,O52*P52),0) -> 20
B53: Ally Total | D53: =SUM(D49:D52) -> 860 | F53: =SUM(F49:F52) -> 27436.75 | J53: 42 | K53: 46155 | L53: Work Jacket | M53: Shopping | N53: Robinhood | O53: 85.6 | P53: 1 | Q53: =IFERROR(IF(O53="",0,O53*P53),0) -> 85.6
B54: Total Invested (excl. Ally) | D54: =D45+D46 -> 800 | J54: 43 | K54: 46157 | L54: Albertsons | M54: Groceries | N54: Capital One | O54: 26.38 | P54: 0.5 | Q54: =IFERROR(IF(O54="",0,O54*P54),0) -> 13.19
J55: 44 | K55: 46157 | L55: In n out | M55: Dining / Takeout | O55: 19.54 | P55: 0.5 | Q55: =IFERROR(IF(O55="",0,O55*P55),0) -> 9.77
B56: 📈 MONTHLY SUMMARY | J56: 45 | K56: 46159 | L56: Lasita | M56: Dining / Takeout | N56: Discover | O56: 60.68 | P56: 0.5 | Q56: =O55*P55 -> 9.77
B57: Total Monthly Income | D57: =H8 -> 4277.32 | J57: 46 | K57: 46159 | L57: Vons | M57: Groceries | O57: 13.6 | P57: 0.5 | Q57: 6.8
B58: Your Base Rent Share | D58: =D7*H7 -> 1110.7 | J58: 47 | K58: 46160 | L58: USA Gas Ervin | M58: Gas / Transport | N58: Citi | O58: 52.23 | P58: 1 | Q58: 52.23
B59: You Covered (partner's share ↓ your rent) | D59: =SUMPRODUCT((N12:N131<>"")*O12:O131*(1-P12:P131)) -> 615.645 | J59: 48 | K59: 46160 | L59: Sinclair Gas Sharon | M59: Gas / Transport | N59: Citi | O59: 32.75 | P59: 0.5 | Q59: 16.38
J60: 49 | K60: 46158 | L60: Car Wash | M60: Personal / Misc | N60: WF | O60: 11.75 | P60: 1 | Q60: 11.75
B61: Your Rent After Adjustment | D61: =MAX(D7*H7-SUMPRODUCT((N12:N131<>"")*O12:O131*(1-P12:P131))+SUMPRODUCT((N12:N131="")*(O12:O131>0)*Q12:Q131),0) -> 867.78 | J61: 50 | K61: 46161 | L61: Student Loan Cash | M61: Cash | N61: Cash | O61: 100 | P61: 1 | Q61: 100
B62: Total CC Charges | D62: =D41 -> 2456.28 | J62: 51 | K62: 46161 | L62: Costco steak and stuff | M62: Groceries | N62: Robinhood | O62: 113.84 | P62: 0.5 | Q62: 56.92
B63: Total Invested (excl. Ally) | D63: =D45+D46 -> 800 | J63: 52 | K63: 46162 | L63: Little Tokyo market place | M63: Groceries | N63: Capital One | O63: 23.38 | P63: 0.5 | Q63: 11.69
B64: TOTAL GOING OUT | D64: =D61+D62+D63 -> 4124.06 | J64: 53 | K64: 46164 | L64: Gen KBBQ | M64: Dining / Takeout | O64: 44 | P64: 0.5 | Q64: 22
B65: 💵 MONEY LEFT OVER | D65: =H8-D64 -> 153.26 | J65: 54 | K65: 46164 | L65: Look Food + Parking | M65: Dining / Takeout | N65: Robinhood | O65: 11.43 | P65: 0.75 | Q65: 8.57
J66: 55 | K66: 46165 | L66: 5 punch LBR | M66: Health | O66: 125 | P66: 0.5 | Q66: 62.5
B67: 🔁 PARTNER BALANCE | J67: 56 | K67: 46165 | L67: Rakkan Ramen | M67: Dining / Takeout | O67: 84 | P67: 0.5 | Q67: 42
B68: Sharon Base Rent Share | D68: =D7*(1-H7) -> 1110.7 | J68: 57 | K68: 46165 | L68: Foodoligie | M68: Dining / Takeout | O68: 23 | P68: 0.35 | Q68: 8.05
B69: She Covered (your share ↑ her rent) | D69: =SUMPRODUCT((N12:N131="")*(O12:O131>0)*Q12:Q131) -> 372.725 | J69: 58 | K69: 46165 | L69: 2nd street | M69: Shopping | N69: Robinhood | O69: =26.41+1.1 -> 27.51 | P69: 1 | Q69: 27.51 | R69: Aritzia Sweat pants
B70: You Covered (partner's share ↓ your rent) | D70: =SUMPRODUCT((N12:N131<>"")*O12:O131*(1-P12:P131)) -> 615.645 | J70: 59 | K70: 46165 | L70: Steam | M70: Shopping | N70: Robinhood | O70: 19.99 | P70: 1 | Q70: 19.99 | R70: Far far west
B71: Sharon's Total Rent This Month | D71: =MAX(D7*(1-H7)+SUMPRODUCT((N12:N131<>"")*O12:O131*(1-P12:P131))-SUMPRODUCT((N12:N131="")*(O12:O131>0)*Q12:Q131),0) -> 1353.62 | J71: 60 | K71: 46166 | L71: TJs+Ralphs | M71: Groceries | N71: Capital One | O71: 34.32 | P71: 0.5 | Q71: 17.16
B72: You Owe Sharon (if she overpaid) | D72: =MAX(SUMPRODUCT((N12:N131="")*(O12:O131>0)*Q12:Q131)-D7*(1-H7),0) -> 0 | J72: 61 | K72: 46166 | L72: Kitsmet Rotisserie | M72: Dining / Takeout | N72: Discover | O72: 37 | P72: 0.5 | Q72: =IFERROR(IF(O72="",0,O72*P72),0) -> 18.5
J73: 62 | K73: 46167 | L73: Bao Master | M73: Dining / Takeout | O73: 82 | P73: 0.5 | Q73: 41
J74: 63 | K74: 46167 | L74: 99 Ranch+sprouts | M74: Groceries | N74: Capital One | O74: =42.16+9 -> 51.16 | P74: 0.5 | Q74: =IFERROR(IF(O74="",0,O74*P74),0) -> 25.58
J75: 64 | K75: 46166 | L75: Farmers Market | M75: Groceries | N75: Capital One | O75: 8 | P75: 1 | Q75: =IFERROR(IF(O75="",0,O75*P75),0) -> 8
J76: 65 | K76: 46168 | L76: Ralphs | M76: Groceries | N76: Capital One | O76: 13.21 | P76: 0.5 | Q76: =IFERROR(IF(O76="",0,O76*P76),0) -> 6.605
J77: 66 | K77: 46169 | L77: Stronghold food | M77: Dining / Takeout | O77: 5 | P77: 1 | Q77: =IFERROR(IF(O77="",0,O77*P77),0) -> 5
J78: 67 | K78: 46170 | L78: Chocolate milk | M78: Groceries | N78: Robinhood | O78: 10.99 | P78: 1 | Q78: 10.99
J79: 68 | K79: 46171 | L79: Foodologie | M79: Dining / Takeout | N79: Robinhood | O79: 22 | P79: 1 | Q79: 22
J80: 69 | K80: 46171 | L80: The game chest smiski | M80: Shopping | N80: Robinhood | O80: 14.35 | P80: 1 | Q80: 14.35
J81: 70 | K81: 46171 | L81: Cash | M81: Cash | N81: Cash | O81: 40 | P81: 1 | Q81: 40
J82: 71 | K82: 46171 | L82: Chubby cattle | M82: Dining / Takeout | N82: Discover | O82: 160 | P82: 0.5 | Q82: 80
J83: 72 | K83: 46172 | L83: Popeyes | M83: Dining / Takeout | N83: Discover | O83: 20 | P83: 1 | Q83: 20
J84: 73 | K84: 46173 | L84: Airbnb for October | M84: Travel | N84: Robinhood | O84: 334.69 | P84: 1 | Q84: =IFERROR(IF(O84="",0,O84*P84),0) -> 334.69
J85: 74 | K85: 46172 | L85: Gas bill | M85: Utilities | O85: 1.12 | P85: 0.5 | Q85: 0.56
J86: 75 | P86: 1 | Q86: =IFERROR(IF(O86="",0,O86*P86),0) -> 0
J87: 76 | P87: 1 | Q87: =IFERROR(IF(O87="",0,O87*P87),0) -> 0
J88: 77 | P88: 1 | Q88: =IFERROR(IF(O88="",0,O88*P88),0) -> 0
J89: 78 | P89: 1 | Q89: =IFERROR(IF(O89="",0,O89*P89),0) -> 0
J90: 79 | P90: 1 | Q90: =IFERROR(IF(O90="",0,O90*P90),0) -> 0
J91: 80 | P91: 1 | Q91: =IFERROR(IF(O91="",0,O91*P91),0) -> 0
J92: 81 | P92: 1 | Q92: =IFERROR(IF(O92="",0,O92*P92),0) -> 0
J93: 82 | P93: 1 | Q93: =IFERROR(IF(O93="",0,O93*P93),0) -> 0
J94: 83 | P94: 1 | Q94: =IFERROR(IF(O94="",0,O94*P94),0) -> 0
J95: 84 | P95: 1 | Q95: =IFERROR(IF(O95="",0,O95*P95),0) -> 0
J96: 85 | P96: 1 | Q96: =IFERROR(IF(O96="",0,O96*P96),0) -> 0
J97: 86 | P97: 1 | Q97: =IFERROR(IF(O97="",0,O97*P97),0) -> 0
... J130: 119 | P130: 1 | Q130: =IFERROR(IF(O130="",0,O130*P130),0) -> 0
J131: 120 | P131: 1 | Q131: =IFERROR(IF(O132="",0,O132*P132),0) -> 0
L132: LOG TOTALS | O132: =SUM(O12:O131) -> 3203.63 | Q132: =SUM(Q12:Q131) -> 2192.7925

Sheet Jun 2026
B2: 💰 Jun 2026 — Expense Tracker
B3: LEFT: summaries auto-update | RIGHT: log every transaction | Blue cells = enter data
B5: ⚙️ SETTINGS
B6: Paycheck #1 (mid-mo) | D6: 1926.96 | F6: Paycheck #2 (end-mo) | H6: 2032.14
B7: Full Monthly Rent | D7: 2221.4 | F7: Your Rent Split % | H7: 0.5
B8: Monthly Savings Goal | D8: 500 | F8: Total Monthly Income | H8: =D6+H6+D9 -> 4112.36
B9: Carried Over (prior month) | D9: ='May 2026'!D65 -> 153.26
B10: 📊 CATEGORY SUMMARY | J10: 📋 EXPENSE LOG — Enter every transaction here
B11: Category | D11: Your Share $ | E11: % Income | F11: Budget $ | G11: vs Budget | J11: # | K11: Date | L11: Description | M11: Category | N11: Credit Card | O11: Total $ | P11: Split % | Q11: Your Share $ | R11: Notes / Memo | S11: Recurring?
B12: Groceries | D12: =SUMIF(M12:M131,B12,Q12:Q131) -> 90.37 | E12: =IFERROR(D12/(H8),0) -> 0.021975216 | F12: 300 | G12: =IF(D12=0,"",D12-F12) -> -209.63 | J12: 1 | K12: 46174 | L12: Car Insurance | M12: Gas / Transport | N12: Cash | O12: 65 | P12: 1 | Q12: =IFERROR(IF(O12="",0,O12*P12),0) -> 65 | R12: Auto-pay | S12: Y
B13: Utilities | D13: =SUMIF(M12:M131,B13,Q12:Q131) -> 120.625 | E13: =IFERROR(D13/(H8),0) -> 0.029332306 | F13: 150 | G13: =IF(D13=0,"",D13-F13) -> -29.375 | J13: 2 | K13: 46174 | L13: Stronghold | M13: Health | N13: Robinhood | O13: 13 | P13: 1 | Q13: 13 | R13: Auto-pay
B14: Gas / Transport | D14: =SUMIF(M12:M131,B14,Q12:Q131) -> 81.27 | E14: =IFERROR(D14/(H8),0) -> 0.019762375 | F14: 200 | G14: =IF(D14=0,"",D14-F14) -> -118.73 | J14: 3 | K14: 46174 | L14: Spectrum Internet | M14: Utilities | N14: Discover | O14: 41.25 | P14: 0.5 | Q14: =IFERROR(IF(O14="",0,O14*P14),0) -> 20.625 | R14: Auto-pay | S14: Y
B15: Dining / Takeout | D15: =SUMIF(M12:M131,B15,Q12:Q131) -> 115.05 | E15: =IFERROR(D15/(H8),0) -> 0.027976636 | F15: 300 | G15: =IF(D15=0,"",D15-F15) -> -184.95 | J15: 4 | K15: 46174 | L15: Amazon Prime | M15: Subscriptions | N15: Amazon Card | O15: 7.65 | P15: 1 | Q15: =IFERROR(IF(O15="",0,O15*P15),0) -> 7.65 | R15: Auto-pay | S15: Y
B16: Entertainment | D16: =SUMIF(M12:M131,B16,Q12:Q131) -> 0 | E16: =IFERROR(D16/(H8),0) -> 0 | F16: 150 | G16: =IF(D16=0,"",D16-F16) | J16: 5 | K16: 46174 | L16: Spotify | M16: Subscriptions | N16: Capital One | O16: 21.99 | P16: 1 | Q16: =IFERROR(IF(O16="",0,O16*P16),0) -> 21.99 | R16: Auto-pay | S16: Y
B17: Health | D17: =SUMIF(M12:M131,B17,Q12:Q131) -> 13 | E17: =IFERROR(D17/(H8),0) -> 0.0031612018 | F17: 200 | G17: =IF(D17=0,"",D17-F17) -> -187 | J17: 6 | K17: 46174 | L17: Electricity | M17: Utilities | O17: 170 | P17: 0.5 | Q17: =IFERROR(IF(O17="",0,O17*P17),0) -> 85 | R17: She pays | S17: Y
B18: Shopping | D18: =SUMIF(M12:M131,B18,Q12:Q131) -> 0 | E18: =IFERROR(D18/(H8),0) -> 0 | F18: 200 | G18: =IF(D18=0,"",D18-F18) | J18: 7 | K18: 46174 | L18: Twitch Sub | M18: Subscriptions | N18: CFF | O18: 5.99 | P18: 1 | Q18: =IFERROR(IF(O18="",0,O18*P18),0) -> 5.99 | R18: Auto-pay | S18: Y
B19: Subscriptions | D19: =SUMIF(M12:M131,B19,Q12:Q131) -> 71.57 | E19: =IFERROR(D19/(H8),0) -> 0.017403632 | F19: 100 | G19: =IF(D19=0,"",D19-F19) -> -28.43 | J19: 8 | K19: 46174 | L19: Claude AI | M19: Subscriptions | N19: Robinhood | O19: 20 | P19: 1 | Q19: =IFERROR(IF(O19="",0,O19*P19),0) -> 20 | R19: Auto-pay | S19: Y
B20: Cash | D20: =SUMIF(M12:M131,B20,Q12:Q131) -> 0 | E20: =IFERROR(D20/(H8),0) -> 0 | F20: 100 | G20: =IF(D20=0,"",D20-F20) | J20: 9 | K20: 46174 | L20: Discord | M20: Subscriptions | N20: CFF | O20: 9.99 | P20: 1 | Q20: =IFERROR(IF(O20="",0,O20*P20),0) -> 9.99 | R20: Auto-pay | S20: Y
B21: Personal / Misc | D21: =SUMIF(M12:M131,B21,Q12:Q131) -> 40 | E21: =IFERROR(D21/(H8),0) -> 0.0097267749 | F21: 50 | G21: =IF(D21=0,"",D21-F21) -> -10 | J21: 10 | K21: 46175 | L21: Laundromat | M21: Utilities | N21: Robinhood | O21: 15 | P21: 1 | Q21: 15
B22: Other | D22: =SUMIF(M12:M131,B22,Q12:Q131) -> 179.99 | E22: =IFERROR(D22/(H8),0) -> 0.043768055 | F22: 700 | G22: =IF(D22=0,"",D22-F22) -> -520.01 | J22: 11 | K22: 46176 | L22: Sharon Gas 1 | M22: Gas / Transport | N22: Citi | O22: 32.54 | P22: 0.5 | Q22: 16.27
B23: Travel | D23: =SUMIF($M$12:$M$131,B23,$Q$12:$Q$131) -> 0 | E23: =IFERROR(D23/(H8),0) -> 0 | F23: 100 | G23: =IF(D23=0,"",D23-F23) | J23: 12 | K23: 46176 | L23: Max’s | M23: Dining / Takeout | O23: 32 | P23: 0.5 | Q23: =IFERROR(IF(O23="",0,O23*P23),0) -> 16
B24: Adjusted Rent | D24: =D60 -> 1013.285 | E24: =IFERROR(D24/(H8),0) -> 0.24639988 | J24: 13 | K24: 46174 | L24: Pa Ord noodles | M24: Dining / Takeout | O24: 24 | P24: 0.5 | Q24: 12
B25: Investment | D25: =D63 -> 300 | E25: =IFERROR(D25/(H8),0) -> 0.072950812 | J25: 14 | K25: 46185 | L25: Cash for Haircut | M25: Personal / Misc | N25: Cash | O25: 40 | P25: 1 | Q25: 40
B26: TOTAL Going Out | D26: =D64 -> 2122.585 | E26: =IFERROR(D26/(H8),0) -> 0.51614766 | J26: 15 | K26: 46175 | L26: LA TACO | M26: Subscriptions | N26: Robinhood | O26: 5.95 | P26: 1 | Q26: =IFERROR(IF(O26="",0,O26*P26),0) -> 5.95
B27: 💵 Money Left Over | D27: =D65 -> 1989.775 | E27: =IFERROR(D27/(H8),0) -> 0.48385234 | J27: 16 | K27: 46176 | L27: Birthday cake Whole Foods | M27: Dining / Takeout | N27: CFF | O27: 39 | P27: 1 | Q27: 39
J28: 17 | K28: 46178 | L28: DERA Crepe | M28: Dining / Takeout | N28: Discover | O28: 25.68 | P28: 1 | Q28: 25.68 | R28: For parents
B29: Card | D29: Total This Month $ | J29: 18 | K29: 46191 | L29: AAA Membership | M29: Other | N29: Robinhood | O29: 95 | P29: 1 | Q29: 95
B30: CFF | D30: =SUMIF(N12:N131,B30,O12:O131) -> 54.98 | J30: 19 | K30: 46179 | L30: Laundry 2 Sharon | M30: Utilities | N30: Robinhood | O30: 10 | P30: 0 | Q30: 0
B31: CFU | D31: =SUMIF(N12:N131,B31,O12:O131) -> 0 | J31: 20 | K31: 46180 | L31: New Airfryer! | M31: Other | N31: Robinhood | O31: 150 | P31: 0.5 | Q31: 75
B32: CSP | D32: =SUMIF(N12:N131,B32,O12:O131) -> 0 | J32: 21 | K32: 46180 | L32: Costco 1 | M32: Groceries | N32: Robinhood | O32: 113.22 | P32: 0.5 | Q32: 56.61
B33: Discover | D33: =SUMIF(N12:N131,B33,O12:O131) -> 77.35 | J33: 22 | K33: 46180 | L33: Ding Tea | M33: Dining / Takeout | N33: Robinhood | O33: 14.06 | P33: 0.85 | Q33: 11.95
B34: Citi | D34: =SUMIF(N12:N131,B34,O12:O131) -> 32.54 | J34: 23 | K34: 46181 | L34: Ralphs + chocolate milk | M34: Groceries | N34: Capital One | O34: 19.84 | P34: 0.6 | Q34: 11.9
B35: Capital One | D35: =SUMIF(N12:N131,B35,O12:O131) -> 85.56 | J35: 24 | K35: 46182 | L35: The Finals Video Game | M35: Other | N35: Robinhood | O35: 9.99 | P35: 1 | Q35: 9.99
B36: WF | D36: =SUMIF(N12:N131,B36,O12:O131) -> 0 | J36: 25 | K36: 46183 | L36: Pizza Hut | M36: Dining / Takeout | N36: Discover | O36: 10.42 | P36: 1 | Q36: 10.42
B37: Amazon Card | D37: =SUMIF(N12:N131,B37,O12:O131) -> 7.65 | J37: 26 | K37: 46183 | L37: Little Tokyo Market Place 1 | M37: Groceries | N37: Capital One | O37: 43.73 | P37: 0.5 | Q37: 21.86
B38: Robinhood | D38: =SUMIF(N12:N131,B38,O12:O131) -> 446.22 | J38: 27 | P38: 1 | Q38: =IFERROR(IF(O38="",0,O38*P38),0) -> 0
B39: Cash | D39: =SUMIF(N12:N131,B39,O12:O131) -> 105 | J39: 28 | P39: 1 | Q39: =IFERROR(IF(O39="",0,O39*P39),0) -> 0
B40: Other | D40: =SUMIF(N12:N131,B40,O12:O131) -> 0 | J40: 29 | P40: 1 | Q40: =IFERROR(IF(O40="",0,O40*P40),0) -> 0
B41: TOTAL CC CHARGES | D41: =SUM(D30:D40) -> 809.3 | J41: 30 | P41: 1 | Q41: =IFERROR(IF(O41="",0,O41*P41),0) -> 0
J42: 31 | P42: 1 | Q42: =IFERROR(IF(O42="",0,O42*P42),0) -> 0
B43: 📈 INVESTMENTS | J43: 32 | P43: 1 | Q43: =IFERROR(IF(O43="",0,O43*P43),0) -> 0
B44: Account | D44: Added This Month $ | F44: Invested $ | J44: 33 | P44: 1 | Q44: =IFERROR(IF(O44="",0,O44*P44),0) -> 0
B45: Robinhood Brokerage | D45: 300 | F45: ='May 2026'!F45+D45 -> 300 | J45: 34 | P45: 1 | Q45: =IFERROR(IF(O45="",0,O45*P45),0) -> 0
B46: Vanguard IRA | D46: 0 | J46: 35 | P46: 1 | Q46: =IFERROR(IF(O46="",0,O46*P46),0) -> 0
B47: 🏦 Ally Savings Buckets | J47: 36 | P47: 1 | Q47: =IFERROR(IF(O47="",0,O47*P47),0) -> 0
B48: Bucket | D48: Added This Month $ | F48: Balance $ | J48: 37 | P48: 1 | Q48: =IFERROR(IF(O48="",0,O48*P48),0) -> 0
B49: Wants | D49: 120 | F49: ='May 2026'!F49+D49 -> 3720 | J49: 38 | P49: 1 | Q49: =IFERROR(IF(O49="",0,O49*P49),0) -> 0
B50: Vacation | D50: 200 | F50: ='May 2026'!F50+D50 -> 7850 | J50: 39 | P50: 1 | Q50: =IFERROR(IF(O50="",0,O50*P50),0) -> 0
B51: Car Fund | D51: 400 | F51: ='May 2026'!F51+D51 -> 10400 | J51: 40 | P51: 1 | Q51: =IFERROR(IF(O51="",0,O51*P51),0) -> 0
B52: Emergency Fund | D52: 140 | F52: ='May 2026'!F52+D52 -> 6326.75 | J52: 41 | P52: 1 | Q52: =IFERROR(IF(O52="",0,O52*P52),0) -> 0
B53: Ally Total | D53: =SUM(D49:D52) -> 860 | F53: =SUM(F49:F52) -> 28296.75 | J53: 42 | P53: 1 | Q53: =IFERROR(IF(O53="",0,O53*P53),0) -> 0
B54: Total Invested (excl. Ally) | D54: =D45+D46 -> 300 | J54: 43 | P54: 1 | Q54: =IFERROR(IF(O54="",0,O54*P54),0) -> 0
J55: 44 | P55: 1 | Q55: =IFERROR(IF(O55="",0,O55*P55),0) -> 0
B56: 📈 MONTHLY SUMMARY | J56: 45 | P56: 1 | Q56: =IFERROR(IF(O56="",0,O56*P56),0) -> 0
B57: Total Monthly Income | D57: =H8 -> 4112.36 | J57: 46 | P57: 1 | Q57: =IFERROR(IF(O57="",0,O57*P57),0) -> 0
B58: Your Base Rent Share | D58: =D7*H7 -> 1110.7 | J58: 47 | P58: 1 | Q58: =IFERROR(IF(O58="",0,O58*P58),0) -> 0
B59: You Covered (partner's share ↓ your rent) | D59: =SUMPRODUCT((N12:N131<>"")*O12:O131*(1-P12:P131)) -> 210.415 | J59: 48 | P59: 1 | Q59: =IFERROR(IF(O59="",0,O59*P59),0) -> 0
B60: Your Rent After Adjustment | D60: =MAX(D7*H7-SUMPRODUCT((N12:N131<>"")*O12:O131*(1-P12:P131))+SUMPRODUCT((N12:N131="")*(O12:O131>0)*Q12:Q131),0) -> 1013.285 | J60: 49 | P60: 1 | Q60: =IFERROR(IF(O60="",0,O60*P60),0) -> 0
J61: 50 | P61: 1 | Q61: =IFERROR(IF(O61="",0,O61*P61),0) -> 0
B62: Total CC Charges | D62: =D41 -> 809.3 | J62: 51 | P62: 1 | Q62: =IFERROR(IF(O62="",0,O62*P62),0) -> 0
B63: Total Invested (excl. Ally) | D63: =D45+D46 -> 300 | J63: 52 | P63: 1 | Q63: =IFERROR(IF(O63="",0,O63*P63),0) -> 0
B64: TOTAL GOING OUT | D64: =D60+D62+D63 -> 2122.585 | J64: 53 | P64: 1 | Q64: =IFERROR(IF(O64="",0,O64*P64),0) -> 0
B65: 💵 MONEY LEFT OVER | D65: =H8-D64 -> 1989.775 | J65: 54 | P65: 1 | Q65: =IFERROR(IF(O65="",0,O65*P65),0) -> 0
J66: 55 | P66: 1 | Q66: =IFERROR(IF(O66="",0,O66*P66),0) -> 0
B67: 🔁 PARTNER BALANCE | J67: 56 | P67: 1 | Q67: =IFERROR(IF(O67="",0,O67*P67),0) -> 0
B68: Sharon Base Rent Share | D68: =D7*(1-H7) -> 1110.7 | J68: 57 | P68: 1 | Q68: =IFERROR(IF(O68="",0,O68*P68),0) -> 0
B69: She Covered (your share ↑ her rent) | D69: =SUMPRODUCT((N12:N131="")*(O12:O131>0)*Q12:Q131) -> 113 | J69: 58 | P69: 1 | Q69: =IFERROR(IF(O69="",0,O69*P69),0) -> 0
B70: You Covered (partner's share ↓ your rent) | D70: =SUMPRODUCT((N12:N131<>"")*O12:O131*(1-P12:P131)) -> 210.415 | J70: 59 | P70: 1 | Q70: =IFERROR(IF(O70="",0,O70*P70),0) -> 0
B71: Sharon's Total Rent This Month | D71: =MAX(D7*(1-H7)+SUMPRODUCT((N12:N131<>"")*O12:O131*(1-P12:P131))-SUMPRODUCT((N12:N131="")*(O12:O131>0)*Q12:Q131),0) -> 1208.115 | J71: 60 | P71: 1 | Q71: =IFERROR(IF(O71="",0,O71*P71),0) -> 0
B72: You Owe Sharon (if she overpaid) | D72: =MAX(SUMPRODUCT((N12:N131="")*(O12:O131>0)*Q12:Q131)-D7*(1-H7),0) -> 0 | J72: 61 | P72: 1 | Q72: =IFERROR(IF(O72="",0,O72*P72),0) -> 0
J73: 62 | P73: 1 | Q73: =IFERROR(IF(O73="",0,O73*P73),0) -> 0
J74: 63 | P74: 1 | Q74: =IFERROR(IF(O74="",0,O74*P74),0) -> 0
J75: 64 | P75: 1 | Q75: =IFERROR(IF(O75="",0,O75*P75),0) -> 0
J76: 65 | P76: 1 | Q76: =IFERROR(IF(O76="",0,O76*P76),0) -> 0
J77: 66 | P77: 1 | Q77: =IFERROR(IF(O77="",0,O77*P77),0) -> 0
J78: 67 | P78: 1 | Q78: =IFERROR(IF(O78="",0,O78*P78),0) -> 0
J79: 68 | P79: 1 | Q79: =IFERROR(IF(O79="",0,O79*P79),0) -> 0
J80: 69 | P80: 1 | Q80: =IFERROR(IF(O80="",0,O80*P80),0) -> 0
J81: 70 | P81: 1 | Q81: =IFERROR(IF(O81="",0,O81*P81),0) -> 0
J82: 71 | P82: 1 | Q82: =IFERROR(IF(O82="",0,O82*P82),0) -> 0
J83: 72 | P83: 1 | Q83: =IFERROR(IF(O83="",0,O83*P83),0) -> 0
J84: 73 | P84: 1 | Q84: =IFERROR(IF(O84="",0,O84*P84),0) -> 0
... J130: 119 | P130: 1 | Q130: =IFERROR(IF(O130="",0,O130*P130),0) -> 0
J131: 120 | P131: 1 | Q131: =IFERROR(IF(O132="",0,O132*P132),0) -> 0
L132: LOG TOTALS | O132: =SUM(O12:O131) -> 1035.3 | Q132: =SUM(Q12:Q131) -> 711.875

Sheet Jul 2026
B2: 💰 Jul 2026 — Expense Tracker
B3: LEFT: summaries auto-update | RIGHT: log every transaction | Blue cells = enter data
B5: ⚙️ SETTINGS
B6: Paycheck #1 (mid-mo) | D6: 2135.21 | F6: Paycheck #2 (end-mo) | H6: 2135.21
B7: Full Monthly Rent | D7: 2221.4 | F7: Your Rent Split % | H7: 0.5
B8: Monthly Savings Goal | D8: 500 | F8: Total Monthly Income | H8: =D6+H6+D9 -> 6260.195
B9: Carried Over (prior month) | D9: ='Jun 2026'!D65 -> 1989.775
B10: 📊 CATEGORY SUMMARY | J10: 📋 EXPENSE LOG — Enter every transaction here
B11: Category | D11: Your Share $ | E11: % Income | F11: Budget $ | G11: vs Budget | J11: # | K11: Date | L11: Description | M11: Category | N11: Credit Card | O11: Total $ | P11: Split % | Q11: Your Share $ | R11: Notes / Memo | S11: Recurring?
B12: Groceries | D12: =SUMIF(M12:M131,B12,Q12:Q131) -> 0 | E12: =IFERROR(D12/(H8),0) -> 0 | F12: 300 | G12: =IF(D12=0,"",D12-F12) | J12: 1 | K12: 46204 | L12: Car Insurance | M12: Gas / Transport | N12: Cash | O12: 65 | P12: 1 | Q12: =IFERROR(IF(O12="",0,O12*P12),0) -> 65 | R12: Auto-pay | S12: Y
B13: Utilities | D13: =SUMIF(M12:M131,B13,Q12:Q131) -> 20.625 | E13: =IFERROR(D13/(H8),0) -> 0.0032946258 | F13: 50 | G13: =IF(D13=0,"",D13-F13) -> -29.375 | J13: 2 | K13: 46204 | L13: Stronghold | M13: Health | N13: Robinhood | O13: 105 | P13: 1 | Q13: =IFERROR(IF(O13="",0,O13*P13),0) -> 105 | R13: Auto-pay | S13: Y
B14: Gas / Transport | D14: =SUMIF(M12:M131,B14,Q12:Q131) -> 65 | E14: =IFERROR(D14/(H8),0) -> 0.010383063 | F14: 200 | G14: =IF(D14=0,"",D14-F14) -> -135 | J14: 3 | K14: 46204 | L14: Spectrum Internet | M14: Utilities | N14: Discover | O14: 41.25 | P14: 0.5 | Q14: =IFERROR(IF(O14="",0,O14*P14),0) -> 20.625 | R14: Auto-pay | S14: Y
B15: Dining / Takeout | D15: =SUMIF(M12:M131,B15,Q12:Q131) -> 0 | E15: =IFERROR(D15/(H8),0) -> 0 | F15: 300 | G15: =IF(D15=0,"",D15-F15) | J15: 4 | K15: 46204 | L15: Amazon Prime | M15: Subscriptions | N15: Amazon Card | O15: 7.65 | P15: 1 | Q15: =IFERROR(IF(O15="",0,O15*P15),0) -> 7.65 | R15: Auto-pay | S15: Y
B16: Entertainment | D16: =SUMIF(M12:M131,B16,Q12:Q131) -> 0 | E16: =IFERROR(D16/(H8),0) -> 0 | F16: 150 | G16: =IF(D16=0,"",D16-F16) | J16: 5 | K16: 46204 | L16: Spotify | M16: Subscriptions | N16: Capital One | O16: 21.99 | P16: 1 | Q16: =IFERROR(IF(O16="",0,O16*P16),0) -> 21.99 | R16: Auto-pay | S16: Y
B17: Health | D17: =SUMIF(M12:M131,B17,Q12:Q131) -> 105 | E17: =IFERROR(D17/(H8),0) -> 0.01677264 | F17: 200 | G17: =IF(D17=0,"",D17-F17) -> -95 | J17: 6 | K17: 46204 | L17: Electricity | M17: Utilities | P17: 0.5 | Q17: =IFERROR(IF(O17="",0,O17*P17),0) -> 0 | R17: She pays | S17: Y
B18: Shopping | D18: =SUMIF(M12:M131,B18,Q12:Q131) -> 0 | E18: =IFERROR(D18/(H8),0) -> 0 | F18: 200 | G18: =IF(D18=0,"",D18-F18) | J18: 7 | K18: 46204 | L18: Twitch Sub | M18: Subscriptions | N18: CFF | O18: 5.99 | P18: 1 | Q18: =IFERROR(IF(O18="",0,O18*P18),0) -> 5.99 | R18: Auto-pay | S18: Y
B19: Subscriptions | D19: =SUMIF(M12:M131,B19,Q12:Q131) -> 65.62 | E19: =IFERROR(D19/(H8),0) -> 0.010482102 | F19: 100 | G19: =IF(D19=0,"",D19-F19) -> -34.38 | J19: 8 | K19: 46204 | L19: Claude AI | M19: Subscriptions | N19: Robinhood | O19: 20 | P19: 1 | Q19: =IFERROR(IF(O19="",0,O19*P19),0) -> 20 | R19: Auto-pay | S19: Y
B20: Cash | D20: =SUMIF(M12:M131,B20,Q12:Q131) -> 0 | E20: =IFERROR(D20/(H8),0) -> 0 | F20: 100 | G20: =IF(D20=0,"",D20-F20) | J20: 9 | K20: 46204 | L20: Discord | M20: Subscriptions | N20: CFF | O20: 9.99 | P20: 1 | Q20: =IFERROR(IF(O20="",0,O20*P20),0) -> 9.99 | R20: Auto-pay | S20: Y
B21: Personal / Misc | D21: =SUMIF(M12:M131,B21,Q12:Q131) -> 0 | E21: =IFERROR(D21/(H8),0) -> 0 | F21: 50 | G21: =IF(D21=0,"",D21-F21) | J21: 10 | K21: 46213 | L21: SMOG | M21: Other | N21: Robinhood | O21: 70 | P21: 1 | Q21: 70 | S21: TRUE
B22: Other | D22: =SUMIF(M12:M131,B22,Q12:Q131) -> 70 | E22: =IFERROR(D22/(H8),0) -> 0.01118176 | F22: 300 | G22: =IF(D22=0,"",D22-F22) -> -230 | J22: 11 | P22: 1 | Q22: =IFERROR(IF(O22="",0,O22*P22),0) -> 0
B23: Travel | D23: =SUMIF($M$12:$M$131,B23,$Q$12:$Q$131) -> 0 | E23: =IFERROR(D23/(H8),0) -> 0 | J23: 12 | P23: 1 | Q23: =IFERROR(IF(O23="",0,O23*P23),0) -> 0
B24: Adjusted Rent | D24: =D60 -> 1090.075 | E24: =IFERROR(D24/(H8),0) -> 0.17412796 | J24: 13 | P24: 1 | Q24: =IFERROR(IF(O24="",0,O24*P24),0) -> 0
B25: Investment | D25: =D63 -> 0 | E25: =IFERROR(D25/(H8),0) -> 0 | J25: 14 | P25: 1 | Q25: =IFERROR(IF(O25="",0,O25*P25),0) -> 0
B26: TOTAL Going Out | D26: =D64 -> 1436.945 | E26: =IFERROR(D26/(H8),0) -> 0.22953678 | J26: 15 | P26: 1 | Q26: =IFERROR(IF(O26="",0,O26*P26),0) -> 0
B27: 💵 Money Left Over | D27: =D65 -> 4823.25 | E27: =IFERROR(D27/(H8),0) -> 0.77046322 | J27: 16 | P27: 1 | Q27: =IFERROR(IF(O27="",0,O27*P27),0) -> 0
J28: 17 | P28: 1 | Q28: =IFERROR(IF(O28="",0,O28*P28),0) -> 0
B29: Card | D29: Total This Month $ | J29: 18 | P29: 1 | Q29: =IFERROR(IF(O29="",0,O29*P29),0) -> 0
B30: CFF | D30: =SUMIF(N12:N131,B30,O12:O131) -> 15.98 | J30: 19 | P30: 1 | Q30: =IFERROR(IF(O30="",0,O30*P30),0) -> 0
B31: CFU | D31: =SUMIF(N12:N131,B31,O12:O131) -> 0 | J31: 20 | P31: 1 | Q31: =IFERROR(IF(O31="",0,O31*P31),0) -> 0
B32: CSP | D32: =SUMIF(N12:N131,B32,O12:O131) -> 0 | J32: 21 | P32: 1 | Q32: =IFERROR(IF(O32="",0,O32*P32),0) -> 0
B33: Discover | D33: =SUMIF(N12:N131,B33,O12:O131) -> 41.25 | J33: 22 | P33: 1 | Q33: =IFERROR(IF(O33="",0,O33*P33),0) -> 0
B34: Citi | D34: =SUMIF(N12:N131,B34,O12:O131) -> 0 | J34: 23 | P34: 1 | Q34: =IFERROR(IF(O34="",0,O34*P34),0) -> 0
B35: Capital One | D35: =SUMIF(N12:N131,B35,O12:O131) -> 21.99 | J35: 24 | P35: 1 | Q35: =IFERROR(IF(O35="",0,O35*P35),0) -> 0
B36: WF | D36: =SUMIF(N12:N131,B36,O12:O131) -> 0 | J36: 25 | P36: 1 | Q36: =IFERROR(IF(O36="",0,O36*P36),0) -> 0
B37: Amazon Card | D37: =SUMIF(N12:N131,B37,O12:O131) -> 7.65 | J37: 26 | P37: 1 | Q37: =IFERROR(IF(O37="",0,O37*P37),0) -> 0
B38: Robinhood | D38: =SUMIF(N12:N131,B38,O12:O131) -> 195 | J38: 27 | P38: 1 | Q38: =IFERROR(IF(O38="",0,O38*P38),0) -> 0
B39: Cash | D39: =SUMIF(N12:N131,B39,O12:O131) -> 65 | J39: 28 | P39: 1 | Q39: =IFERROR(IF(O39="",0,O39*P39),0) -> 0
B40: Other | D40: =SUMIF(N12:N131,B40,O12:O131) -> 0 | J40: 29 | P40: 1 | Q40: =IFERROR(IF(O40="",0,O40*P40),0) -> 0
B41: TOTAL CC CHARGES | D41: =SUM(D30:D40) -> 346.87 | J41: 30 | P41: 1 | Q41: =IFERROR(IF(O41="",0,O41*P41),0) -> 0
J42: 31 | P42: 1 | Q42: =IFERROR(IF(O42="",0,O42*P42),0) -> 0
B43: 📈 INVESTMENTS | J43: 32 | P43: 1 | Q43: =IFERROR(IF(O43="",0,O43*P43),0) -> 0
B44: Account | D44: Added This Month $ | F44: Invested $ | J44: 33 | P44: 1 | Q44: =IFERROR(IF(O44="",0,O44*P44),0) -> 0
B45: Robinhood Brokerage | D45: 0 | F45: ='Jun 2026'!F45+D45 -> 300 | J45: 34 | P45: 1 | Q45: =IFERROR(IF(O45="",0,O45*P45),0) -> 0
B46: Vanguard IRA | D46: 0 | J46: 35 | P46: 1 | Q46: =IFERROR(IF(O46="",0,O46*P46),0) -> 0
B47: 🏦 Ally Savings Buckets | J47: 36 | P47: 1 | Q47: =IFERROR(IF(O47="",0,O47*P47),0) -> 0
B48: Bucket | D48: Added This Month $ | F48: Balance $ | J48: 37 | P48: 1 | Q48: =IFERROR(IF(O48="",0,O48*P48),0) -> 0
B49: Wants | D49: 120 | F49: ='Jun 2026'!F49+D49 -> 3840 | J49: 38 | P49: 1 | Q49: =IFERROR(IF(O49="",0,O49*P49),0) -> 0
B50: Vacation | D50: 200 | F50: ='Jun 2026'!F50+D50 -> 8050 | J50: 39 | P50: 1 | Q50: =IFERROR(IF(O50="",0,O50*P50),0) -> 0
B51: Car Fund | D51: 400 | F51: ='Jun 2026'!F51+D51 -> 10800 | J51: 40 | P51: 1 | Q51: =IFERROR(IF(O51="",0,O51*P51),0) -> 0
B52: Emergency Fund | D52: 140 | F52: ='Jun 2026'!F52+D52 -> 6466.75 | J52: 41 | P52: 1 | Q52: =IFERROR(IF(O52="",0,O52*P52),0) -> 0
B53: Ally Total | D53: =SUM(D49:D52) -> 860 | F53: =SUM(F49:F52) -> 29156.75 | J53: 42 | P53: 1 | Q53: =IFERROR(IF(O53="",0,O53*P53),0) -> 0
B54: Total Invested (excl. Ally) | D54: =D45+D46 -> 0 | J54: 43 | P54: 1 | Q54: =IFERROR(IF(O54="",0,O54*P54),0) -> 0
J55: 44 | P55: 1 | Q55: =IFERROR(IF(O55="",0,O55*P55),0) -> 0
B56: 📈 MONTHLY SUMMARY | J56: 45 | P56: 1 | Q56: =IFERROR(IF(O56="",0,O56*P56),0) -> 0
B57: Total Monthly Income | D57: =H8 -> 6260.195 | J57: 46 | P57: 1 | Q57: =IFERROR(IF(O57="",0,O57*P57),0) -> 0
B58: Your Base Rent Share | D58: =D7*H7 -> 1110.7 | J58: 47 | P58: 1 | Q58: =IFERROR(IF(O58="",0,O58*P58),0) -> 0
B59: You Covered (partner's share ↓ your rent) | D59: =SUMPRODUCT((N12:N131<>"")*O12:O131*(1-P12:P131)) -> 20.625 | J59: 48 | P59: 1 | Q59: =IFERROR(IF(O59="",0,O59*P59),0) -> 0
B60: Your Rent After Adjustment | D60: =MAX(D7*H7-SUMPRODUCT((N12:N131<>"")*O12:O131*(1-P12:P131))+SUMPRODUCT((N12:N131="")*(O12:O131>0)*Q12:Q131),0) -> 1090.075 | J60: 49 | P60: 1 | Q60: =IFERROR(IF(O60="",0,O60*P60),0) -> 0
J61: 50 | P61: 1 | Q61: =IFERROR(IF(O61="",0,O61*P61),0) -> 0
B62: Total CC Charges | D62: =D41 -> 346.87 | J62: 51 | P62: 1 | Q62: =IFERROR(IF(O62="",0,O62*P62),0) -> 0
B63: Total Invested (excl. Ally) | D63: =D45+D46 -> 0 | J63: 52 | P63: 1 | Q63: =IFERROR(IF(O63="",0,O63*P63),0) -> 0
B64: TOTAL GOING OUT | D64: =D60+D62+D63 -> 1436.945 | J64: 53 | P64: 1 | Q64: =IFERROR(IF(O64="",0,O64*P64),0) -> 0
B65: 💵 MONEY LEFT OVER | D65: =H8-D64 -> 4823.25 | J65: 54 | P65: 1 | Q65: =IFERROR(IF(O65="",0,O65*P65),0) -> 0
J66: 55 | P66: 1 | Q66: =IFERROR(IF(O66="",0,O66*P66),0) -> 0
B67: 🔁 PARTNER BALANCE | J67: 56 | P67: 1 | Q67: =IFERROR(IF(O67="",0,O67*P67),0) -> 0
B68: Sharon Base Rent Share | D68: =D7*(1-H7) -> 1110.7 | J68: 57 | P68: 1 | Q68: =IFERROR(IF(O68="",0,O68*P68),0) -> 0
B69: She Covered (your share ↑ her rent) | D69: =SUMPRODUCT((N12:N131="")*(O12:O131>0)*Q12:Q131) -> 0 | J69: 58 | P69: 1 | Q69: =IFERROR(IF(O69="",0,O69*P69),0) -> 0
B70: You Covered (partner's share ↓ your rent) | D70: =SUMPRODUCT((N12:N131<>"")*O12:O131*(1-P12:P131)) -> 20.625 | J70: 59 | P70: 1 | Q70: =IFERROR(IF(O70="",0,O70*P70),0) -> 0
B71: Sharon's Total Rent This Month | D71: =MAX(D7*(1-H7)+SUMPRODUCT((N12:N131<>"")*O12:O131*(1-P12:P131))-SUMPRODUCT((N12:N131="")*(O12:O131>0)*Q12:Q131),0) -> 1131.325 | J71: 60 | P71: 1 | Q71: =IFERROR(IF(O71="",0,O71*P71),0) -> 0
B72: You Owe Sharon (if she overpaid) | D72: =MAX(SUMPRODUCT((N12:N131="")*(O12:O131>0)*Q12:Q131)-D7*(1-H7),0) -> 0 | J72: 61 | P72: 1 | Q72: =IFERROR(IF(O72="",0,O72*P72),0) -> 0
J73: 62 | P73: 1 | Q73: =IFERROR(IF(O73="",0,O73*P73),0) -> 0
J74: 63 | P74: 1 | Q74: =IFERROR(IF(O74="",0,O74*P74),0) -> 0
J75: 64 | P75: 1 | Q75: =IFERROR(IF(O75="",0,O75*P75),0) -> 0
J76: 65 | P76: 1 | Q76: =IFERROR(IF(O76="",0,O76*P76),0) -> 0
J77: 66 | P77: 1 | Q77: =IFERROR(IF(O77="",0,O77*P77),0) -> 0
J78: 67 | P78: 1 | Q78: =IFERROR(IF(O78="",0,O78*P78),0) -> 0
J79: 68 | P79: 1 | Q79: =IFERROR(IF(O79="",0,O79*P79),0) -> 0
J80: 69 | P80: 1 | Q80: =IFERROR(IF(O80="",0,O80*P80),0) -> 0
J81: 70 | P81: 1 | Q81: =IFERROR(IF(O81="",0,O81*P81),0) -> 0
J82: 71 | P82: 1 | Q82: =IFERROR(IF(O82="",0,O82*P82),0) -> 0
J83: 72 | P83: 1 | Q83: =IFERROR(IF(O83="",0,O83*P83),0) -> 0
J84: 73 | P84: 1 | Q84: =IFERROR(IF(O84="",0,O84*P84),0) -> 0
... J130: 119 | P130: 1 | Q130: =IFERROR(IF(O130="",0,O130*P130),0) -> 0
J131: 120 | P131: 1 | Q131: =IFERROR(IF(O132="",0,O132*P132),0) -> 0
L132: LOG TOTALS | O132: =SUM(O12:O131) -> 346.87 | Q132: =SUM(Q12:Q131) -> 326.245

Sheet Aug 2026
B2: 💰 Aug 2026 — Expense Tracker
B3: LEFT: summaries auto-update | RIGHT: log every transaction | Blue cells = enter data
B5: ⚙️ SETTINGS
B6: Paycheck #1 (mid-mo) | D6: 2500 | F6: Paycheck #2 (end-mo) | H6: 2500
B7: Full Monthly Rent | D7: 2221.4 | F7: Your Rent Split % | H7: 0.5
B8: Monthly Savings Goal | D8: 500 | F8: Total Monthly Income | H8: =D6+H6+D9 -> 9823.25
B9: Carried Over (prior month) | D9: ='Jul 2026'!D65 -> 4823.25
B10: 📊 CATEGORY SUMMARY | J10: 📋 EXPENSE LOG — Enter every transaction here
B11: Category | D11: Your Share $ | E11: % Income | F11: Budget $ | G11: vs Budget | J11: # | K11: Date | L11: Description | M11: Category | N11: Credit Card | O11: Total $ | P11: Split % | Q11: Your Share $ | R11: Notes / Memo | S11: Recurring?
B12: Groceries | D12: =SUMIF(M12:M131,B12,Q12:Q131) -> 0 | E12: =IFERROR(D12/(H8),0) -> 0 | F12: 300 | G12: =IF(D12=0,"",D12-F12) | J12: 1 | K12: 46235 | L12: Car Insurance | M12: Gas / Transport | N12: Cash | O12: 65 | P12: 1 | Q12: =IFERROR(IF(O12="",0,O12*P12),0) -> 65 | R12: Auto-pay | S12: Y
B13: Utilities | D13: =SUMIF(M12:M131,B13,Q12:Q131) -> 105.625 | E13: =IFERROR(D13/(H8),0) -> 0.010752551 | F13: 50 | G13: =IF(D13=0,"",D13-F13) -> 55.625 | J13: 2 | K13: 46235 | L13: Stronghold | M13: Health | N13: Robinhood | O13: 105 | P13: 1 | Q13: =IFERROR(IF(O13="",0,O13*P13),0) -> 105 | R13: Auto-pay | S13: Y
B14: Gas / Transport | D14: =SUMIF(M12:M131,B14,Q12:Q131) -> 65 | E14: =IFERROR(D14/(H8),0) -> 0.0066169547 | F14: 200 | G14: =IF(D14=0,"",D14-F14) -> -135 | J14: 3 | K14: 46235 | L14: Spectrum Internet | M14: Utilities | N14: Discover | O14: 41.25 | P14: 0.5 | Q14: =IFERROR(IF(O14="",0,O14*P14),0) -> 20.625 | R14: Auto-pay | S14: Y
B15: Dining / Takeout | D15: =SUMIF(M12:M131,B15,Q12:Q131) -> 0 | E15: =IFERROR(D15/(H8),0) -> 0 | F15: 300 | G15: =IF(D15=0,"",D15-F15) | J15: 4 | K15: 46235 | L15: Amazon Prime | M15: Subscriptions | N15: Amazon Card | O15: 7.65 | P15: 1 | Q15: =IFERROR(IF(O15="",0,O15*P15),0) -> 7.65 | R15: Auto-pay | S15: Y
B16: Entertainment | D16: =SUMIF(M12:M131,B16,Q12:Q131) -> 0 | E16: =IFERROR(D16/(H8),0) -> 0 | F16: 150 | G16: =IF(D16=0,"",D16-F16) | J16: 5 | K16: 46235 | L16: Spotify | M16: Subscriptions | N16: Capital One | O16: 21.99 | P16: 1 | Q16: =IFERROR(IF(O16="",0,O16*P16),0) -> 21.99 | R16: Auto-pay | S16: Y
B17: Health | D17: =SUMIF(M12:M131,B17,Q12:Q131) -> 105 | E17: =IFERROR(D17/(H8),0) -> 0.010688927 | F17: 200 | G17: =IF(D17=0,"",D17-F17) -> -95 | J17: 6 | K17: 46235 | L17: Electricity | M17: Utilities | O17: 170 | P17: 0.5 | Q17: =IFERROR(IF(O17="",0,O17*P17),0) -> 85 | R17: She pays | S17: Y
B18: Shopping | D18: =SUMIF(M12:M131,B18,Q12:Q131) -> 0 | E18: =IFERROR(D18/(H8),0) -> 0 | F18: 200 | G18: =IF(D18=0,"",D18-F18) | J18: 7 | K18: 46235 | L18: Twitch Sub | M18: Subscriptions | N18: CFF | O18: 5.99 | P18: 1 | Q18: =IFERROR(IF(O18="",0,O18*P18),0) -> 5.99 | R18: Auto-pay | S18: Y
B19: Subscriptions | D19: =SUMIF(M12:M131,B19,Q12:Q131) -> 65.62 | E19: =IFERROR(D19/(H8),0) -> 0.0066800702 | F19: 100 | G19: =IF(D19=0,"",D19-F19) -> -34.38 | J19: 8 | K19: 46235 | L19: Claude AI | M19: Subscriptions | N19: Robinhood | O19: 20 | P19: 1 | Q19: =IFERROR(IF(O19="",0,O19*P19),0) -> 20 | R19: Auto-pay | S19: Y
B20: Cash | D20: =SUMIF(M12:M131,B20,Q12:Q131) -> 0 | E20: =IFERROR(D20/(H8),0) -> 0 | F20: 100 | G20: =IF(D20=0,"",D20-F20) | J20: 9 | K20: 46235 | L20: Discord | M20: Subscriptions | N20: CFF | O20: 9.99 | P20: 1 | Q20: =IFERROR(IF(O20="",0,O20*P20),0) -> 9.99 | R20: Auto-pay | S20: Y
B21: Personal / Misc | D21: =SUMIF(M12:M131,B21,Q12:Q131) -> 0 | E21: =IFERROR(D21/(H8),0) -> 0 | F21: 50 | G21: =IF(D21=0,"",D21-F21) | J21: 10 | K21: 46241 | L21: DMV renewal | M21: Other | N21: Robinhood | O21: 169 | P21: 1 | Q21: 169 | S21: TRUE
B22: Other | D22: =SUMIF(M12:M131,B22,Q12:Q131) -> 169 | E22: =IFERROR(D22/(H8),0) -> 0.017204082 | F22: 50 | G22: =IF(D22=0,"",D22-F22) -> 119 | J22: 11 | P22: 1 | Q22: =IFERROR(IF(O22="",0,O22*P22),0) -> 0
B23: Travel | D23: =SUMIF($M$12:$M$131,B23,$Q$12:$Q$131) -> 0 | E23: =IFERROR(D23/(H8),0) -> 0 | J23: 12 | P23: 1 | Q23: =IFERROR(IF(O23="",0,O23*P23),0) -> 0
B24: Adjusted Rent | D24: =D60 -> 1175.075 | E24: =IFERROR(D24/(H8),0) -> 0.11962182 | J24: 13 | P24: 1 | Q24: =IFERROR(IF(O24="",0,O24*P24),0) -> 0
B25: Investment | D25: =D63 -> 0 | E25: =IFERROR(D25/(H8),0) -> 0 | J25: 14 | P25: 1 | Q25: =IFERROR(IF(O25="",0,O25*P25),0) -> 0
B26: TOTAL Going Out | D26: =D64 -> 1620.945 | E26: =IFERROR(D26/(H8),0) -> 0.16501107 | J26: 15 | P26: 1 | Q26: =IFERROR(IF(O26="",0,O26*P26),0) -> 0
B27: 💵 Money Left Over | D27: =D65 -> 8202.305 | E27: =IFERROR(D27/(H8),0) -> 0.83498893 | J27: 16 | P27: 1 | Q27: =IFERROR(IF(O27="",0,O27*P27),0) -> 0
J28: 17 | P28: 1 | Q28: =IFERROR(IF(O28="",0,O28*P28),0) -> 0
B29: Card | D29: Total This Month $ | J29: 18 | P29: 1 | Q29: =IFERROR(IF(O29="",0,O29*P29),0) -> 0
B30: CFF | D30: =SUMIF(N12:N131,B30,O12:O131) -> 15.98 | J30: 19 | P30: 1 | Q30: =IFERROR(IF(O30="",0,O30*P30),0) -> 0
B31: CFU | D31: =SUMIF(N12:N131,B31,O12:O131) -> 0 | J31: 20 | P31: 1 | Q31: =IFERROR(IF(O31="",0,O31*P31),0) -> 0
B32: CSP | D32: =SUMIF(N12:N131,B32,O12:O131) -> 0 | J32: 21 | P32: 1 | Q32: =IFERROR(IF(O32="",0,O32*P32),0) -> 0
B33: Discover | D33: =SUMIF(N12:N131,B33,O12:O131) -> 41.25 | J33: 22 | P33: 1 | Q33: =IFERROR(IF(O33="",0,O33*P33),0) -> 0
B34: Citi | D34: =SUMIF(N12:N131,B34,O12:O131) -> 0 | J34: 23 | P34: 1 | Q34: =IFERROR(IF(O34="",0,O34*P34),0) -> 0
B35: Capital One | D35: =SUMIF(N12:N131,B35,O12:O131) -> 21.99 | J35: 24 | P35: 1 | Q35: =IFERROR(IF(O35="",0,O35*P35),0) -> 0
B36: WF | D36: =SUMIF(N12:N131,B36,O12:O131) -> 0 | J36: 25 | P36: 1 | Q36: =IFERROR(IF(O36="",0,O36*P36),0) -> 0
B37: Amazon Card | D37: =SUMIF(N12:N131,B37,O12:O131) -> 7.65 | J37: 26 | P37: 1 | Q37: =IFERROR(IF(O37="",0,O37*P37),0) -> 0
B38: Robinhood | D38: =SUMIF(N12:N131,B38,O12:O131) -> 294 | J38: 27 | P38: 1 | Q38: =IFERROR(IF(O38="",0,O38*P38),0) -> 0
B39: Cash | D39: =SUMIF(N12:N131,B39,O12:O131) -> 65 | J39: 28 | P39: 1 | Q39: =IFERROR(IF(O39="",0,O39*P39),0) -> 0
B40: Other | D40: =SUMIF(N12:N131,B40,O12:O131) -> 0 | J40: 29 | P40: 1 | Q40: =IFERROR(IF(O40="",0,O40*P40),0) -> 0
B41: TOTAL CC CHARGES | D41: =SUM(D30:D40) -> 445.87 | J41: 30 | P41: 1 | Q41: =IFERROR(IF(O41="",0,O41*P41),0) -> 0
J42: 31 | P42: 1 | Q42: =IFERROR(IF(O42="",0,O42*P42),0) -> 0
B43: 📈 INVESTMENTS | J43: 32 | P43: 1 | Q43: =IFERROR(IF(O43="",0,O43*P43),0) -> 0
B44: Account | D44: Added This Month $ | F44: Invested $ | J44: 33 | P44: 1 | Q44: =IFERROR(IF(O44="",0,O44*P44),0) -> 0
B45: Robinhood Brokerage | D45: 0 | F45: ='Jul 2026'!F45+D45 -> 300 | J45: 34 | P45: 1 | Q45: =IFERROR(IF(O45="",0,O45*P45),0) -> 0
B46: Vanguard IRA | D46: 0 | J46: 35 | P46: 1 | Q46: =IFERROR(IF(O46="",0,O46*P46),0) -> 0
B47: 🏦 Ally Savings Buckets | J47: 36 | P47: 1 | Q47: =IFERROR(IF(O47="",0,O47*P47),0) -> 0
B48: Bucket | D48: Added This Month $ | F48: Balance $ | J48: 37 | P48: 1 | Q48: =IFERROR(IF(O48="",0,O48*P48),0) -> 0
B49: Wants | D49: 120 | F49: ='Jul 2026'!F49+D49 -> 3960 | J49: 38 | P49: 1 | Q49: =IFERROR(IF(O49="",0,O49*P49),0) -> 0
B50: Vacation | D50: 200 | F50: ='Jul 2026'!F50+D50 -> 8250 | J50: 39 | P50: 1 | Q50: =IFERROR(IF(O50="",0,O50*P50),0) -> 0
B51: Car Fund | D51: 400 | F51: ='Jul 2026'!F51+D51 -> 11200 | J51: 40 | P51: 1 | Q51: =IFERROR(IF(O51="",0,O51*P51),0) -> 0
B52: Emergency Fund | D52: 140 | F52: ='Jul 2026'!F52+D52 -> 6606.75 | J52: 41 | P52: 1 | Q52: =IFERROR(IF(O52="",0,O52*P52),0) -> 0
B53: Ally Total | D53: =SUM(D49:D52) -> 860 | F53: =SUM(F49:F52) -> 30016.75 | J53: 42 | P53: 1 | Q53: =IFERROR(IF(O53="",0,O53*P53),0) -> 0
B54: Total Invested (excl. Ally) | D54: =D45+D46 -> 0 | J54: 43 | P54: 1 | Q54: =IFERROR(IF(O54="",0,O54*P54),0) -> 0
J55: 44 | P55: 1 | Q55: =IFERROR(IF(O55="",0,O55*P55),0) -> 0
B56: 📈 MONTHLY SUMMARY | J56: 45 | P56: 1 | Q56: =IFERROR(IF(O56="",0,O56*P56),0) -> 0
B57: Total Monthly Income | D57: =H8 -> 9823.25 | J57: 46 | P57: 1 | Q57: =IFERROR(IF(O57="",0,O57*P57),0) -> 0
B58: Your Base Rent Share | D58: =D7*H7 -> 1110.7 | J58: 47 | P58: 1 | Q58: =IFERROR(IF(O58="",0,O58*P58),0) -> 0
B59: You Covered (partner's share ↓ your rent) | D59: =SUMPRODUCT((N12:N131<>"")*O12:O131*(1-P12:P131)) -> 20.625 | J59: 48 | P59: 1 | Q59: =IFERROR(IF(O59="",0,O59*P59),0) -> 0
B60: Your Rent After Adjustment | D60: =MAX(D7*H7-SUMPRODUCT((N12:N131<>"")*O12:O131*(1-P12:P131))+SUMPRODUCT((N12:N131="")*(O12:O131>0)*Q12:Q131),0) -> 1175.075 | J60: 49 | P60: 1 | Q60: =IFERROR(IF(O60="",0,O60*P60),0) -> 0
J61: 50 | P61: 1 | Q61: =IFERROR(IF(O61="",0,O61*P61),0) -> 0
B62: Total CC Charges | D62: =D41 -> 445.87 | J62: 51 | P62: 1 | Q62: =IFERROR(IF(O62="",0,O62*P62),0) -> 0
B63: Total Invested (excl. Ally) | D63: =D45+D46 -> 0 | J63: 52 | P63: 1 | Q63: =IFERROR(IF(O63="",0,O63*P63),0) -> 0
B64: TOTAL GOING OUT | D64: =D60+D62+D63 -> 1620.945 | J64: 53 | P64: 1 | Q64: =IFERROR(IF(O64="",0,O64*P64),0) -> 0
B65: 💵 MONEY LEFT OVER | D65: =H8-D64 -> 8202.305 | J65: 54 | P65: 1 | Q65: =IFERROR(IF(O65="",0,O65*P65),0) -> 0
J66: 55 | P66: 1 | Q66: =IFERROR(IF(O66="",0,O66*P66),0) -> 0
B67: 🔁 PARTNER BALANCE | J67: 56 | P67: 1 | Q67: =IFERROR(IF(O67="",0,O67*P67),0) -> 0
B68: Sharon Base Rent Share | D68: =D7*(1-H7) -> 1110.7 | J68: 57 | P68: 1 | Q68: =IFERROR(IF(O68="",0,O68*P68),0) -> 0
B69: She Covered (your share ↑ her rent) | D69: =SUMPRODUCT((N12:N131="")*(O12:O131>0)*Q12:Q131) -> 85 | J69: 58 | P69: 1 | Q69: =IFERROR(IF(O69="",0,O69*P69),0) -> 0
B70: You Covered (partner's share ↓ your rent) | D70: =SUMPRODUCT((N12:N131<>"")*O12:O131*(1-P12:P131)) -> 20.625 | J70: 59 | P70: 1 | Q70: =IFERROR(IF(O70="",0,O70*P70),0) -> 0
B71: Sharon's Total Rent This Month | D71: =MAX(D7*(1-H7)+SUMPRODUCT((N12:N131<>"")*O12:O131*(1-P12:P131))-SUMPRODUCT((N12:N131="")*(O12:O131>0)*Q12:Q131),0) -> 1046.325 | J71: 60 | P71: 1 | Q71: =IFERROR(IF(O71="",0,O71*P71),0) -> 0
B72: You Owe Sharon (if she overpaid) | D72: =MAX(SUMPRODUCT((N12:N131="")*(O12:O131>0)*Q12:Q131)-D7*(1-H7),0) -> 0 | J72: 61 | P72: 1 | Q72: =IFERROR(IF(O72="",0,O72*P72),0) -> 0
J73: 62 | P73: 1 | Q73: =IFERROR(IF(O73="",0,O73*P73),0) -> 0
J74: 63 | P74: 1 | Q74: =IFERROR(IF(O74="",0,O74*P74),0) -> 0
J75: 64 | P75: 1 | Q75: =IFERROR(IF(O75="",0,O75*P75),0) -> 0
J76: 65 | P76: 1 | Q76: =IFERROR(IF(O76="",0,O76*P76),0) -> 0
J77: 66 | P77: 1 | Q77: =IFERROR(IF(O77="",0,O77*P77),0) -> 0
J78: 67 | P78: 1 | Q78: =IFERROR(IF(O78="",0,O78*P78),0) -> 0
J79: 68 | P79: 1 | Q79: =IFERROR(IF(O79="",0,O79*P79),0) -> 0
J80: 69 | P80: 1 | Q80: =IFERROR(IF(O80="",0,O80*P80),0) -> 0
J81: 70 | P81: 1 | Q81: =IFERROR(IF(O81="",0,O81*P81),0) -> 0
J82: 71 | P82: 1 | Q82: =IFERROR(IF(O82="",0,O82*P82),0) -> 0
J83: 72 | P83: 1 | Q83: =IFERROR(IF(O83="",0,O83*P83),0) -> 0
J84: 73 | P84: 1 | Q84: =IFERROR(IF(O84="",0,O84*P84),0) -> 0
... J130: 119 | P130: 1 | Q130: =IFERROR(IF(O130="",0,O130*P130),0) -> 0
J131: 120 | P131: 1 | Q131: =IFERROR(IF(O132="",0,O132*P132),0) -> 0
L132: LOG TOTALS | O132: =SUM(O12:O131) -> 615.87 | Q132: =SUM(Q12:Q131) -> 510.245

Sheet Sep 2026
B2: 💰 Sep 2026 — Expense Tracker
B3: LEFT: summaries auto-update | RIGHT: log every transaction | Blue cells = enter data
B5: ⚙️ SETTINGS
B6: Paycheck #1 (mid-mo) | D6: 2500 | F6: Paycheck #2 (end-mo) | H6: 2500
B7: Full Monthly Rent | D7: 2221.4 | F7: Your Rent Split % | H7: 0.5
B8: Monthly Savings Goal | D8: 500 | F8: Total Monthly Income | H8: =D6+H6+D9 -> 13202.305
B9: Carried Over (prior month) | D9: ='Aug 2026'!D65 -> 8202.305
B10: 📊 CATEGORY SUMMARY | J10: 📋 EXPENSE LOG — Enter every transaction here
B11: Category | D11: Your Share $ | E11: % Income | F11: Budget $ | G11: vs Budget | J11: # | K11: Date | L11: Description | M11: Category | N11: Credit Card | O11: Total $ | P11: Split % | Q11: Your Share $ | R11: Notes / Memo | S11: Recurring?
B12: Groceries | D12: =SUMIF(M12:M131,B12,Q12:Q131) -> 0 | E12: =IFERROR(D12/(H8),0) -> 0 | F12: 300 | G12: =IF(D12=0,"",D12-F12) | J12: 1 | K12: 46266 | L12: Car Insurance | M12: Gas / Transport | N12: Cash | O12: 65 | P12: 1 | Q12: =IFERROR(IF(O12="",0,O12*P12),0) -> 65 | R12: Auto-pay | S12: Y
B13: Utilities | D13: =SUMIF(M12:M131,B13,Q12:Q131) -> 20.625 | E13: =IFERROR(D13/(H8),0) -> 0.0015622272 | F13: 50 | G13: =IF(D13=0,"",D13-F13) -> -29.375 | J13: 2 | K13: 46266 | L13: Stronghold | M13: Health | N13: Robinhood | O13: 105 | P13: 1 | Q13: =IFERROR(IF(O13="",0,O13*P13),0) -> 105 | R13: Auto-pay | S13: Y
B14: Gas / Transport | D14: =SUMIF(M12:M131,B14,Q12:Q131) -> 65 | E14: =IFERROR(D14/(H8),0) -> 0.0049233827 | F14: 200 | G14: =IF(D14=0,"",D14-F14) -> -135 | J14: 3 | K14: 46266 | L14: Spectrum Internet | M14: Utilities | N14: Discover | O14: 41.25 | P14: 0.5 | Q14: =IFERROR(IF(O14="",0,O14*P14),0) -> 20.625 | R14: Auto-pay | S14: Y
B15: Dining / Takeout | D15: =SUMIF(M12:M131,B15,Q12:Q131) -> 0 | E15: =IFERROR(D15/(H8),0) -> 0 | F15: 300 | G15: =IF(D15=0,"",D15-F15) | J15: 4 | K15: 46266 | L15: Amazon Prime | M15: Subscriptions | N15: Amazon Card | O15: 7.65 | P15: 1 | Q15: =IFERROR(IF(O15="",0,O15*P15),0) -> 7.65 | R15: Auto-pay | S15: Y
B16: Entertainment | D16: =SUMIF(M12:M131,B16,Q12:Q131) -> 0 | E16: =IFERROR(D16/(H8),0) -> 0 | F16: 150 | G16: =IF(D16=0,"",D16-F16) | J16: 5 | K16: 46266 | L16: Spotify | M16: Subscriptions | N16: Capital One | O16: 21.99 | P16: 1 | Q16: =IFERROR(IF(O16="",0,O16*P16),0) -> 21.99 | R16: Auto-pay | S16: Y
B17: Health | D17: =SUMIF(M12:M131,B17,Q12:Q131) -> 105 | E17: =IFERROR(D17/(H8),0) -> 0.0079531567 | F17: 200 | G17: =IF(D17=0,"",D17-F17) -> -95 | J17: 6 | K17: 46266 | L17: Electricity | M17: Utilities | P17: 0.5 | Q17: =IFERROR(IF(O17="",0,O17*P17),0) -> 0 | R17: She pays | S17: Y
B18: Shopping | D18: =SUMIF(M12:M131,B18,Q12:Q131) -> 0 | E18: =IFERROR(D18/(H8),0) -> 0 | F18: 200 | G18: =IF(D18=0,"",D18-F18) | J18: 7 | K18: 46266 | L18: Twitch Sub | M18: Subscriptions | N18: CFF | O18: 5.99 | P18: 1 | Q18: =IFERROR(IF(O18="",0,O18*P18),0) -> 5.99 | R18: Auto-pay | S18: Y
B19: Subscriptions | D19: =SUMIF(M12:M131,B19,Q12:Q131) -> 65.62 | E19: =IFERROR(D19/(H8),0) -> 0.0049703442 | F19: 100 | G19: =IF(D19=0,"",D19-F19) -> -34.38 | J19: 8 | K19: 46266 | L19: Claude AI | M19: Subscriptions | N19: Robinhood | O19: 20 | P19: 1 | Q19: =IFERROR(IF(O19="",0,O19*P19),0) -> 20 | R19: Auto-pay | S19: Y
B20: Cash | D20: =SUMIF(M12:M131,B20,Q12:Q131) -> 0 | E20: =IFERROR(D20/(H8),0) -> 0 | F20: 100 | G20: =IF(D20=0,"",D20-F20) | J20: 9 | K20: 46266 | L20: Discord | M20: Subscriptions | N20: CFF | O20: 9.99 | P20: 1 | Q20: =IFERROR(IF(O20="",0,O20*P20),0) -> 9.99 | R20: Auto-pay | S20: Y
B21: Personal / Misc | D21: =SUMIF(M12:M131,B21,Q12:Q131) -> 0 | E21: =IFERROR(D21/(H8),0) -> 0 | F21: 50 | G21: =IF(D21=0,"",D21-F21) | J21: 10 | P21: 1 | Q21: =IFERROR(IF(O21="",0,O21*P21),0) -> 0
B22: Other | D22: =SUMIF(M12:M131,B22,Q12:Q131) -> 0 | E22: =IFERROR(D22/(H8),0) -> 0 | F22: 50 | G22: =IF(D22=0,"",D22-F22) | J22: 11 | P22: 1 | Q22: =IFERROR(IF(O22="",0,O22*P22),0) -> 0
B23: Travel | D23: =SUMIF($M$12:$M$131,B23,$Q$12:$Q$131) -> 0 | E23: =IFERROR(D23/(H8),0) -> 0 | J23: 12 | P23: 1 | Q23: =IFERROR(IF(O23="",0,O23*P23),0) -> 0
B24: Adjusted Rent | D24: =D60 -> 1090.075 | E24: =IFERROR(D24/(H8),0) -> 0.082567021 | J24: 13 | P24: 1 | Q24: =IFERROR(IF(O24="",0,O24*P24),0) -> 0
B25: Investment | D25: =D63 -> 0 | E25: =IFERROR(D25/(H8),0) -> 0 | J25: 14 | P25: 1 | Q25: =IFERROR(IF(O25="",0,O25*P25),0) -> 0
B26: TOTAL Going Out | D26: =D64 -> 1366.945 | E26: =IFERROR(D26/(H8),0) -> 0.10353836 | J26: 15 | P26: 1 | Q26: =IFERROR(IF(O26="",0,O26*P26),0) -> 0
B27: 💵 Money Left Over | D27: =D65 -> 11835.36 | E27: =IFERROR(D27/(H8),0) -> 0.89646164 | J27: 16 | P27: 1 | Q27: =IFERROR(IF(O27="",0,O27*P27),0) -> 0
J28: 17 | P28: 1 | Q28: =IFERROR(IF(O28="",0,O28*P28),0) -> 0
B29: Card | D29: Total This Month $ | J29: 18 | P29: 1 | Q29: =IFERROR(IF(O29="",0,O29*P29),0) -> 0
B30: CFF | D30: =SUMIF(N12:N131,B30,O12:O131) -> 15.98 | J30: 19 | P30: 1 | Q30: =IFERROR(IF(O30="",0,O30*P30),0) -> 0
B31: CFU | D31: =SUMIF(N12:N131,B31,O12:O131) -> 0 | J31: 20 | P31: 1 | Q31: =IFERROR(IF(O31="",0,O31*P31),0) -> 0
B32: CSP | D32: =SUMIF(N12:N131,B32,O12:O131) -> 0 | J32: 21 | P32: 1 | Q32: =IFERROR(IF(O32="",0,O32*P32),0) -> 0
B33: Discover | D33: =SUMIF(N12:N131,B33,O12:O131) -> 41.25 | J33: 22 | P33: 1 | Q33: =IFERROR(IF(O33="",0,O33*P33),0) -> 0
B34: Citi | D34: =SUMIF(N12:N131,B34,O12:O131) -> 0 | J34: 23 | P34: 1 | Q34: =IFERROR(IF(O34="",0,O34*P34),0) -> 0
B35: Capital One | D35: =SUMIF(N12:N131,B35,O12:O131) -> 21.99 | J35: 24 | P35: 1 | Q35: =IFERROR(IF(O35="",0,O35*P35),0) -> 0
B36: WF | D36: =SUMIF(N12:N131,B36,O12:O131) -> 0 | J36: 25 | P36: 1 | Q36: =IFERROR(IF(O36="",0,O36*P36),0) -> 0
B37: Amazon Card | D37: =SUMIF(N12:N131,B37,O12:O131) -> 7.65 | J37: 26 | P37: 1 | Q37: =IFERROR(IF(O37="",0,O37*P37),0) -> 0
B38: Robinhood | D38: =SUMIF(N12:N131,B38,O12:O131) -> 125 | J38: 27 | P38: 1 | Q38: =IFERROR(IF(O38="",0,O38*P38),0) -> 0
B39: Cash | D39: =SUMIF(N12:N131,B39,O12:O131) -> 65 | J39: 28 | P39: 1 | Q39: =IFERROR(IF(O39="",0,O39*P39),0) -> 0
B40: Other | D40: =SUMIF(N12:N131,B40,O12:O131) -> 0 | J40: 29 | P40: 1 | Q40: =IFERROR(IF(O40="",0,O40*P40),0) -> 0
B41: TOTAL CC CHARGES | D41: =SUM(D30:D40) -> 276.87 | J41: 30 | P41: 1 | Q41: =IFERROR(IF(O41="",0,O41*P41),0) -> 0
J42: 31 | P42: 1 | Q42: =IFERROR(IF(O42="",0,O42*P42),0) -> 0
B43: 📈 INVESTMENTS | J43: 32 | P43: 1 | Q43: =IFERROR(IF(O43="",0,O43*P43),0) -> 0
B44: Account | D44: Added This Month $ | F44: Invested $ | J44: 33 | P44: 1 | Q44: =IFERROR(IF(O44="",0,O44*P44),0) -> 0
B45: Robinhood Brokerage | D45: 0 | F45: ='Aug 2026'!F45+D45 -> 300 | J45: 34 | P45: 1 | Q45: =IFERROR(IF(O45="",0,O45*P45),0) -> 0
B46: Vanguard IRA | D46: 0 | J46: 35 | P46: 1 | Q46: =IFERROR(IF(O46="",0,O46*P46),0) -> 0
B47: 🏦 Ally Savings Buckets | J47: 36 | P47: 1 | Q47: =IFERROR(IF(O47="",0,O47*P47),0) -> 0
B48: Bucket | D48: Added This Month $ | F48: Balance $ | J48: 37 | P48: 1 | Q48: =IFERROR(IF(O48="",0,O48*P48),0) -> 0
B49: Wants | D49: 120 | F49: ='Aug 2026'!F49+D49 -> 4080 | J49: 38 | P49: 1 | Q49: =IFERROR(IF(O49="",0,O49*P49),0) -> 0
B50: Vacation | D50: 200 | F50: ='Aug 2026'!F50+D50 -> 8450 | J50: 39 | P50: 1 | Q50: =IFERROR(IF(O50="",0,O50*P50),0) -> 0
B51: Car Fund | D51: 400 | F51: ='Aug 2026'!F51+D51 -> 11600 | J51: 40 | P51: 1 | Q51: =IFERROR(IF(O51="",0,O51*P51),0) -> 0
B52: Emergency Fund | D52: 140 | F52: ='Aug 2026'!F52+D52 -> 6746.75 | J52: 41 | P52: 1 | Q52: =IFERROR(IF(O52="",0,O52*P52),0) -> 0
B53: Ally Total | D53: =SUM(D49:D52) -> 860 | F53: =SUM(F49:F52) -> 30876.75 | J53: 42 | P53: 1 | Q53: =IFERROR(IF(O53="",0,O53*P53),0) -> 0
B54: Total Invested (excl. Ally) | D54: =D45+D46 -> 0 | J54: 43 | P54: 1 | Q54: =IFERROR(IF(O54="",0,O54*P54),0) -> 0
J55: 44 | P55: 1 | Q55: =IFERROR(IF(O55="",0,O55*P55),0) -> 0
B56: 📈 MONTHLY SUMMARY | J56: 45 | P56: 1 | Q56: =IFERROR(IF(O56="",0,O56*P56),0) -> 0
B57: Total Monthly Income | D57: =H8 -> 13202.305 | J57: 46 | P57: 1 | Q57: =IFERROR(IF(O57="",0,O57*P57),0) -> 0
B58: Your Base Rent Share | D58: =D7*H7 -> 1110.7 | J58: 47 | P58: 1 | Q58: =IFERROR(IF(O58="",0,O58*P58),0) -> 0
B59: You Covered (partner's share ↓ your rent) | D59: =SUMPRODUCT((N12:N131<>"")*O12:O131*(1-P12:P131)) -> 20.625 | J59: 48 | P59: 1 | Q59: =IFERROR(IF(O59="",0,O59*P59),0) -> 0
B60: Your Rent After Adjustment | D60: =MAX(D7*H7-SUMPRODUCT((N12:N131<>"")*O12:O131*(1-P12:P131))+SUMPRODUCT((N12:N131="")*(O12:O131>0)*Q12:Q131),0) -> 1090.075 | J60: 49 | P60: 1 | Q60: =IFERROR(IF(O60="",0,O60*P60),0) -> 0
J61: 50 | P61: 1 | Q61: =IFERROR(IF(O61="",0,O61*P61),0) -> 0
B62: Total CC Charges | D62: =D41 -> 276.87 | J62: 51 | P62: 1 | Q62: =IFERROR(IF(O62="",0,O62*P62),0) -> 0
B63: Total Invested (excl. Ally) | D63: =D45+D46 -> 0 | J63: 52 | P63: 1 | Q63: =IFERROR(IF(O63="",0,O63*P63),0) -> 0
B64: TOTAL GOING OUT | D64: =D60+D62+D63 -> 1366.945 | J64: 53 | P64: 1 | Q64: =IFERROR(IF(O64="",0,O64*P64),0) -> 0
B65: 💵 MONEY LEFT OVER | D65: =H8-D64 -> 11835.36 | J65: 54 | P65: 1 | Q65: =IFERROR(IF(O65="",0,O65*P65),0) -> 0
J66: 55 | P66: 1 | Q66: =IFERROR(IF(O66="",0,O66*P66),0) -> 0
B67: 🔁 PARTNER BALANCE | J67: 56 | P67: 1 | Q67: =IFERROR(IF(O67="",0,O67*P67),0) -> 0
B68: Sharon Base Rent Share | D68: =D7*(1-H7) -> 1110.7 | J68: 57 | P68: 1 | Q68: =IFERROR(IF(O68="",0,O68*P68),0) -> 0
B69: She Covered (your share ↑ her rent) | D69: =SUMPRODUCT((N12:N131="")*(O12:O131>0)*Q12:Q131) -> 0 | J69: 58 | P69: 1 | Q69: =IFERROR(IF(O69="",0,O69*P69),0) -> 0
B70: You Covered (partner's share ↓ your rent) | D70: =SUMPRODUCT((N12:N131<>"")*O12:O131*(1-P12:P131)) -> 20.625 | J70: 59 | P70: 1 | Q70: =IFERROR(IF(O70="",0,O70*P70),0) -> 0
B71: Sharon's Total Rent This Month | D71: =MAX(D7*(1-H7)+SUMPRODUCT((N12:N131<>"")*O12:O131*(1-P12:P131))-SUMPRODUCT((N12:N131="")*(O12:O131>0)*Q12:Q131),0) -> 1131.325 | J71: 60 | P71: 1 | Q71: =IFERROR(IF(O71="",0,O71*P71),0) -> 0
B72: You Owe Sharon (if she overpaid) | D72: =MAX(SUMPRODUCT((N12:N131="")*(O12:O131>0)*Q12:Q131)-D7*(1-H7),0) -> 0 | J72: 61 | P72: 1 | Q72: =IFERROR(IF(O72="",0,O72*P72),0) -> 0
J73: 62 | P73: 1 | Q73: =IFERROR(IF(O73="",0,O73*P73),0) -> 0
J74: 63 | P74: 1 | Q74: =IFERROR(IF(O74="",0,O74*P74),0) -> 0
J75: 64 | P75: 1 | Q75: =IFERROR(IF(O75="",0,O75*P75),0) -> 0
J76: 65 | P76: 1 | Q76: =IFERROR(IF(O76="",0,O76*P76),0) -> 0
J77: 66 | P77: 1 | Q77: =IFERROR(IF(O77="",0,O77*P77),0) -> 0
J78: 67 | P78: 1 | Q78: =IFERROR(IF(O78="",0,O78*P78),0) -> 0
J79: 68 | P79: 1 | Q79: =IFERROR(IF(O79="",0,O79*P79),0) -> 0
J80: 69 | P80: 1 | Q80: =IFERROR(IF(O80="",0,O80*P80),0) -> 0
J81: 70 | P81: 1 | Q81: =IFERROR(IF(O81="",0,O81*P81),0) -> 0
J82: 71 | P82: 1 | Q82: =IFERROR(IF(O82="",0,O82*P82),0) -> 0
J83: 72 | P83: 1 | Q83: =IFERROR(IF(O83="",0,O83*P83),0) -> 0
J84: 73 | P84: 1 | Q84: =IFERROR(IF(O84="",0,O84*P84),0) -> 0
... J130: 119 | P130: 1 | Q130: =IFERROR(IF(O130="",0,O130*P130),0) -> 0
J131: 120 | P131: 1 | Q131: =IFERROR(IF(O132="",0,O132*P132),0) -> 0
L132: LOG TOTALS | O132: =SUM(O12:O131) -> 276.87 | Q132: =SUM(Q12:Q131) -> 256.245

Sheet Oct 2026
B2: 💰 Oct 2026 — Expense Tracker
B3: LEFT: summaries auto-update | RIGHT: log every transaction | Blue cells = enter data
B5: ⚙️ SETTINGS
B6: Paycheck #1 (mid-mo) | D6: 2500 | F6: Paycheck #2 (end-mo) | H6: 2500
B7: Full Monthly Rent | D7: 2221.4 | F7: Your Rent Split % | H7: 0.5
B8: Monthly Savings Goal | D8: 500 | F8: Total Monthly Income | H8: =D6+H6+D9 -> 16835.36
B9: Carried Over (prior month) | D9: ='Sep 2026'!D65 -> 11835.36
B10: 📊 CATEGORY SUMMARY | J10: 📋 EXPENSE LOG — Enter every transaction here
B11: Category | D11: Your Share $ | E11: % Income | F11: Budget $ | G11: vs Budget | J11: # | K11: Date | L11: Description | M11: Category | N11: Credit Card | O11: Total $ | P11: Split % | Q11: Your Share $ | R11: Notes / Memo | S11: Recurring?
B12: Groceries | D12: =SUMIF(M12:M131,B12,Q12:Q131) -> 0 | E12: =IFERROR(D12/(H8),0) -> 0 | F12: 300 | G12: =IF(D12=0,"",D12-F12) | J12: 1 | K12: 46296 | L12: Car Insurance | M12: Gas / Transport | N12: Cash | O12: 65 | P12: 1 | Q12: =IFERROR(IF(O12="",0,O12*P12),0) -> 65 | R12: Auto-pay | S12: Y
B13: Utilities | D13: =SUMIF(M12:M131,B13,Q12:Q131) -> 105.625 | E13: =IFERROR(D13/(H8),0) -> 0.0062739971 | F13: 50 | G13: =IF(D13=0,"",D13-F13) -> 55.625 | J13: 2 | K13: 46296 | L13: Stronghold | M13: Health | N13: Robinhood | O13: 105 | P13: 1 | Q13: =IFERROR(IF(O13="",0,O13*P13),0) -> 105 | R13: Auto-pay | S13: Y
B14: Gas / Transport | D14: =SUMIF(M12:M131,B14,Q12:Q131) -> 65 | E14: =IFERROR(D14/(H8),0) -> 0.0038609213 | F14: 200 | G14: =IF(D14=0,"",D14-F14) -> -135 | J14: 3 | K14: 46296 | L14: Spectrum Internet | M14: Utilities | N14: Discover | O14: 41.25 | P14: 0.5 | Q14: =IFERROR(IF(O14="",0,O14*P14),0) -> 20.625 | R14: Auto-pay | S14: Y
B15: Dining / Takeout | D15: =SUMIF(M12:M131,B15,Q12:Q131) -> 0 | E15: =IFERROR(D15/(H8),0) -> 0 | F15: 300 | G15: =IF(D15=0,"",D15-F15) | J15: 4 | K15: 46296 | L15: Amazon Prime | M15: Subscriptions | N15: Amazon Card | O15: 7.65 | P15: 1 | Q15: =IFERROR(IF(O15="",0,O15*P15),0) -> 7.65 | R15: Auto-pay | S15: Y
B16: Entertainment | D16: =SUMIF(M12:M131,B16,Q12:Q131) -> 0 | E16: =IFERROR(D16/(H8),0) -> 0 | F16: 150 | G16: =IF(D16=0,"",D16-F16) | J16: 5 | K16: 46296 | L16: Spotify | M16: Subscriptions | N16: Capital One | O16: 21.99 | P16: 1 | Q16: =IFERROR(IF(O16="",0,O16*P16),0) -> 21.99 | R16: Auto-pay | S16: Y
B17: Health | D17: =SUMIF(M12:M131,B17,Q12:Q131) -> 105 | E17: =IFERROR(D17/(H8),0) -> 0.0062368729 | F17: 200 | G17: =IF(D17=0,"",D17-F17) -> -95 | J17: 6 | K17: 46296 | L17: Electricity | M17: Utilities | O17: 170 | P17: 0.5 | Q17: =IFERROR(IF(O17="",0,O17*P17),0) -> 85 | R17: She pays | S17: Y
B18: Shopping | D18: =SUMIF(M12:M131,B18,Q12:Q131) -> 0 | E18: =IFERROR(D18/(H8),0) -> 0 | F18: 200 | G18: =IF(D18=0,"",D18-F18) | J18: 7 | K18: 46296 | L18: Twitch Sub | M18: Subscriptions | N18: CFF | O18: 5.99 | P18: 1 | Q18: =IFERROR(IF(O18="",0,O18*P18),0) -> 5.99 | R18: Auto-pay | S18: Y
B19: Subscriptions | D19: =SUMIF(M12:M131,B19,Q12:Q131) -> 65.62 | E19: =IFERROR(D19/(H8),0) -> 0.0038977485 | F19: 100 | G19: =IF(D19=0,"",D19-F19) -> -34.38 | J19: 8 | K19: 46296 | L19: Claude AI | M19: Subscriptions | N19: Robinhood | O19: 20 | P19: 1 | Q19: =IFERROR(IF(O19="",0,O19*P19),0) -> 20 | R19: Auto-pay | S19: Y
B20: Cash | D20: =SUMIF(M12:M131,B20,Q12:Q131) -> 0 | E20: =IFERROR(D20/(H8),0) -> 0 | F20: 100 | G20: =IF(D20=0,"",D20-F20) | J20: 9 | K20: 46296 | L20: Discord | M20: Subscriptions | N20: CFF | O20: 9.99 | P20: 1 | Q20: =IFERROR(IF(O20="",0,O20*P20),0) -> 9.99 | R20: Auto-pay | S20: Y
B21: Personal / Misc | D21: =SUMIF(M12:M131,B21,Q12:Q131) -> 0 | E21: =IFERROR(D21/(H8),0) -> 0 | F21: 50 | G21: =IF(D21=0,"",D21-F21) | J21: 10 | P21: 1 | Q21: =IFERROR(IF(O21="",0,O21*P21),0) -> 0
B22: Other | D22: =SUMIF(M12:M131,B22,Q12:Q131) -> 0 | E22: =IFERROR(D22/(H8),0) -> 0 | F22: 50 | G22: =IF(D22=0,"",D22-F22) | J22: 11 | P22: 1 | Q22: =IFERROR(IF(O22="",0,O22*P22),0) -> 0
B23: Travel | D23: =SUMIF($M$12:$M$131,B23,$Q$12:$Q$131) -> 0 | E23: =IFERROR(D23/(H8),0) -> 0 | J23: 12 | P23: 1 | Q23: =IFERROR(IF(O23="",0,O23*P23),0) -> 0
B24: Adjusted Rent | D24: =D60 -> 1175.075 | E24: =IFERROR(D24/(H8),0) -> 0.069798032 | J24: 13 | P24: 1 | Q24: =IFERROR(IF(O24="",0,O24*P24),0) -> 0
B25: Investment | D25: =D63 -> 0 | E25: =IFERROR(D25/(H8),0) -> 0 | J25: 14 | P25: 1 | Q25: =IFERROR(IF(O25="",0,O25*P25),0) -> 0
B26: TOTAL Going Out | D26: =D64 -> 1451.945 | E26: =IFERROR(D26/(H8),0) -> 0.086243775 | J26: 15 | P26: 1 | Q26: =IFERROR(IF(O26="",0,O26*P26),0) -> 0
B27: 💵 Money Left Over | D27: =D65 -> 15383.415 | E27: =IFERROR(D27/(H8),0) -> 0.91375622 | J27: 16 | P27: 1 | Q27: =IFERROR(IF(O27="",0,O27*P27),0) -> 0
J28: 17 | P28: 1 | Q28: =IFERROR(IF(O28="",0,O28*P28),0) -> 0
B29: Card | D29: Total This Month $ | J29: 18 | P29: 1 | Q29: =IFERROR(IF(O29="",0,O29*P29),0) -> 0
B30: CFF | D30: =SUMIF(N12:N131,B30,O12:O131) -> 15.98 | J30: 19 | P30: 1 | Q30: =IFERROR(IF(O30="",0,O30*P30),0) -> 0
B31: CFU | D31: =SUMIF(N12:N131,B31,O12:O131) -> 0 | J31: 20 | P31: 1 | Q31: =IFERROR(IF(O31="",0,O31*P31),0) -> 0
B32: CSP | D32: =SUMIF(N12:N131,B32,O12:O131) -> 0 | J32: 21 | P32: 1 | Q32: =IFERROR(IF(O32="",0,O32*P32),0) -> 0
B33: Discover | D33: =SUMIF(N12:N131,B33,O12:O131) -> 41.25 | J33: 22 | P33: 1 | Q33: =IFERROR(IF(O33="",0,O33*P33),0) -> 0
B34: Citi | D34: =SUMIF(N12:N131,B34,O12:O131) -> 0 | J34: 23 | P34: 1 | Q34: =IFERROR(IF(O34="",0,O34*P34),0) -> 0
B35: Capital One | D35: =SUMIF(N12:N131,B35,O12:O131) -> 21.99 | J35: 24 | P35: 1 | Q35: =IFERROR(IF(O35="",0,O35*P35),0) -> 0
B36: WF | D36: =SUMIF(N12:N131,B36,O12:O131) -> 0 | J36: 25 | P36: 1 | Q36: =IFERROR(IF(O36="",0,O36*P36),0) -> 0
B37: Amazon Card | D37: =SUMIF(N12:N131,B37,O12:O131) -> 7.65 | J37: 26 | P37: 1 | Q37: =IFERROR(IF(O37="",0,O37*P37),0) -> 0
B38: Robinhood | D38: =SUMIF(N12:N131,B38,O12:O131) -> 125 | J38: 27 | P38: 1 | Q38: =IFERROR(IF(O38="",0,O38*P38),0) -> 0
B39: Cash | D39: =SUMIF(N12:N131,B39,O12:O131) -> 65 | J39: 28 | P39: 1 | Q39: =IFERROR(IF(O39="",0,O39*P39),0) -> 0
B40: Other | D40: =SUMIF(N12:N131,B40,O12:O131) -> 0 | J40: 29 | P40: 1 | Q40: =IFERROR(IF(O40="",0,O40*P40),0) -> 0
B41: TOTAL CC CHARGES | D41: =SUM(D30:D40) -> 276.87 | J41: 30 | P41: 1 | Q41: =IFERROR(IF(O41="",0,O41*P41),0) -> 0
J42: 31 | P42: 1 | Q42: =IFERROR(IF(O42="",0,O42*P42),0) -> 0
B43: 📈 INVESTMENTS | J43: 32 | P43: 1 | Q43: =IFERROR(IF(O43="",0,O43*P43),0) -> 0
B44: Account | D44: Added This Month $ | F44: Invested $ | J44: 33 | P44: 1 | Q44: =IFERROR(IF(O44="",0,O44*P44),0) -> 0
B45: Robinhood Brokerage | D45: 0 | F45: ='Sep 2026'!F45+D45 -> 300 | J45: 34 | P45: 1 | Q45: =IFERROR(IF(O45="",0,O45*P45),0) -> 0
B46: Vanguard IRA | D46: 0 | J46: 35 | P46: 1 | Q46: =IFERROR(IF(O46="",0,O46*P46),0) -> 0
B47: 🏦 Ally Savings Buckets | J47: 36 | P47: 1 | Q47: =IFERROR(IF(O47="",0,O47*P47),0) -> 0
B48: Bucket | D48: Added This Month $ | F48: Balance $ | J48: 37 | P48: 1 | Q48: =IFERROR(IF(O48="",0,O48*P48),0) -> 0
B49: Wants | D49: 120 | F49: ='Sep 2026'!F49+D49 -> 4200 | J49: 38 | P49: 1 | Q49: =IFERROR(IF(O49="",0,O49*P49),0) -> 0
B50: Vacation | D50: 200 | F50: ='Sep 2026'!F50+D50 -> 8650 | J50: 39 | P50: 1 | Q50: =IFERROR(IF(O50="",0,O50*P50),0) -> 0
B51: Car Fund | D51: 400 | F51: ='Sep 2026'!F51+D51 -> 12000 | J51: 40 | P51: 1 | Q51: =IFERROR(IF(O51="",0,O51*P51),0) -> 0
B52: Emergency Fund | D52: 140 | F52: ='Sep 2026'!F52+D52 -> 6886.75 | J52: 41 | P52: 1 | Q52: =IFERROR(IF(O52="",0,O52*P52),0) -> 0
B53: Ally Total | D53: =SUM(D49:D52) -> 860 | F53: =SUM(F49:F52) -> 31736.75 | J53: 42 | P53: 1 | Q53: =IFERROR(IF(O53="",0,O53*P53),0) -> 0
B54: Total Invested (excl. Ally) | D54: =D45+D46 -> 0 | J54: 43 | P54: 1 | Q54: =IFERROR(IF(O54="",0,O54*P54),0) -> 0
J55: 44 | P55: 1 | Q55: =IFERROR(IF(O55="",0,O55*P55),0) -> 0
B56: 📈 MONTHLY SUMMARY | J56: 45 | P56: 1 | Q56: =IFERROR(IF(O56="",0,O56*P56),0) -> 0
B57: Total Monthly Income | D57: =H8 -> 16835.36 | J57: 46 | P57: 1 | Q57: =IFERROR(IF(O57="",0,O57*P57),0) -> 0
B58: Your Base Rent Share | D58: =D7*H7 -> 1110.7 | J58: 47 | P58: 1 | Q58: =IFERROR(IF(O58="",0,O58*P58),0) -> 0
B59: You Covered (partner's share ↓ your rent) | D59: =SUMPRODUCT((N12:N131<>"")*O12:O131*(1-P12:P131)) -> 20.625 | J59: 48 | P59: 1 | Q59: =IFERROR(IF(O59="",0,O59*P59),0) -> 0
B60: Your Rent After Adjustment | D60: =MAX(D7*H7-SUMPRODUCT((N12:N131<>"")*O12:O131*(1-P12:P131))+SUMPRODUCT((N12:N131="")*(O12:O131>0)*Q12:Q131),0) -> 1175.075 | J60: 49 | P60: 1 | Q60: =IFERROR(IF(O60="",0,O60*P60),0) -> 0
J61: 50 | P61: 1 | Q61: =IFERROR(IF(O61="",0,O61*P61),0) -> 0
B62: Total CC Charges | D62: =D41 -> 276.87 | J62: 51 | P62: 1 | Q62: =IFERROR(IF(O62="",0,O62*P62),0) -> 0
B63: Total Invested (excl. Ally) | D63: =D45+D46 -> 0 | J63: 52 | P63: 1 | Q63: =IFERROR(IF(O63="",0,O63*P63),0) -> 0
B64: TOTAL GOING OUT | D64: =D60+D62+D63 -> 1451.945 | J64: 53 | P64: 1 | Q64: =IFERROR(IF(O64="",0,O64*P64),0) -> 0
B65: 💵 MONEY LEFT OVER | D65: =H8-D64 -> 15383.415 | J65: 54 | P65: 1 | Q65: =IFERROR(IF(O65="",0,O65*P65),0) -> 0
J66: 55 | P66: 1 | Q66: =IFERROR(IF(O66="",0,O66*P66),0) -> 0
B67: 🔁 PARTNER BALANCE | J67: 56 | P67: 1 | Q67: =IFERROR(IF(O67="",0,O67*P67),0) -> 0
B68: Sharon Base Rent Share | D68: =D7*(1-H7) -> 1110.7 | J68: 57 | P68: 1 | Q68: =IFERROR(IF(O68="",0,O68*P68),0) -> 0
B69: She Covered (your share ↑ her rent) | D69: =SUMPRODUCT((N12:N131="")*(O12:O131>0)*Q12:Q131) -> 85 | J69: 58 | P69: 1 | Q69: =IFERROR(IF(O69="",0,O69*P69),0) -> 0
B70: You Covered (partner's share ↓ your rent) | D70: =SUMPRODUCT((N12:N131<>"")*O12:O131*(1-P12:P131)) -> 20.625 | J70: 59 | P70: 1 | Q70: =IFERROR(IF(O70="",0,O70*P70),0) -> 0
B71: Sharon's Total Rent This Month | D71: =MAX(D7*(1-H7)+SUMPRODUCT((N12:N131<>"")*O12:O131*(1-P12:P131))-SUMPRODUCT((N12:N131="")*(O12:O131>0)*Q12:Q131),0) -> 1046.325 | J71: 60 | P71: 1 | Q71: =IFERROR(IF(O71="",0,O71*P71),0) -> 0
B72: You Owe Sharon (if she overpaid) | D72: =MAX(SUMPRODUCT((N12:N131="")*(O12:O131>0)*Q12:Q131)-D7*(1-H7),0) -> 0 | J72: 61 | P72: 1 | Q72: =IFERROR(IF(O72="",0,O72*P72),0) -> 0
J73: 62 | P73: 1 | Q73: =IFERROR(IF(O73="",0,O73*P73),0) -> 0
J74: 63 | P74: 1 | Q74: =IFERROR(IF(O74="",0,O74*P74),0) -> 0
J75: 64 | P75: 1 | Q75: =IFERROR(IF(O75="",0,O75*P75),0) -> 0
J76: 65 | P76: 1 | Q76: =IFERROR(IF(O76="",0,O76*P76),0) -> 0
J77: 66 | P77: 1 | Q77: =IFERROR(IF(O77="",0,O77*P77),0) -> 0
J78: 67 | P78: 1 | Q78: =IFERROR(IF(O78="",0,O78*P78),0) -> 0
J79: 68 | P79: 1 | Q79: =IFERROR(IF(O79="",0,O79*P79),0) -> 0
J80: 69 | P80: 1 | Q80: =IFERROR(IF(O80="",0,O80*P80),0) -> 0
J81: 70 | P81: 1 | Q81: =IFERROR(IF(O81="",0,O81*P81),0) -> 0
J82: 71 | P82: 1 | Q82: =IFERROR(IF(O82="",0,O82*P82),0) -> 0
J83: 72 | P83: 1 | Q83: =IFERROR(IF(O83="",0,O83*P83),0) -> 0
J84: 73 | P84: 1 | Q84: =IFERROR(IF(O84="",0,O84*P84),0) -> 0
... J130: 119 | P130: 1 | Q130: =IFERROR(IF(O130="",0,O130*P130),0) -> 0
J131: 120 | P131: 1 | Q131: =IFERROR(IF(O132="",0,O132*P132),0) -> 0
L132: LOG TOTALS | O132: =SUM(O12:O131) -> 446.87 | Q132: =SUM(Q12:Q131) -> 341.245

Sheet Nov 2026
B2: 💰 Nov 2026 — Expense Tracker
B3: LEFT: summaries auto-update | RIGHT: log every transaction | Blue cells = enter data
B5: ⚙️ SETTINGS
B6: Paycheck #1 (mid-mo) | D6: 2500 | F6: Paycheck #2 (end-mo) | H6: 2500
B7: Full Monthly Rent | D7: 2221.4 | F7: Your Rent Split % | H7: 0.5
B8: Monthly Savings Goal | D8: 500 | F8: Total Monthly Income | H8: =D6+H6+D9 -> 20383.415
B9: Carried Over (prior month) | D9: ='Oct 2026'!D65 -> 15383.415
B10: 📊 CATEGORY SUMMARY | J10: 📋 EXPENSE LOG — Enter every transaction here
B11: Category | D11: Your Share $ | E11: % Income | F11: Budget $ | G11: vs Budget | J11: # | K11: Date | L11: Description | M11: Category | N11: Credit Card | O11: Total $ | P11: Split % | Q11: Your Share $ | R11: Notes / Memo | S11: Recurring?
B12: Groceries | D12: =SUMIF(M12:M131,B12,Q12:Q131) -> 0 | E12: =IFERROR(D12/(H8),0) -> 0 | F12: 300 | G12: =IF(D12=0,"",D12-F12) | J12: 1 | K12: 46327 | L12: Car Insurance | M12: Gas / Transport | N12: Cash | O12: 65 | P12: 1 | Q12: =IFERROR(IF(O12="",0,O12*P12),0) -> 65 | R12: Auto-pay | S12: Y
B13: Utilities | D13: =SUMIF(M12:M131,B13,Q12:Q131) -> 20.625 | E13: =IFERROR(D13/(H8),0) -> 0.001011852 | F13: 50 | G13: =IF(D13=0,"",D13-F13) -> -29.375 | J13: 2 | K13: 46327 | L13: Stronghold | M13: Health | N13: Robinhood | O13: 105 | P13: 1 | Q13: =IFERROR(IF(O13="",0,O13*P13),0) -> 105 | R13: Auto-pay | S13: Y
B14: Gas / Transport | D14: =SUMIF(M12:M131,B14,Q12:Q131) -> 65 | E14: =IFERROR(D14/(H8),0) -> 0.003188867 | F14: 200 | G14: =IF(D14=0,"",D14-F14) -> -135 | J14: 3 | K14: 46327 | L14: Spectrum Internet | M14: Utilities | N14: Discover | O14: 41.25 | P14: 0.5 | Q14: =IFERROR(IF(O14="",0,O14*P14),0) -> 20.625 | R14: Auto-pay | S14: Y
B15: Dining / Takeout | D15: =SUMIF(M12:M131,B15,Q12:Q131) -> 0 | E15: =IFERROR(D15/(H8),0) -> 0 | F15: 300 | G15: =IF(D15=0,"",D15-F15) | J15: 4 | K15: 46327 | L15: Amazon Prime | M15: Subscriptions | N15: Amazon Card | O15: 7.65 | P15: 1 | Q15: =IFERROR(IF(O15="",0,O15*P15),0) -> 7.65 | R15: Auto-pay | S15: Y
B16: Entertainment | D16: =SUMIF(M12:M131,B16,Q12:Q131) -> 0 | E16: =IFERROR(D16/(H8),0) -> 0 | F16: 150 | G16: =IF(D16=0,"",D16-F16) | J16: 5 | K16: 46327 | L16: Spotify | M16: Subscriptions | N16: Capital One | O16: 21.99 | P16: 1 | Q16: =IFERROR(IF(O16="",0,O16*P16),0) -> 21.99 | R16: Auto-pay | S16: Y
B17: Health | D17: =SUMIF(M12:M131,B17,Q12:Q131) -> 105 | E17: =IFERROR(D17/(H8),0) -> 0.0051512467 | F17: 200 | G17: =IF(D17=0,"",D17-F17) -> -95 | J17: 6 | K17: 46327 | L17: Electricity | M17: Utilities | P17: 0.5 | Q17: =IFERROR(IF(O17="",0,O17*P17),0) -> 0 | R17: She pays | S17: Y
B18: Shopping | D18: =SUMIF(M12:M131,B18,Q12:Q131) -> 0 | E18: =IFERROR(D18/(H8),0) -> 0 | F18: 200 | G18: =IF(D18=0,"",D18-F18) | J18: 7 | K18: 46327 | L18: Twitch Sub | M18: Subscriptions | N18: CFF | O18: 5.99 | P18: 1 | Q18: =IFERROR(IF(O18="",0,O18*P18),0) -> 5.99 | R18: Auto-pay | S18: Y
B19: Subscriptions | D19: =SUMIF(M12:M131,B19,Q12:Q131) -> 65.62 | E19: =IFERROR(D19/(H8),0) -> 0.0032192839 | F19: 100 | G19: =IF(D19=0,"",D19-F19) -> -34.38 | J19: 8 | K19: 46327 | L19: Claude AI | M19: Subscriptions | N19: Robinhood | O19: 20 | P19: 1 | Q19: =IFERROR(IF(O19="",0,O19*P19),0) -> 20 | R19: Auto-pay | S19: Y
B20: Cash | D20: =SUMIF(M12:M131,B20,Q12:Q131) -> 0 | E20: =IFERROR(D20/(H8),0) -> 0 | F20: 100 | G20: =IF(D20=0,"",D20-F20) | J20: 9 | K20: 46327 | L20: Discord | M20: Subscriptions | N20: CFF | O20: 9.99 | P20: 1 | Q20: =IFERROR(IF(O20="",0,O20*P20),0) -> 9.99 | R20: Auto-pay | S20: Y
B21: Personal / Misc | D21: =SUMIF(M12:M131,B21,Q12:Q131) -> 0 | E21: =IFERROR(D21/(H8),0) -> 0 | F21: 50 | G21: =IF(D21=0,"",D21-F21) | J21: 10 | P21: 1 | Q21: =IFERROR(IF(O21="",0,O21*P21),0) -> 0
B22: Other | D22: =SUMIF(M12:M131,B22,Q12:Q131) -> 0 | E22: =IFERROR(D22/(H8),0) -> 0 | F22: 50 | G22: =IF(D22=0,"",D22-F22) | J22: 11 | P22: 1 | Q22: =IFERROR(IF(O22="",0,O22*P22),0) -> 0
B23: Travel | D23: =SUMIF($M$12:$M$131,B23,$Q$12:$Q$131) -> 0 | E23: =IFERROR(D23/(H8),0) -> 0 | J23: 12 | P23: 1 | Q23: =IFERROR(IF(O23="",0,O23*P23),0) -> 0
B24: Adjusted Rent | D24: =D60 -> 1090.075 | E24: =IFERROR(D24/(H8),0) -> 0.053478527 | J24: 13 | P24: 1 | Q24: =IFERROR(IF(O24="",0,O24*P24),0) -> 0
B25: Investment | D25: =D63 -> 0 | E25: =IFERROR(D25/(H8),0) -> 0 | J25: 14 | P25: 1 | Q25: =IFERROR(IF(O25="",0,O25*P25),0) -> 0
B26: TOTAL Going Out | D26: =D64 -> 1366.945 | E26: =IFERROR(D26/(H8),0) -> 0.067061628 | J26: 15 | P26: 1 | Q26: =IFERROR(IF(O26="",0,O26*P26),0) -> 0
B27: 💵 Money Left Over | D27: =D65 -> 19016.47 | E27: =IFERROR(D27/(H8),0) -> 0.93293837 | J27: 16 | P27: 1 | Q27: =IFERROR(IF(O27="",0,O27*P27),0) -> 0
J28: 17 | P28: 1 | Q28: =IFERROR(IF(O28="",0,O28*P28),0) -> 0
B29: Card | D29: Total This Month $ | J29: 18 | P29: 1 | Q29: =IFERROR(IF(O29="",0,O29*P29),0) -> 0
B30: CFF | D30: =SUMIF(N12:N131,B30,O12:O131) -> 15.98 | J30: 19 | P30: 1 | Q30: =IFERROR(IF(O30="",0,O30*P30),0) -> 0
B31: CFU | D31: =SUMIF(N12:N131,B31,O12:O131) -> 0 | J31: 20 | P31: 1 | Q31: =IFERROR(IF(O31="",0,O31*P31),0) -> 0
B32: CSP | D32: =SUMIF(N12:N131,B32,O12:O131) -> 0 | J32: 21 | P32: 1 | Q32: =IFERROR(IF(O32="",0,O32*P32),0) -> 0
B33: Discover | D33: =SUMIF(N12:N131,B33,O12:O131) -> 41.25 | J33: 22 | P33: 1 | Q33: =IFERROR(IF(O33="",0,O33*P33),0) -> 0
B34: Citi | D34: =SUMIF(N12:N131,B34,O12:O131) -> 0 | J34: 23 | P34: 1 | Q34: =IFERROR(IF(O34="",0,O34*P34),0) -> 0
B35: Capital One | D35: =SUMIF(N12:N131,B35,O12:O131) -> 21.99 | J35: 24 | P35: 1 | Q35: =IFERROR(IF(O35="",0,O35*P35),0) -> 0
B36: WF | D36: =SUMIF(N12:N131,B36,O12:O131) -> 0 | J36: 25 | P36: 1 | Q36: =IFERROR(IF(O36="",0,O36*P36),0) -> 0
B37: Amazon Card | D37: =SUMIF(N12:N131,B37,O12:O131) -> 7.65 | J37: 26 | P37: 1 | Q37: =IFERROR(IF(O37="",0,O37*P37),0) -> 0
B38: Robinhood | D38: =SUMIF(N12:N131,B38,O12:O131) -> 125 | J38: 27 | P38: 1 | Q38: =IFERROR(IF(O38="",0,O38*P38),0) -> 0
B39: Cash | D39: =SUMIF(N12:N131,B39,O12:O131) -> 65 | J39: 28 | P39: 1 | Q39: =IFERROR(IF(O39="",0,O39*P39),0) -> 0
B40: Other | D40: =SUMIF(N12:N131,B40,O12:O131) -> 0 | J40: 29 | P40: 1 | Q40: =IFERROR(IF(O40="",0,O40*P40),0) -> 0
B41: TOTAL CC CHARGES | D41: =SUM(D30:D40) -> 276.87 | J41: 30 | P41: 1 | Q41: =IFERROR(IF(O41="",0,O41*P41),0) -> 0
J42: 31 | P42: 1 | Q42: =IFERROR(IF(O42="",0,O42*P42),0) -> 0
B43: 📈 INVESTMENTS | J43: 32 | P43: 1 | Q43: =IFERROR(IF(O43="",0,O43*P43),0) -> 0
B44: Account | D44: Added This Month $ | F44: Invested $ | J44: 33 | P44: 1 | Q44: =IFERROR(IF(O44="",0,O44*P44),0) -> 0
B45: Robinhood Brokerage | D45: 0 | F45: ='Oct 2026'!F45+D45 -> 300 | J45: 34 | P45: 1 | Q45: =IFERROR(IF(O45="",0,O45*P45),0) -> 0
B46: Vanguard IRA | D46: 0 | J46: 35 | P46: 1 | Q46: =IFERROR(IF(O46="",0,O46*P46),0) -> 0
B47: 🏦 Ally Savings Buckets | J47: 36 | P47: 1 | Q47: =IFERROR(IF(O47="",0,O47*P47),0) -> 0
B48: Bucket | D48: Added This Month $ | F48: Balance $ | J48: 37 | P48: 1 | Q48: =IFERROR(IF(O48="",0,O48*P48),0) -> 0
B49: Wants | D49: 120 | F49: ='Oct 2026'!F49+D49 -> 4320 | J49: 38 | P49: 1 | Q49: =IFERROR(IF(O49="",0,O49*P49),0) -> 0
B50: Vacation | D50: 200 | F50: ='Oct 2026'!F50+D50 -> 8850 | J50: 39 | P50: 1 | Q50: =IFERROR(IF(O50="",0,O50*P50),0) -> 0
B51: Car Fund | D51: 400 | F51: ='Oct 2026'!F51+D51 -> 12400 | J51: 40 | P51: 1 | Q51: =IFERROR(IF(O51="",0,O51*P51),0) -> 0
B52: Emergency Fund | D52: 140 | F52: ='Oct 2026'!F52+D52 -> 7026.75 | J52: 41 | P52: 1 | Q52: =IFERROR(IF(O52="",0,O52*P52),0) -> 0
B53: Ally Total | D53: =SUM(D49:D52) -> 860 | F53: =SUM(F49:F52) -> 32596.75 | J53: 42 | P53: 1 | Q53: =IFERROR(IF(O53="",0,O53*P53),0) -> 0
B54: Total Invested (excl. Ally) | D54: =D45+D46 -> 0 | J54: 43 | P54: 1 | Q54: =IFERROR(IF(O54="",0,O54*P54),0) -> 0
J55: 44 | P55: 1 | Q55: =IFERROR(IF(O55="",0,O55*P55),0) -> 0
B56: 📈 MONTHLY SUMMARY | J56: 45 | P56: 1 | Q56: =IFERROR(IF(O56="",0,O56*P56),0) -> 0
B57: Total Monthly Income | D57: =H8 -> 20383.415 | J57: 46 | P57: 1 | Q57: =IFERROR(IF(O57="",0,O57*P57),0) -> 0
B58: Your Base Rent Share | D58: =D7*H7 -> 1110.7 | J58: 47 | P58: 1 | Q58: =IFERROR(IF(O58="",0,O58*P58),0) -> 0
B59: You Covered (partner's share ↓ your rent) | D59: =SUMPRODUCT((N12:N131<>"")*O12:O131*(1-P12:P131)) -> 20.625 | J59: 48 | P59: 1 | Q59: =IFERROR(IF(O59="",0,O59*P59),0) -> 0
B60: Your Rent After Adjustment | D60: =MAX(D7*H7-SUMPRODUCT((N12:N131<>"")*O12:O131*(1-P12:P131))+SUMPRODUCT((N12:N131="")*(O12:O131>0)*Q12:Q131),0) -> 1090.075 | J60: 49 | P60: 1 | Q60: =IFERROR(IF(O60="",0,O60*P60),0) -> 0
J61: 50 | P61: 1 | Q61: =IFERROR(IF(O61="",0,O61*P61),0) -> 0
B62: Total CC Charges | D62: =D41 -> 276.87 | J62: 51 | P62: 1 | Q62: =IFERROR(IF(O62="",0,O62*P62),0) -> 0
B63: Total Invested (excl. Ally) | D63: =D45+D46 -> 0 | J63: 52 | P63: 1 | Q63: =IFERROR(IF(O63="",0,O63*P63),0) -> 0
B64: TOTAL GOING OUT | D64: =D60+D62+D63 -> 1366.945 | J64: 53 | P64: 1 | Q64: =IFERROR(IF(O64="",0,O64*P64),0) -> 0
B65: 💵 MONEY LEFT OVER | D65: =H8-D64 -> 19016.47 | J65: 54 | P65: 1 | Q65: =IFERROR(IF(O65="",0,O65*P65),0) -> 0
J66: 55 | P66: 1 | Q66: =IFERROR(IF(O66="",0,O66*P66),0) -> 0
B67: 🔁 PARTNER BALANCE | J67: 56 | P67: 1 | Q67: =IFERROR(IF(O67="",0,O67*P67),0) -> 0
B68: Sharon Base Rent Share | D68: =D7*(1-H7) -> 1110.7 | J68: 57 | P68: 1 | Q68: =IFERROR(IF(O68="",0,O68*P68),0) -> 0
B69: She Covered (your share ↑ her rent) | D69: =SUMPRODUCT((N12:N131="")*(O12:O131>0)*Q12:Q131) -> 0 | J69: 58 | P69: 1 | Q69: =IFERROR(IF(O69="",0,O69*P69),0) -> 0
B70: You Covered (partner's share ↓ your rent) | D70: =SUMPRODUCT((N12:N131<>"")*O12:O131*(1-P12:P131)) -> 20.625 | J70: 59 | P70: 1 | Q70: =IFERROR(IF(O70="",0,O70*P70),0) -> 0
B71: Sharon's Total Rent This Month | D71: =MAX(D7*(1-H7)+SUMPRODUCT((N12:N131<>"")*O12:O131*(1-P12:P131))-SUMPRODUCT((N12:N131="")*(O12:O131>0)*Q12:Q131),0) -> 1131.325 | J71: 60 | P71: 1 | Q71: =IFERROR(IF(O71="",0,O71*P71),0) -> 0
B72: You Owe Sharon (if she overpaid) | D72: =MAX(SUMPRODUCT((N12:N131="")*(O12:O131>0)*Q12:Q131)-D7*(1-H7),0) -> 0 | J72: 61 | P72: 1 | Q72: =IFERROR(IF(O72="",0,O72*P72),0) -> 0
J73: 62 | P73: 1 | Q73: =IFERROR(IF(O73="",0,O73*P73),0) -> 0
J74: 63 | P74: 1 | Q74: =IFERROR(IF(O74="",0,O74*P74),0) -> 0
J75: 64 | P75: 1 | Q75: =IFERROR(IF(O75="",0,O75*P75),0) -> 0
J76: 65 | P76: 1 | Q76: =IFERROR(IF(O76="",0,O76*P76),0) -> 0
J77: 66 | P77: 1 | Q77: =IFERROR(IF(O77="",0,O77*P77),0) -> 0
J78: 67 | P78: 1 | Q78: =IFERROR(IF(O78="",0,O78*P78),0) -> 0
J79: 68 | P79: 1 | Q79: =IFERROR(IF(O79="",0,O79*P79),0) -> 0
J80: 69 | P80: 1 | Q80: =IFERROR(IF(O80="",0,O80*P80),0) -> 0
J81: 70 | P81: 1 | Q81: =IFERROR(IF(O81="",0,O81*P81),0) -> 0
J82: 71 | P82: 1 | Q82: =IFERROR(IF(O82="",0,O82*P82),0) -> 0
J83: 72 | P83: 1 | Q83: =IFERROR(IF(O83="",0,O83*P83),0) -> 0
J84: 73 | P84: 1 | Q84: =IFERROR(IF(O84="",0,O84*P84),0) -> 0
... J130: 119 | P130: 1 | Q130: =IFERROR(IF(O130="",0,O130*P130),0) -> 0
J131: 120 | P131: 1 | Q131: =IFERROR(IF(O132="",0,O132*P132),0) -> 0
L132: LOG TOTALS | O132: =SUM(O12:O131) -> 276.87 | Q132: =SUM(Q12:Q131) -> 256.245

Sheet Dec 2026
B2: 💰 Dec 2026 — Expense Tracker
B3: LEFT: summaries auto-update | RIGHT: log every transaction | Blue cells = enter data
B5: ⚙️ SETTINGS
B6: Paycheck #1 (mid-mo) | D6: 2500 | F6: Paycheck #2 (end-mo) | H6: 2500
B7: Full Monthly Rent | D7: 2221.4 | F7: Your Rent Split % | H7: 0.5
B8: Monthly Savings Goal | D8: 500 | F8: Total Monthly Income | H8: =D6+H6+D9 -> 24016.47
B9: Carried Over (prior month) | D9: ='Nov 2026'!D65 -> 19016.47
B10: 📊 CATEGORY SUMMARY | J10: 📋 EXPENSE LOG — Enter every transaction here
B11: Category | D11: Your Share $ | E11: % Income | F11: Budget $ | G11: vs Budget | J11: # | K11: Date | L11: Description | M11: Category | N11: Credit Card | O11: Total $ | P11: Split % | Q11: Your Share $ | R11: Notes / Memo | S11: Recurring?
B12: Groceries | D12: =SUMIF(M12:M131,B12,Q12:Q131) -> 0 | E12: =IFERROR(D12/(H8),0) -> 0 | F12: 300 | G12: =IF(D12=0,"",D12-F12) | J12: 1 | K12: 46357 | L12: Car Insurance | M12: Gas / Transport | N12: Cash | O12: 65 | P12: 1 | Q12: =IFERROR(IF(O12="",0,O12*P12),0) -> 65 | R12: Auto-pay | S12: Y
B13: Utilities | D13: =SUMIF(M12:M131,B13,Q12:Q131) -> 105.625 | E13: =IFERROR(D13/(H8),0) -> 0.0043980235 | F13: 50 | G13: =IF(D13=0,"",D13-F13) -> 55.625 | J13: 2 | K13: 46357 | L13: Stronghold | M13: Health | N13: Robinhood | O13: 105 | P13: 1 | Q13: =IFERROR(IF(O13="",0,O13*P13),0) -> 105 | R13: Auto-pay | S13: Y
B14: Gas / Transport | D14: =SUMIF(M12:M131,B14,Q12:Q131) -> 65 | E14: =IFERROR(D14/(H8),0) -> 0.002706476 | F14: 200 | G14: =IF(D14=0,"",D14-F14) -> -135 | J14: 3 | K14: 46357 | L14: Spectrum Internet | M14: Utilities | N14: Discover | O14: 41.25 | P14: 0.5 | Q14: =IFERROR(IF(O14="",0,O14*P14),0) -> 20.625 | R14: Auto-pay | S14: Y
B15: Dining / Takeout | D15: =SUMIF(M12:M131,B15,Q12:Q131) -> 0 | E15: =IFERROR(D15/(H8),0) -> 0 | F15: 300 | G15: =IF(D15=0,"",D15-F15) | J15: 4 | K15: 46357 | L15: Amazon Prime | M15: Subscriptions | N15: Amazon Card | O15: 7.65 | P15: 1 | Q15: =IFERROR(IF(O15="",0,O15*P15),0) -> 7.65 | R15: Auto-pay | S15: Y
B16: Entertainment | D16: =SUMIF(M12:M131,B16,Q12:Q131) -> 0 | E16: =IFERROR(D16/(H8),0) -> 0 | F16: 150 | G16: =IF(D16=0,"",D16-F16) | J16: 5 | K16: 46357 | L16: Spotify | M16: Subscriptions | N16: Capital One | O16: 21.99 | P16: 1 | Q16: =IFERROR(IF(O16="",0,O16*P16),0) -> 21.99 | R16: Auto-pay | S16: Y
B17: Health | D17: =SUMIF(M12:M131,B17,Q12:Q131) -> 105 | E17: =IFERROR(D17/(H8),0) -> 0.0043719997 | F17: 200 | G17: =IF(D17=0,"",D17-F17) -> -95 | J17: 6 | K17: 46357 | L17: Electricity | M17: Utilities | O17: 170 | P17: 0.5 | Q17: =IFERROR(IF(O17="",0,O17*P17),0) -> 85 | R17: She pays | S17: Y
B18: Shopping | D18: =SUMIF(M12:M131,B18,Q12:Q131) -> 0 | E18: =IFERROR(D18/(H8),0) -> 0 | F18: 200 | G18: =IF(D18=0,"",D18-F18) | J18: 7 | K18: 46357 | L18: Twitch Sub | M18: Subscriptions | N18: CFF | O18: 5.99 | P18: 1 | Q18: =IFERROR(IF(O18="",0,O18*P18),0) -> 5.99 | R18: Auto-pay | S18: Y
B19: Subscriptions | D19: =SUMIF(M12:M131,B19,Q12:Q131) -> 65.62 | E19: =IFERROR(D19/(H8),0) -> 0.0027322916 | F19: 100 | G19: =IF(D19=0,"",D19-F19) -> -34.38 | J19: 8 | K19: 46357 | L19: Claude AI | M19: Subscriptions | N19: Robinhood | O19: 20 | P19: 1 | Q19: =IFERROR(IF(O19="",0,O19*P19),0) -> 20 | R19: Auto-pay | S19: Y
B20: Cash | D20: =SUMIF(M12:M131,B20,Q12:Q131) -> 0 | E20: =IFERROR(D20/(H8),0) -> 0 | F20: 100 | G20: =IF(D20=0,"",D20-F20) | J20: 9 | K20: 46357 | L20: Discord | M20: Subscriptions | N20: CFF | O20: 9.99 | P20: 1 | Q20: =IFERROR(IF(O20="",0,O20*P20),0) -> 9.99 | R20: Auto-pay | S20: Y
B21: Personal / Misc | D21: =SUMIF(M12:M131,B21,Q12:Q131) -> 0 | E21: =IFERROR(D21/(H8),0) -> 0 | F21: 50 | G21: =IF(D21=0,"",D21-F21) | J21: 10 | P21: 1 | Q21: =IFERROR(IF(O21="",0,O21*P21),0) -> 0
B22: Other | D22: =SUMIF(M12:M131,B22,Q12:Q131) -> 0 | E22: =IFERROR(D22/(H8),0) -> 0 | F22: 50 | G22: =IF(D22=0,"",D22-F22) | J22: 11 | P22: 1 | Q22: =IFERROR(IF(O22="",0,O22*P22),0) -> 0
B23: Travel | D23: =SUMIF($M$12:$M$131,B23,$Q$12:$Q$131) -> 0 | E23: =IFERROR(D23/(H8),0) -> 0 | J23: 12 | P23: 1 | Q23: =IFERROR(IF(O23="",0,O23*P23),0) -> 0
B24: Adjusted Rent | D24: =D60 -> 1175.075 | E24: =IFERROR(D24/(H8),0) -> 0.048927882 | J24: 13 | P24: 1 | Q24: =IFERROR(IF(O24="",0,O24*P24),0) -> 0
B25: Investment | D25: =D63 -> 0 | E25: =IFERROR(D25/(H8),0) -> 0 | J25: 14 | P25: 1 | Q25: =IFERROR(IF(O25="",0,O25*P25),0) -> 0
B26: TOTAL Going Out | D26: =D64 -> 1451.945 | E26: =IFERROR(D26/(H8),0) -> 0.06045622 | J26: 15 | P26: 1 | Q26: =IFERROR(IF(O26="",0,O26*P26),0) -> 0
B27: 💵 Money Left Over | D27: =D65 -> 22564.525 | E27: =IFERROR(D27/(H8),0) -> 0.93954378 | J27: 16 | P27: 1 | Q27: =IFERROR(IF(O27="",0,O27*P27),0) -> 0
J28: 17 | P28: 1 | Q28: =IFERROR(IF(O28="",0,O28*P28),0) -> 0
B29: Card | D29: Total This Month $ | J29: 18 | P29: 1 | Q29: =IFERROR(IF(O29="",0,O29*P29),0) -> 0
B30: CFF | D30: =SUMIF(N12:N131,B30,O12:O131) -> 15.98 | J30: 19 | P30: 1 | Q30: =IFERROR(IF(O30="",0,O30*P30),0) -> 0
B31: CFU | D31: =SUMIF(N12:N131,B31,O12:O131) -> 0 | J31: 20 | P31: 1 | Q31: =IFERROR(IF(O31="",0,O31*P31),0) -> 0
B32: CSP | D32: =SUMIF(N12:N131,B32,O12:O131) -> 0 | J32: 21 | P32: 1 | Q32: =IFERROR(IF(O32="",0,O32*P32),0) -> 0
B33: Discover | D33: =SUMIF(N12:N131,B33,O12:O131) -> 41.25 | J33: 22 | P33: 1 | Q33: =IFERROR(IF(O33="",0,O33*P33),0) -> 0
B34: Citi | D34: =SUMIF(N12:N131,B34,O12:O131) -> 0 | J34: 23 | P34: 1 | Q34: =IFERROR(IF(O34="",0,O34*P34),0) -> 0
B35: Capital One | D35: =SUMIF(N12:N131,B35,O12:O131) -> 21.99 | J35: 24 | P35: 1 | Q35: =IFERROR(IF(O35="",0,O35*P35),0) -> 0
B36: WF | D36: =SUMIF(N12:N131,B36,O12:O131) -> 0 | J36: 25 | P36: 1 | Q36: =IFERROR(IF(O36="",0,O36*P36),0) -> 0
B37: Amazon Card | D37: =SUMIF(N12:N131,B37,O12:O131) -> 7.65 | J37: 26 | P37: 1 | Q37: =IFERROR(IF(O37="",0,O37*P37),0) -> 0
B38: Robinhood | D38: =SUMIF(N12:N131,B38,O12:O131) -> 125 | J38: 27 | P38: 1 | Q38: =IFERROR(IF(O38="",0,O38*P38),0) -> 0
B39: Cash | D39: =SUMIF(N12:N131,B39,O12:O131) -> 65 | J39: 28 | P39: 1 | Q39: =IFERROR(IF(O39="",0,O39*P39),0) -> 0
B40: Other | D40: =SUMIF(N12:N131,B40,O12:O131) -> 0 | J40: 29 | P40: 1 | Q40: =IFERROR(IF(O40="",0,O40*P40),0) -> 0
B41: TOTAL CC CHARGES | D41: =SUM(D30:D40) -> 276.87 | J41: 30 | P41: 1 | Q41: =IFERROR(IF(O41="",0,O41*P41),0) -> 0
J42: 31 | P42: 1 | Q42: =IFERROR(IF(O42="",0,O42*P42),0) -> 0
B43: 📈 INVESTMENTS | J43: 32 | P43: 1 | Q43: =IFERROR(IF(O43="",0,O43*P43),0) -> 0
B44: Account | D44: Added This Month $ | F44: Invested $ | J44: 33 | P44: 1 | Q44: =IFERROR(IF(O44="",0,O44*P44),0) -> 0
B45: Robinhood Brokerage | D45: 0 | F45: ='Nov 2026'!F45+D45 -> 300 | J45: 34 | P45: 1 | Q45: =IFERROR(IF(O45="",0,O45*P45),0) -> 0
B46: Vanguard IRA | D46: 0 | J46: 35 | P46: 1 | Q46: =IFERROR(IF(O46="",0,O46*P46),0) -> 0
B47: 🏦 Ally Savings Buckets | J47: 36 | P47: 1 | Q47: =IFERROR(IF(O47="",0,O47*P47),0) -> 0
B48: Bucket | D48: Added This Month $ | F48: Balance $ | J48: 37 | P48: 1 | Q48: =IFERROR(IF(O48="",0,O48*P48),0) -> 0
B49: Wants | D49: 120 | F49: ='Nov 2026'!F49+D49 -> 4440 | J49: 38 | P49: 1 | Q49: =IFERROR(IF(O49="",0,O49*P49),0) -> 0
B50: Vacation | D50: 200 | F50: ='Nov 2026'!F50+D50 -> 9050 | J50: 39 | P50: 1 | Q50: =IFERROR(IF(O50="",0,O50*P50),0) -> 0
B51: Car Fund | D51: 400 | F51: ='Nov 2026'!F51+D51 -> 12800 | J51: 40 | P51: 1 | Q51: =IFERROR(IF(O51="",0,O51*P51),0) -> 0
B52: Emergency Fund | D52: 140 | F52: ='Nov 2026'!F52+D52 -> 7166.75 | J52: 41 | P52: 1 | Q52: =IFERROR(IF(O52="",0,O52*P52),0) -> 0
B53: Ally Total | D53: =SUM(D49:D52) -> 860 | F53: =SUM(F49:F52) -> 33456.75 | J53: 42 | P53: 1 | Q53: =IFERROR(IF(O53="",0,O53*P53),0) -> 0
B54: Total Invested (excl. Ally) | D54: =D45+D46 -> 0 | J54: 43 | P54: 1 | Q54: =IFERROR(IF(O54="",0,O54*P54),0) -> 0
J55: 44 | P55: 1 | Q55: =IFERROR(IF(O55="",0,O55*P55),0) -> 0
B56: 📈 MONTHLY SUMMARY | J56: 45 | P56: 1 | Q56: =IFERROR(IF(O56="",0,O56*P56),0) -> 0
B57: Total Monthly Income | D57: =H8 -> 24016.47 | J57: 46 | P57: 1 | Q57: =IFERROR(IF(O57="",0,O57*P57),0) -> 0
B58: Your Base Rent Share | D58: =D7*H7 -> 1110.7 | J58: 47 | P58: 1 | Q58: =IFERROR(IF(O58="",0,O58*P58),0) -> 0
B59: You Covered (partner's share ↓ your rent) | D59: =SUMPRODUCT((N12:N131<>"")*O12:O131*(1-P12:P131)) -> 20.625 | J59: 48 | P59: 1 | Q59: =IFERROR(IF(O59="",0,O59*P59),0) -> 0
B60: Your Rent After Adjustment | D60: =MAX(D7*H7-SUMPRODUCT((N12:N131<>"")*O12:O131*(1-P12:P131))+SUMPRODUCT((N12:N131="")*(O12:O131>0)*Q12:Q131),0) -> 1175.075 | J60: 49 | P60: 1 | Q60: =IFERROR(IF(O60="",0,O60*P60),0) -> 0
J61: 50 | P61: 1 | Q61: =IFERROR(IF(O61="",0,O61*P61),0) -> 0
B62: Total CC Charges | D62: =D41 -> 276.87 | J62: 51 | P62: 1 | Q62: =IFERROR(IF(O62="",0,O62*P62),0) -> 0
B63: Total Invested (excl. Ally) | D63: =D45+D46 -> 0 | J63: 52 | P63: 1 | Q63: =IFERROR(IF(O63="",0,O63*P63),0) -> 0
B64: TOTAL GOING OUT | D64: =D60+D62+D63 -> 1451.945 | J64: 53 | P64: 1 | Q64: =IFERROR(IF(O64="",0,O64*P64),0) -> 0
B65: 💵 MONEY LEFT OVER | D65: =H8-D64 -> 22564.525 | J65: 54 | P65: 1 | Q65: =IFERROR(IF(O65="",0,O65*P65),0) -> 0
J66: 55 | P66: 1 | Q66: =IFERROR(IF(O66="",0,O66*P66),0) -> 0
B67: 🔁 PARTNER BALANCE | J67: 56 | P67: 1 | Q67: =IFERROR(IF(O67="",0,O67*P67),0) -> 0
B68: Sharon Base Rent Share | D68: =D7*(1-H7) -> 1110.7 | J68: 57 | P68: 1 | Q68: =IFERROR(IF(O68="",0,O68*P68),0) -> 0
B69: She Covered (your share ↑ her rent) | D69: =SUMPRODUCT((N12:N131="")*(O12:O131>0)*Q12:Q131) -> 85 | J69: 58 | P69: 1 | Q69: =IFERROR(IF(O69="",0,O69*P69),0) -> 0
B70: You Covered (partner's share ↓ your rent) | D70: =SUMPRODUCT((N12:N131<>"")*O12:O131*(1-P12:P131)) -> 20.625 | J70: 59 | P70: 1 | Q70: =IFERROR(IF(O70="",0,O70*P70),0) -> 0
B71: Sharon's Total Rent This Month | D71: =MAX(D7*(1-H7)+SUMPRODUCT((N12:N131<>"")*O12:O131*(1-P12:P131))-SUMPRODUCT((N12:N131="")*(O12:O131>0)*Q12:Q131),0) -> 1046.325 | J71: 60 | P71: 1 | Q71: =IFERROR(IF(O71="",0,O71*P71),0) -> 0
B72: You Owe Sharon (if she overpaid) | D72: =MAX(SUMPRODUCT((N12:N131="")*(O12:O131>0)*Q12:Q131)-D7*(1-H7),0) -> 0 | J72: 61 | P72: 1 | Q72: =IFERROR(IF(O72="",0,O72*P72),0) -> 0
J73: 62 | P73: 1 | Q73: =IFERROR(IF(O73="",0,O73*P73),0) -> 0
J74: 63 | P74: 1 | Q74: =IFERROR(IF(O74="",0,O74*P74),0) -> 0
J75: 64 | P75: 1 | Q75: =IFERROR(IF(O75="",0,O75*P75),0) -> 0
J76: 65 | P76: 1 | Q76: =IFERROR(IF(O76="",0,O76*P76),0) -> 0
J77: 66 | P77: 1 | Q77: =IFERROR(IF(O77="",0,O77*P77),0) -> 0
J78: 67 | P78: 1 | Q78: =IFERROR(IF(O78="",0,O78*P78),0) -> 0
J79: 68 | P79: 1 | Q79: =IFERROR(IF(O79="",0,O79*P79),0) -> 0
J80: 69 | P80: 1 | Q80: =IFERROR(IF(O80="",0,O80*P80),0) -> 0
J81: 70 | P81: 1 | Q81: =IFERROR(IF(O81="",0,O81*P81),0) -> 0
J82: 71 | P82: 1 | Q82: =IFERROR(IF(O82="",0,O82*P82),0) -> 0
J83: 72 | P83: 1 | Q83: =IFERROR(IF(O83="",0,O83*P83),0) -> 0
J84: 73 | P84: 1 | Q84: =IFERROR(IF(O84="",0,O84*P84),0) -> 0
... J130: 119 | P130: 1 | Q130: =IFERROR(IF(O130="",0,O130*P130),0) -> 0
J131: 120 | P131: 1 | Q131: =IFERROR(IF(O132="",0,O132*P132),0) -> 0
L132: LOG TOTALS | O132: =SUM(O12:O131) -> 446.87 | Q132: =SUM(Q12:Q131) -> 341.245

Sheet Jan 2027
B2: 💰 Jan 2027 — Expense Tracker
B3: LEFT: summaries auto-update | RIGHT: log every transaction | Blue cells = enter data
B5: ⚙️ SETTINGS
B6: Paycheck #1 (mid-mo) | D6: 2500 | F6: Paycheck #2 (end-mo) | H6: 2500
B7: Full Monthly Rent | D7: 2221.4 | F7: Your Rent Split % | H7: 0.5
B8: Monthly Savings Goal | D8: 500 | F8: Total Monthly Income | H8: =D6+H6+D9 -> 24016.47
B9: Carried Over (prior month) | D9: ='Dec 2026'!D65 -> 19016.47
B10: 📊 CATEGORY SUMMARY | J10: 📋 EXPENSE LOG — Enter every transaction here
B11: Category | D11: Your Share $ | E11: % Income | F11: Budget $ | G11: vs Budget | J11: # | K11: Date | L11: Description | M11: Category | N11: Credit Card | O11: Total $ | P11: Split % | Q11: Your Share $ | R11: Notes / Memo | S11: Recurring?
B12: Groceries | D12: =SUMIF(M12:M131,B12,Q12:Q131) -> 0 | E12: =IFERROR(D12/(H8),0) -> 0 | F12: 300 | G12: =IF(D12=0,"",D12-F12) | J12: 1 | K12: 46388 | L12: Car Insurance | M12: Gas / Transport | N12: Cash | O12: 65 | P12: 1 | Q12: =IFERROR(IF(O12="",0,O12*P12),0) -> 65 | R12: Auto-pay | S12: Y
B13: Utilities | D13: =SUMIF(M12:M131,B13,Q12:Q131) -> 105.625 | E13: =IFERROR(D13/(H8),0) -> 0.0043980235 | F13: 50 | G13: =IF(D13=0,"",D13-F13) -> 55.625 | J13: 2 | K13: 46388 | L13: Stronghold | M13: Health | N13: Robinhood | O13: 105 | P13: 1 | Q13: =IFERROR(IF(O13="",0,O13*P13),0) -> 105 | R13: Auto-pay | S13: Y
B14: Gas / Transport | D14: =SUMIF(M12:M131,B14,Q12:Q131) -> 65 | E14: =IFERROR(D14/(H8),0) -> 0.002706476 | F14: 200 | G14: =IF(D14=0,"",D14-F14) -> -135 | J14: 3 | K14: 46388 | L14: Spectrum Internet | M14: Utilities | N14: Discover | O14: 41.25 | P14: 0.5 | Q14: =IFERROR(IF(O14="",0,O14*P14),0) -> 20.625 | R14: Auto-pay | S14: Y
B15: Dining / Takeout | D15: =SUMIF(M12:M131,B15,Q12:Q131) -> 0 | E15: =IFERROR(D15/(H8),0) -> 0 | F15: 300 | G15: =IF(D15=0,"",D15-F15) | J15: 4 | K15: 46388 | L15: Amazon Prime | M15: Subscriptions | N15: Amazon Card | O15: 7.65 | P15: 1 | Q15: =IFERROR(IF(O15="",0,O15*P15),0) -> 7.65 | R15: Auto-pay | S15: Y
B16: Entertainment | D16: =SUMIF(M12:M131,B16,Q12:Q131) -> 0 | E16: =IFERROR(D16/(H8),0) -> 0 | F16: 150 | G16: =IF(D16=0,"",D16-F16) | J16: 5 | K16: 46388 | L16: Spotify | M16: Subscriptions | N16: Capital One | O16: 21.99 | P16: 1 | Q16: =IFERROR(IF(O16="",0,O16*P16),0) -> 21.99 | R16: Auto-pay | S16: Y
B17: Health | D17: =SUMIF(M12:M131,B17,Q12:Q131) -> 105 | E17: =IFERROR(D17/(H8),0) -> 0.0043719997 | F17: 200 | G17: =IF(D17=0,"",D17-F17) -> -95 | J17: 6 | K17: 46388 | L17: Electricity | M17: Utilities | O17: 170 | P17: 0.5 | Q17: =IFERROR(IF(O17="",0,O17*P17),0) -> 85 | R17: She pays | S17: Y
B18: Shopping | D18: =SUMIF(M12:M131,B18,Q12:Q131) -> 0 | E18: =IFERROR(D18/(H8),0) -> 0 | F18: 200 | G18: =IF(D18=0,"",D18-F18) | J18: 7 | K18: 46388 | L18: Twitch Sub | M18: Subscriptions | N18: CFF | O18: 5.99 | P18: 1 | Q18: =IFERROR(IF(O18="",0,O18*P18),0) -> 5.99 | R18: Auto-pay | S18: Y
B19: Subscriptions | D19: =SUMIF(M12:M131,B19,Q12:Q131) -> 65.62 | E19: =IFERROR(D19/(H8),0) -> 0.0027322916 | F19: 100 | G19: =IF(D19=0,"",D19-F19) -> -34.38 | J19: 8 | K19: 46388 | L19: Claude AI | M19: Subscriptions | N19: Robinhood | O19: 20 | P19: 1 | Q19: =IFERROR(IF(O19="",0,O19*P19),0) -> 20 | R19: Auto-pay | S19: Y
B20: Cash | D20: =SUMIF(M12:M131,B20,Q12:Q131) -> 0 | E20: =IFERROR(D20/(H8),0) -> 0 | F20: 100 | G20: =IF(D20=0,"",D20-F20) | J20: 9 | K20: 46388 | L20: Discord | M20: Subscriptions | N20: CFF | O20: 9.99 | P20: 1 | Q20: =IFERROR(IF(O20="",0,O20*P20),0) -> 9.99 | R20: Auto-pay | S20: Y
B21: Personal / Misc | D21: =SUMIF(M12:M131,B21,Q12:Q131) -> 0 | E21: =IFERROR(D21/(H8),0) -> 0 | F21: 50 | G21: =IF(D21=0,"",D21-F21) | J21: 10 | P21: 1 | Q21: =IFERROR(IF(O21="",0,O21*P21),0) -> 0
B22: Other | D22: =SUMIF(M12:M131,B22,Q12:Q131) -> 0 | E22: =IFERROR(D22/(H8),0) -> 0 | F22: 50 | G22: =IF(D22=0,"",D22-F22) | J22: 11 | P22: 1 | Q22: =IFERROR(IF(O22="",0,O22*P22),0) -> 0
B23: Travel | D23: =SUMIF($M$12:$M$131,B23,$Q$12:$Q$131) -> 0 | E23: =IFERROR(D23/(H8),0) -> 0 | J23: 12 | P23: 1 | Q23: =IFERROR(IF(O23="",0,O23*P23),0) -> 0
B24: Adjusted Rent | D24: =D60 -> 1175.075 | E24: =IFERROR(D24/(H8),0) -> 0.048927882 | J24: 13 | P24: 1 | Q24: =IFERROR(IF(O24="",0,O24*P24),0) -> 0
B25: Investment | D25: =D63 -> 0 | E25: =IFERROR(D25/(H8),0) -> 0 | J25: 14 | P25: 1 | Q25: =IFERROR(IF(O25="",0,O25*P25),0) -> 0
B26: TOTAL Going Out | D26: =D64 -> 1451.945 | E26: =IFERROR(D26/(H8),0) -> 0.06045622 | J26: 15 | P26: 1 | Q26: =IFERROR(IF(O26="",0,O26*P26),0) -> 0
B27: 💵 Money Left Over | D27: =D65 -> 22564.525 | E27: =IFERROR(D27/(H8),0) -> 0.93954378 | J27: 16 | P27: 1 | Q27: =IFERROR(IF(O27="",0,O27*P27),0) -> 0
J28: 17 | P28: 1 | Q28: =IFERROR(IF(O28="",0,O28*P28),0) -> 0
B29: Card | D29: Total This Month $ | J29: 18 | P29: 1 | Q29: =IFERROR(IF(O29="",0,O29*P29),0) -> 0
B30: CFF | D30: =SUMIF(N12:N131,B30,O12:O131) -> 15.98 | J30: 19 | P30: 1 | Q30: =IFERROR(IF(O30="",0,O30*P30),0) -> 0
B31: CFU | D31: =SUMIF(N12:N131,B31,O12:O131) -> 0 | J31: 20 | P31: 1 | Q31: =IFERROR(IF(O31="",0,O31*P31),0) -> 0
B32: CSP | D32: =SUMIF(N12:N131,B32,O12:O131) -> 0 | J32: 21 | P32: 1 | Q32: =IFERROR(IF(O32="",0,O32*P32),0) -> 0
B33: Discover | D33: =SUMIF(N12:N131,B33,O12:O131) -> 41.25 | J33: 22 | P33: 1 | Q33: =IFERROR(IF(O33="",0,O33*P33),0) -> 0
B34: Citi | D34: =SUMIF(N12:N131,B34,O12:O131) -> 0 | J34: 23 | P34: 1 | Q34: =IFERROR(IF(O34="",0,O34*P34),0) -> 0
B35: Capital One | D35: =SUMIF(N12:N131,B35,O12:O131) -> 21.99 | J35: 24 | P35: 1 | Q35: =IFERROR(IF(O35="",0,O35*P35),0) -> 0
B36: WF | D36: =SUMIF(N12:N131,B36,O12:O131) -> 0 | J36: 25 | P36: 1 | Q36: =IFERROR(IF(O36="",0,O36*P36),0) -> 0
B37: Amazon Card | D37: =SUMIF(N12:N131,B37,O12:O131) -> 7.65 | J37: 26 | P37: 1 | Q37: =IFERROR(IF(O37="",0,O37*P37),0) -> 0
B38: Robinhood | D38: =SUMIF(N12:N131,B38,O12:O131) -> 125 | J38: 27 | P38: 1 | Q38: =IFERROR(IF(O38="",0,O38*P38),0) -> 0
B39: Cash | D39: =SUMIF(N12:N131,B39,O12:O131) -> 65 | J39: 28 | P39: 1 | Q39: =IFERROR(IF(O39="",0,O39*P39),0) -> 0
B40: Other | D40: =SUMIF(N12:N131,B40,O12:O131) -> 0 | J40: 29 | P40: 1 | Q40: =IFERROR(IF(O40="",0,O40*P40),0) -> 0
B41: TOTAL CC CHARGES | D41: =SUM(D30:D40) -> 276.87 | J41: 30 | P41: 1 | Q41: =IFERROR(IF(O41="",0,O41*P41),0) -> 0
J42: 31 | P42: 1 | Q42: =IFERROR(IF(O42="",0,O42*P42),0) -> 0
B43: 📈 INVESTMENTS | J43: 32 | P43: 1 | Q43: =IFERROR(IF(O43="",0,O43*P43),0) -> 0
B44: Account | D44: Added This Month $ | F44: Invested $ | J44: 33 | P44: 1 | Q44: =IFERROR(IF(O44="",0,O44*P44),0) -> 0
B45: Robinhood Brokerage | D45: 0 | F45: ='Dec 2026'!F45+D45 -> 300 | J45: 34 | P45: 1 | Q45: =IFERROR(IF(O45="",0,O45*P45),0) -> 0
B46: Vanguard IRA | D46: 0 | J46: 35 | P46: 1 | Q46: =IFERROR(IF(O46="",0,O46*P46),0) -> 0
B47: 🏦 Ally Savings Buckets | J47: 36 | P47: 1 | Q47: =IFERROR(IF(O47="",0,O47*P47),0) -> 0
B48: Bucket | D48: Added This Month $ | F48: Balance $ | J48: 37 | P48: 1 | Q48: =IFERROR(IF(O48="",0,O48*P48),0) -> 0
B49: Wants | D49: 120 | F49: ='Dec 2026'!F49+D49 -> 4440 | J49: 38 | P49: 1 | Q49: =IFERROR(IF(O49="",0,O49*P49),0) -> 0
B50: Vacation | D50: 200 | F50: ='Dec 2026'!F50+D50 -> 9050 | J50: 39 | P50: 1 | Q50: =IFERROR(IF(O50="",0,O50*P50),0) -> 0
B51: Car Fund | D51: 400 | F51: ='Dec 2026'!F51+D51 -> 12800 | J51: 40 | P51: 1 | Q51: =IFERROR(IF(O51="",0,O51*P51),0) -> 0
B52: Emergency Fund | D52: 140 | F52: ='Dec 2026'!F52+D52 -> 7166.75 | J52: 41 | P52: 1 | Q52: =IFERROR(IF(O52="",0,O52*P52),0) -> 0
B53: Ally Total | D53: =SUM(D49:D52) -> 860 | F53: =SUM(F49:F52) -> 33456.75 | J53: 42 | P53: 1 | Q53: =IFERROR(IF(O53="",0,O53*P53),0) -> 0
B54: Total Invested (excl. Ally) | D54: =D45+D46 -> 0 | J54: 43 | P54: 1 | Q54: =IFERROR(IF(O54="",0,O54*P54),0) -> 0
J55: 44 | P55: 1 | Q55: =IFERROR(IF(O55="",0,O55*P55),0) -> 0
B56: 📈 MONTHLY SUMMARY | J56: 45 | P56: 1 | Q56: =IFERROR(IF(O56="",0,O56*P56),0) -> 0
B57: Total Monthly Income | D57: =H8 -> 24016.47 | J57: 46 | P57: 1 | Q57: =IFERROR(IF(O57="",0,O57*P57),0) -> 0
B58: Your Base Rent Share | D58: =D7*H7 -> 1110.7 | J58: 47 | P58: 1 | Q58: =IFERROR(IF(O58="",0,O58*P58),0) -> 0
B59: You Covered (partner's share ↓ your rent) | D59: =SUMPRODUCT((N12:N131<>"")*O12:O131*(1-P12:P131)) -> 20.625 | J59: 48 | P59: 1 | Q59: =IFERROR(IF(O59="",0,O59*P59),0) -> 0
B60: Your Rent After Adjustment | D60: =MAX(D7*H7-SUMPRODUCT((N12:N131<>"")*O12:O131*(1-P12:P131))+SUMPRODUCT((N12:N131="")*(O12:O131>0)*Q12:Q131),0) -> 1175.075 | J60: 49 | P60: 1 | Q60: =IFERROR(IF(O60="",0,O60*P60),0) -> 0
J61: 50 | P61: 1 | Q61: =IFERROR(IF(O61="",0,O61*P61),0) -> 0
B62: Total CC Charges | D62: =D41 -> 276.87 | J62: 51 | P62: 1 | Q62: =IFERROR(IF(O62="",0,O62*P62),0) -> 0
B63: Total Invested (excl. Ally) | D63: =D45+D46 -> 0 | J63: 52 | P63: 1 | Q63: =IFERROR(IF(O63="",0,O63*P63),0) -> 0
B64: TOTAL GOING OUT | D64: =D60+D62+D63 -> 1451.945 | J64: 53 | P64: 1 | Q64: =IFERROR(IF(O64="",0,O64*P64),0) -> 0
B65: 💵 MONEY LEFT OVER | D65: =H8-D64 -> 22564.525 | J65: 54 | P65: 1 | Q65: =IFERROR(IF(O65="",0,O65*P65),0) -> 0
J66: 55 | P66: 1 | Q66: =IFERROR(IF(O66="",0,O66*P66),0) -> 0
B67: 🔁 PARTNER BALANCE | J67: 56 | P67: 1 | Q67: =IFERROR(IF(O67="",0,O67*P67),0) -> 0
B68: Sharon Base Rent Share | D68: =D7*(1-H7) -> 1110.7 | J68: 57 | P68: 1 | Q68: =IFERROR(IF(O68="",0,O68*P68),0) -> 0
B69: She Covered (your share ↑ her rent) | D69: =SUMPRODUCT((N12:N131="")*(O12:O131>0)*Q12:Q131) -> 85 | J69: 58 | P69: 1 | Q69: =IFERROR(IF(O69="",0,O69*P69),0) -> 0
B70: You Covered (partner's share ↓ your rent) | D70: =SUMPRODUCT((N12:N131<>"")*O12:O131*(1-P12:P131)) -> 20.625 | J70: 59 | P70: 1 | Q70: =IFERROR(IF(O70="",0,O70*P70),0) -> 0
B71: Sharon's Total Rent This Month | D71: =MAX(D7*(1-H7)+SUMPRODUCT((N12:N131<>"")*O12:O131*(1-P12:P131))-SUMPRODUCT((N12:N131="")*(O12:O131>0)*Q12:Q131),0) -> 1046.325 | J71: 60 | P71: 1 | Q71: =IFERROR(IF(O71="",0,O71*P71),0) -> 0
B72: You Owe Sharon (if she overpaid) | D72: =MAX(SUMPRODUCT((N12:N131="")*(O12:O131>0)*Q12:Q131)-D7*(1-H7),0) -> 0 | J72: 61 | P72: 1 | Q72: =IFERROR(IF(O72="",0,O72*P72),0) -> 0
J73: 62 | P73: 1 | Q73: =IFERROR(IF(O73="",0,O73*P73),0) -> 0
J74: 63 | P74: 1 | Q74: =IFERROR(IF(O74="",0,O74*P74),0) -> 0
J75: 64 | P75: 1 | Q75: =IFERROR(IF(O75="",0,O75*P75),0) -> 0
J76: 65 | P76: 1 | Q76: =IFERROR(IF(O76="",0,O76*P76),0) -> 0
J77: 66 | P77: 1 | Q77: =IFERROR(IF(O77="",0,O77*P77),0) -> 0
J78: 67 | P78: 1 | Q78: =IFERROR(IF(O78="",0,O78*P78),0) -> 0
J79: 68 | P79: 1 | Q79: =IFERROR(IF(O79="",0,O79*P79),0) -> 0
J80: 69 | P80: 1 | Q80: =IFERROR(IF(O80="",0,O80*P80),0) -> 0
J81: 70 | P81: 1 | Q81: =IFERROR(IF(O81="",0,O81*P81),0) -> 0
J82: 71 | P82: 1 | Q82: =IFERROR(IF(O82="",0,O82*P82),0) -> 0
J83: 72 | P83: 1 | Q83: =IFERROR(IF(O83="",0,O83*P83),0) -> 0
J84: 73 | P84: 1 | Q84: =IFERROR(IF(O84="",0,O84*P84),0) -> 0
... J130: 119 | P130: 1 | Q130: =IFERROR(IF(O130="",0,O130*P130),0) -> 0
J131: 120 | P131: 1 | Q131: =IFERROR(IF(O132="",0,O132*P132),0) -> 0
L132: LOG TOTALS | O132: =SUM(O12:O131) -> 446.87 | Q132: =SUM(Q12:Q131) -> 341.245

Sheet Feb 2027
B2: 💰 Feb 2027 — Expense Tracker
B3: LEFT: summaries auto-update | RIGHT: log every transaction | Blue cells = enter data
B5: ⚙️ SETTINGS
B6: Paycheck #1 (mid-mo) | D6: 2500 | F6: Paycheck #2 (end-mo) | H6: 2500
B7: Full Monthly Rent | D7: 2221.4 | F7: Your Rent Split % | H7: 0.5
B8: Monthly Savings Goal | D8: 500 | F8: Total Monthly Income | H8: =D6+H6+D9 -> 24016.47
B9: Carried Over (prior month) | D9: ='Jan 2027'!D65 -> 19016.47
B10: 📊 CATEGORY SUMMARY | J10: 📋 EXPENSE LOG — Enter every transaction here
B11: Category | D11: Your Share $ | E11: % Income | F11: Budget $ | G11: vs Budget | J11: # | K11: Date | L11: Description | M11: Category | N11: Credit Card | O11: Total $ | P11: Split % | Q11: Your Share $ | R11: Notes / Memo | S11: Recurring?
B12: Groceries | D12: =SUMIF(M12:M131,B12,Q12:Q131) -> 0 | E12: =IFERROR(D12/(H8),0) -> 0 | F12: 300 | G12: =IF(D12=0,"",D12-F12) | J12: 1 | K12: 46419 | L12: Car Insurance | M12: Gas / Transport | N12: Cash | O12: 65 | P12: 1 | Q12: =IFERROR(IF(O12="",0,O12*P12),0) -> 65 | R12: Auto-pay | S12: Y
B13: Utilities | D13: =SUMIF(M12:M131,B13,Q12:Q131) -> 105.625 | E13: =IFERROR(D13/(H8),0) -> 0.0043980235 | F13: 50 | G13: =IF(D13=0,"",D13-F13) -> 55.625 | J13: 2 | K13: 46419 | L13: Stronghold | M13: Health | N13: Robinhood | O13: 105 | P13: 1 | Q13: =IFERROR(IF(O13="",0,O13*P13),0) -> 105 | R13: Auto-pay | S13: Y
B14: Gas / Transport | D14: =SUMIF(M12:M131,B14,Q12:Q131) -> 65 | E14: =IFERROR(D14/(H8),0) -> 0.002706476 | F14: 200 | G14: =IF(D14=0,"",D14-F14) -> -135 | J14: 3 | K14: 46419 | L14: Spectrum Internet | M14: Utilities | N14: Discover | O14: 41.25 | P14: 0.5 | Q14: =IFERROR(IF(O14="",0,O14*P14),0) -> 20.625 | R14: Auto-pay | S14: Y
B15: Dining / Takeout | D15: =SUMIF(M12:M131,B15,Q12:Q131) -> 0 | E15: =IFERROR(D15/(H8),0) -> 0 | F15: 300 | G15: =IF(D15=0,"",D15-F15) | J15: 4 | K15: 46419 | L15: Amazon Prime | M15: Subscriptions | N15: Amazon Card | O15: 7.65 | P15: 1 | Q15: =IFERROR(IF(O15="",0,O15*P15),0) -> 7.65 | R15: Auto-pay | S15: Y
B16: Entertainment | D16: =SUMIF(M12:M131,B16,Q12:Q131) -> 0 | E16: =IFERROR(D16/(H8),0) -> 0 | F16: 150 | G16: =IF(D16=0,"",D16-F16) | J16: 5 | K16: 46419 | L16: Spotify | M16: Subscriptions | N16: Capital One | O16: 21.99 | P16: 1 | Q16: =IFERROR(IF(O16="",0,O16*P16),0) -> 21.99 | R16: Auto-pay | S16: Y
B17: Health | D17: =SUMIF(M12:M131,B17,Q12:Q131) -> 105 | E17: =IFERROR(D17/(H8),0) -> 0.0043719997 | F17: 200 | G17: =IF(D17=0,"",D17-F17) -> -95 | J17: 6 | K17: 46419 | L17: Electricity | M17: Utilities | O17: 170 | P17: 0.5 | Q17: =IFERROR(IF(O17="",0,O17*P17),0) -> 85 | R17: She pays | S17: Y
B18: Shopping | D18: =SUMIF(M12:M131,B18,Q12:Q131) -> 0 | E18: =IFERROR(D18/(H8),0) -> 0 | F18: 200 | G18: =IF(D18=0,"",D18-F18) | J18: 7 | K18: 46419 | L18: Twitch Sub | M18: Subscriptions | N18: CFF | O18: 5.99 | P18: 1 | Q18: =IFERROR(IF(O18="",0,O18*P18),0) -> 5.99 | R18: Auto-pay | S18: Y
B19: Subscriptions | D19: =SUMIF(M12:M131,B19,Q12:Q131) -> 65.62 | E19: =IFERROR(D19/(H8),0) -> 0.0027322916 | F19: 100 | G19: =IF(D19=0,"",D19-F19) -> -34.38 | J19: 8 | K19: 46419 | L19: Claude AI | M19: Subscriptions | N19: Robinhood | O19: 20 | P19: 1 | Q19: =IFERROR(IF(O19="",0,O19*P19),0) -> 20 | R19: Auto-pay | S19: Y
B20: Cash | D20: =SUMIF(M12:M131,B20,Q12:Q131) -> 0 | E20: =IFERROR(D20/(H8),0) -> 0 | F20: 100 | G20: =IF(D20=0,"",D20-F20) | J20: 9 | K20: 46419 | L20: Discord | M20: Subscriptions | N20: CFF | O20: 9.99 | P20: 1 | Q20: =IFERROR(IF(O20="",0,O20*P20),0) -> 9.99 | R20: Auto-pay | S20: Y
B21: Personal / Misc | D21: =SUMIF(M12:M131,B21,Q12:Q131) -> 0 | E21: =IFERROR(D21/(H8),0) -> 0 | F21: 50 | G21: =IF(D21=0,"",D21-F21) | J21: 10 | P21: 1 | Q21: =IFERROR(IF(O21="",0,O21*P21),0) -> 0
B22: Other | D22: =SUMIF(M12:M131,B22,Q12:Q131) -> 0 | E22: =IFERROR(D22/(H8),0) -> 0 | F22: 50 | G22: =IF(D22=0,"",D22-F22) | J22: 11 | P22: 1 | Q22: =IFERROR(IF(O22="",0,O22*P22),0) -> 0
B23: Travel | D23: =SUMIF($M$12:$M$131,B23,$Q$12:$Q$131) -> 0 | E23: =IFERROR(D23/(H8),0) -> 0 | J23: 12 | P23: 1 | Q23: =IFERROR(IF(O23="",0,O23*P23),0) -> 0
B24: Adjusted Rent | D24: =D60 -> 1175.075 | E24: =IFERROR(D24/(H8),0) -> 0.048927882 | J24: 13 | P24: 1 | Q24: =IFERROR(IF(O24="",0,O24*P24),0) -> 0
B25: Investment | D25: =D63 -> 0 | E25: =IFERROR(D25/(H8),0) -> 0 | J25: 14 | P25: 1 | Q25: =IFERROR(IF(O25="",0,O25*P25),0) -> 0
B26: TOTAL Going Out | D26: =D64 -> 1451.945 | E26: =IFERROR(D26/(H8),0) -> 0.06045622 | J26: 15 | P26: 1 | Q26: =IFERROR(IF(O26="",0,O26*P26),0) -> 0
B27: 💵 Money Left Over | D27: =D65 -> 22564.525 | E27: =IFERROR(D27/(H8),0) -> 0.93954378 | J27: 16 | P27: 1 | Q27: =IFERROR(IF(O27="",0,O27*P27),0) -> 0
J28: 17 | P28: 1 | Q28: =IFERROR(IF(O28="",0,O28*P28),0) -> 0
B29: Card | D29: Total This Month $ | J29: 18 | P29: 1 | Q29: =IFERROR(IF(O29="",0,O29*P29),0) -> 0
B30: CFF | D30: =SUMIF(N12:N131,B30,O12:O131) -> 15.98 | J30: 19 | P30: 1 | Q30: =IFERROR(IF(O30="",0,O30*P30),0) -> 0
B31: CFU | D31: =SUMIF(N12:N131,B31,O12:O131) -> 0 | J31: 20 | P31: 1 | Q31: =IFERROR(IF(O31="",0,O31*P31),0) -> 0
B32: CSP | D32: =SUMIF(N12:N131,B32,O12:O131) -> 0 | J32: 21 | P32: 1 | Q32: =IFERROR(IF(O32="",0,O32*P32),0) -> 0
B33: Discover | D33: =SUMIF(N12:N131,B33,O12:O131) -> 41.25 | J33: 22 | P33: 1 | Q33: =IFERROR(IF(O33="",0,O33*P33),0) -> 0
B34: Citi | D34: =SUMIF(N12:N131,B34,O12:O131) -> 0 | J34: 23 | P34: 1 | Q34: =IFERROR(IF(O34="",0,O34*P34),0) -> 0
B35: Capital One | D35: =SUMIF(N12:N131,B35,O12:O131) -> 21.99 | J35: 24 | P35: 1 | Q35: =IFERROR(IF(O35="",0,O35*P35),0) -> 0
B36: WF | D36: =SUMIF(N12:N131,B36,O12:O131) -> 0 | J36: 25 | P36: 1 | Q36: =IFERROR(IF(O36="",0,O36*P36),0) -> 0
B37: Amazon Card | D37: =SUMIF(N12:N131,B37,O12:O131) -> 7.65 | J37: 26 | P37: 1 | Q37: =IFERROR(IF(O37="",0,O37*P37),0) -> 0
B38: Robinhood | D38: =SUMIF(N12:N131,B38,O12:O131) -> 125 | J38: 27 | P38: 1 | Q38: =IFERROR(IF(O38="",0,O38*P38),0) -> 0
B39: Cash | D39: =SUMIF(N12:N131,B39,O12:O131) -> 65 | J39: 28 | P39: 1 | Q39: =IFERROR(IF(O39="",0,O39*P39),0) -> 0
B40: Other | D40: =SUMIF(N12:N131,B40,O12:O131) -> 0 | J40: 29 | P40: 1 | Q40: =IFERROR(IF(O40="",0,O40*P40),0) -> 0
B41: TOTAL CC CHARGES | D41: =SUM(D30:D40) -> 276.87 | J41: 30 | P41: 1 | Q41: =IFERROR(IF(O41="",0,O41*P41),0) -> 0
J42: 31 | P42: 1 | Q42: =IFERROR(IF(O42="",0,O42*P42),0) -> 0
B43: 📈 INVESTMENTS | J43: 32 | P43: 1 | Q43: =IFERROR(IF(O43="",0,O43*P43),0) -> 0
B44: Account | D44: Added This Month $ | F44: Invested $ | J44: 33 | P44: 1 | Q44: =IFERROR(IF(O44="",0,O44*P44),0) -> 0
B45: Robinhood Brokerage | D45: 0 | F45: ='Jan 2027'!F45+D45 -> 300 | J45: 34 | P45: 1 | Q45: =IFERROR(IF(O45="",0,O45*P45),0) -> 0
B46: Vanguard IRA | D46: 0 | J46: 35 | P46: 1 | Q46: =IFERROR(IF(O46="",0,O46*P46),0) -> 0
B47: 🏦 Ally Savings Buckets | J47: 36 | P47: 1 | Q47: =IFERROR(IF(O47="",0,O47*P47),0) -> 0
B48: Bucket | D48: Added This Month $ | F48: Balance $ | J48: 37 | P48: 1 | Q48: =IFERROR(IF(O48="",0,O48*P48),0) -> 0
B49: Wants | D49: 120 | F49: ='Jan 2027'!F49+D49 -> 4440 | J49: 38 | P49: 1 | Q49: =IFERROR(IF(O49="",0,O49*P49),0) -> 0
B50: Vacation | D50: 200 | F50: ='Jan 2027'!F50+D50 -> 9050 | J50: 39 | P50: 1 | Q50: =IFERROR(IF(O50="",0,O50*P50),0) -> 0
B51: Car Fund | D51: 400 | F51: ='Jan 2027'!F51+D51 -> 12800 | J51: 40 | P51: 1 | Q51: =IFERROR(IF(O51="",0,O51*P51),0) -> 0
B52: Emergency Fund | D52: 140 | F52: ='Jan 2027'!F52+D52 -> 7166.75 | J52: 41 | P52: 1 | Q52: =IFERROR(IF(O52="",0,O52*P52),0) -> 0
B53: Ally Total | D53: =SUM(D49:D52) -> 860 | F53: =SUM(F49:F52) -> 33456.75 | J53: 42 | P53: 1 | Q53: =IFERROR(IF(O53="",0,O53*P53),0) -> 0
B54: Total Invested (excl. Ally) | D54: =D45+D46 -> 0 | J54: 43 | P54: 1 | Q54: =IFERROR(IF(O54="",0,O54*P54),0) -> 0
J55: 44 | P55: 1 | Q55: =IFERROR(IF(O55="",0,O55*P55),0) -> 0
B56: 📈 MONTHLY SUMMARY | J56: 45 | P56: 1 | Q56: =IFERROR(IF(O56="",0,O56*P56),0) -> 0
B57: Total Monthly Income | D57: =H8 -> 24016.47 | J57: 46 | P57: 1 | Q57: =IFERROR(IF(O57="",0,O57*P57),0) -> 0
B58: Your Base Rent Share | D58: =D7*H7 -> 1110.7 | J58: 47 | P58: 1 | Q58: =IFERROR(IF(O58="",0,O58*P58),0) -> 0
B59: You Covered (partner's share ↓ your rent) | D59: =SUMPRODUCT((N12:N131<>"")*O12:O131*(1-P12:P131)) -> 20.625 | J59: 48 | P59: 1 | Q59: =IFERROR(IF(O59="",0,O59*P59),0) -> 0
B60: Your Rent After Adjustment | D60: =MAX(D7*H7-SUMPRODUCT((N12:N131<>"")*O12:O131*(1-P12:P131))+SUMPRODUCT((N12:N131="")*(O12:O131>0)*Q12:Q131),0) -> 1175.075 | J60: 49 | P60: 1 | Q60: =IFERROR(IF(O60="",0,O60*P60),0) -> 0
J61: 50 | P61: 1 | Q61: =IFERROR(IF(O61="",0,O61*P61),0) -> 0
B62: Total CC Charges | D62: =D41 -> 276.87 | J62: 51 | P62: 1 | Q62: =IFERROR(IF(O62="",0,O62*P62),0) -> 0
B63: Total Invested (excl. Ally) | D63: =D45+D46 -> 0 | J63: 52 | P63: 1 | Q63: =IFERROR(IF(O63="",0,O63*P63),0) -> 0
B64: TOTAL GOING OUT | D64: =D60+D62+D63 -> 1451.945 | J64: 53 | P64: 1 | Q64: =IFERROR(IF(O64="",0,O64*P64),0) -> 0
B65: 💵 MONEY LEFT OVER | D65: =H8-D64 -> 22564.525 | J65: 54 | P65: 1 | Q65: =IFERROR(IF(O65="",0,O65*P65),0) -> 0
J66: 55 | P66: 1 | Q66: =IFERROR(IF(O66="",0,O66*P66),0) -> 0
B67: 🔁 PARTNER BALANCE | J67: 56 | P67: 1 | Q67: =IFERROR(IF(O67="",0,O67*P67),0) -> 0
B68: Sharon Base Rent Share | D68: =D7*(1-H7) -> 1110.7 | J68: 57 | P68: 1 | Q68: =IFERROR(IF(O68="",0,O68*P68),0) -> 0
B69: She Covered (your share ↑ her rent) | D69: =SUMPRODUCT((N12:N131="")*(O12:O131>0)*Q12:Q131) -> 85 | J69: 58 | P69: 1 | Q69: =IFERROR(IF(O69="",0,O69*P69),0) -> 0
B70: You Covered (partner's share ↓ your rent) | D70: =SUMPRODUCT((N12:N131<>"")*O12:O131*(1-P12:P131)) -> 20.625 | J70: 59 | P70: 1 | Q70: =IFERROR(IF(O70="",0,O70*P70),0) -> 0
B71: Sharon's Total Rent This Month | D71: =MAX(D7*(1-H7)+SUMPRODUCT((N12:N131<>"")*O12:O131*(1-P12:P131))-SUMPRODUCT((N12:N131="")*(O12:O131>0)*Q12:Q131),0) -> 1046.325 | J71: 60 | P71: 1 | Q71: =IFERROR(IF(O71="",0,O71*P71),0) -> 0
B72: You Owe Sharon (if she overpaid) | D72: =MAX(SUMPRODUCT((N12:N131="")*(O12:O131>0)*Q12:Q131)-D7*(1-H7),0) -> 0 | J72: 61 | P72: 1 | Q72: =IFERROR(IF(O72="",0,O72*P72),0) -> 0
J73: 62 | P73: 1 | Q73: =IFERROR(IF(O73="",0,O73*P73),0) -> 0
J74: 63 | P74: 1 | Q74: =IFERROR(IF(O74="",0,O74*P74),0) -> 0
J75: 64 | P75: 1 | Q75: =IFERROR(IF(O75="",0,O75*P75),0) -> 0
J76: 65 | P76: 1 | Q76: =IFERROR(IF(O76="",0,O76*P76),0) -> 0
J77: 66 | P77: 1 | Q77: =IFERROR(IF(O77="",0,O77*P77),0) -> 0
J78: 67 | P78: 1 | Q78: =IFERROR(IF(O78="",0,O78*P78),0) -> 0
J79: 68 | P79: 1 | Q79: =IFERROR(IF(O79="",0,O79*P79),0) -> 0
J80: 69 | P80: 1 | Q80: =IFERROR(IF(O80="",0,O80*P80),0) -> 0
J81: 70 | P81: 1 | Q81: =IFERROR(IF(O81="",0,O81*P81),0) -> 0
J82: 71 | P82: 1 | Q82: =IFERROR(IF(O82="",0,O82*P82),0) -> 0
J83: 72 | P83: 1 | Q83: =IFERROR(IF(O83="",0,O83*P83),0) -> 0
J84: 73 | P84: 1 | Q84: =IFERROR(IF(O84="",0,O84*P84),0) -> 0
... J130: 119 | P130: 1 | Q130: =IFERROR(IF(O130="",0,O130*P130),0) -> 0
J131: 120 | P131: 1 | Q131: =IFERROR(IF(O132="",0,O132*P132),0) -> 0
L132: LOG TOTALS | O132: =SUM(O12:O131) -> 446.87 | Q132: =SUM(Q12:Q131) -> 341.245

Sheet Mar 2027
B2: 💰 Mar 2027 — Expense Tracker
B3: LEFT: summaries auto-update | RIGHT: log every transaction | Blue cells = enter data
B5: ⚙️ SETTINGS
B6: Paycheck #1 (mid-mo) | D6: 2500 | F6: Paycheck #2 (end-mo) | H6: 2500
B7: Full Monthly Rent | D7: 2221.4 | F7: Your Rent Split % | H7: 0.5
B8: Monthly Savings Goal | D8: 500 | F8: Total Monthly Income | H8: =D6+H6+D9 -> 24016.47
B9: Carried Over (prior month) | D9: ='Feb 2027'!D65 -> 19016.47
B10: 📊 CATEGORY SUMMARY | J10: 📋 EXPENSE LOG — Enter every transaction here
B11: Category | D11: Your Share $ | E11: % Income | F11: Budget $ | G11: vs Budget | J11: # | K11: Date | L11: Description | M11: Category | N11: Credit Card | O11: Total $ | P11: Split % | Q11: Your Share $ | R11: Notes / Memo | S11: Recurring?
B12: Groceries | D12: =SUMIF(M12:M131,B12,Q12:Q131) -> 0 | E12: =IFERROR(D12/(H8),0) -> 0 | F12: 300 | G12: =IF(D12=0,"",D12-F12) | J12: 1 | K12: 46447 | L12: Car Insurance | M12: Gas / Transport | N12: Cash | O12: 65 | P12: 1 | Q12: =IFERROR(IF(O12="",0,O12*P12),0) -> 65 | R12: Auto-pay | S12: Y
B13: Utilities | D13: =SUMIF(M12:M131,B13,Q12:Q131) -> 105.625 | E13: =IFERROR(D13/(H8),0) -> 0.0043980235 | F13: 50 | G13: =IF(D13=0,"",D13-F13) -> 55.625 | J13: 2 | K13: 46447 | L13: Stronghold | M13: Health | N13: Robinhood | O13: 105 | P13: 1 | Q13: =IFERROR(IF(O13="",0,O13*P13),0) -> 105 | R13: Auto-pay | S13: Y
B14: Gas / Transport | D14: =SUMIF(M12:M131,B14,Q12:Q131) -> 65 | E14: =IFERROR(D14/(H8),0) -> 0.002706476 | F14: 200 | G14: =IF(D14=0,"",D14-F14) -> -135 | J14: 3 | K14: 46447 | L14: Spectrum Internet | M14: Utilities | N14: Discover | O14: 41.25 | P14: 0.5 | Q14: =IFERROR(IF(O14="",0,O14*P14),0) -> 20.625 | R14: Auto-pay | S14: Y
B15: Dining / Takeout | D15: =SUMIF(M12:M131,B15,Q12:Q131) -> 0 | E15: =IFERROR(D15/(H8),0) -> 0 | F15: 300 | G15: =IF(D15=0,"",D15-F15) | J15: 4 | K15: 46447 | L15: Amazon Prime | M15: Subscriptions | N15: Amazon Card | O15: 7.65 | P15: 1 | Q15: =IFERROR(IF(O15="",0,O15*P15),0) -> 7.65 | R15: Auto-pay | S15: Y
B16: Entertainment | D16: =SUMIF(M12:M131,B16,Q12:Q131) -> 0 | E16: =IFERROR(D16/(H8),0) -> 0 | F16: 150 | G16: =IF(D16=0,"",D16-F16) | J16: 5 | K16: 46447 | L16: Spotify | M16: Subscriptions | N16: Capital One | O16: 21.99 | P16: 1 | Q16: =IFERROR(IF(O16="",0,O16*P16),0) -> 21.99 | R16: Auto-pay | S16: Y
B17: Health | D17: =SUMIF(M12:M131,B17,Q12:Q131) -> 105 | E17: =IFERROR(D17/(H8),0) -> 0.0043719997 | F17: 200 | G17: =IF(D17=0,"",D17-F17) -> -95 | J17: 6 | K17: 46447 | L17: Electricity | M17: Utilities | O17: 170 | P17: 0.5 | Q17: =IFERROR(IF(O17="",0,O17*P17),0) -> 85 | R17: She pays | S17: Y
B18: Shopping | D18: =SUMIF(M12:M131,B18,Q12:Q131) -> 0 | E18: =IFERROR(D18/(H8),0) -> 0 | F18: 200 | G18: =IF(D18=0,"",D18-F18) | J18: 7 | K18: 46447 | L18: Twitch Sub | M18: Subscriptions | N18: CFF | O18: 5.99 | P18: 1 | Q18: =IFERROR(IF(O18="",0,O18*P18),0) -> 5.99 | R18: Auto-pay | S18: Y
B19: Subscriptions | D19: =SUMIF(M12:M131,B19,Q12:Q131) -> 65.62 | E19: =IFERROR(D19/(H8),0) -> 0.0027322916 | F19: 100 | G19: =IF(D19=0,"",D19-F19) -> -34.38 | J19: 8 | K19: 46447 | L19: Claude AI | M19: Subscriptions | N19: Robinhood | O19: 20 | P19: 1 | Q19: =IFERROR(IF(O19="",0,O19*P19),0) -> 20 | R19: Auto-pay | S19: Y
B20: Cash | D20: =SUMIF(M12:M131,B20,Q12:Q131) -> 0 | E20: =IFERROR(D20/(H8),0) -> 0 | F20: 100 | G20: =IF(D20=0,"",D20-F20) | J20: 9 | K20: 46447 | L20: Discord | M20: Subscriptions | N20: CFF | O20: 9.99 | P20: 1 | Q20: =IFERROR(IF(O20="",0,O20*P20),0) -> 9.99 | R20: Auto-pay | S20: Y
B21: Personal / Misc | D21: =SUMIF(M12:M131,B21,Q12:Q131) -> 0 | E21: =IFERROR(D21/(H8),0) -> 0 | F21: 50 | G21: =IF(D21=0,"",D21-F21) | J21: 10 | P21: 1 | Q21: =IFERROR(IF(O21="",0,O21*P21),0) -> 0
B22: Other | D22: =SUMIF(M12:M131,B22,Q12:Q131) -> 0 | E22: =IFERROR(D22/(H8),0) -> 0 | F22: 50 | G22: =IF(D22=0,"",D22-F22) | J22: 11 | P22: 1 | Q22: =IFERROR(IF(O22="",0,O22*P22),0) -> 0
B23: Travel | D23: =SUMIF($M$12:$M$131,B23,$Q$12:$Q$131) -> 0 | E23: =IFERROR(D23/(H8),0) -> 0 | J23: 12 | P23: 1 | Q23: =IFERROR(IF(O23="",0,O23*P23),0) -> 0
B24: Adjusted Rent | D24: =D60 -> 1175.075 | E24: =IFERROR(D24/(H8),0) -> 0.048927882 | J24: 13 | P24: 1 | Q24: =IFERROR(IF(O24="",0,O24*P24),0) -> 0
B25: Investment | D25: =D63 -> 0 | E25: =IFERROR(D25/(H8),0) -> 0 | J25: 14 | P25: 1 | Q25: =IFERROR(IF(O25="",0,O25*P25),0) -> 0
B26: TOTAL Going Out | D26: =D64 -> 1451.945 | E26: =IFERROR(D26/(H8),0) -> 0.06045622 | J26: 15 | P26: 1 | Q26: =IFERROR(IF(O26="",0,O26*P26),0) -> 0
B27: 💵 Money Left Over | D27: =D65 -> 22564.525 | E27: =IFERROR(D27/(H8),0) -> 0.93954378 | J27: 16 | P27: 1 | Q27: =IFERROR(IF(O27="",0,O27*P27),0) -> 0
J28: 17 | P28: 1 | Q28: =IFERROR(IF(O28="",0,O28*P28),0) -> 0
B29: Card | D29: Total This Month $ | J29: 18 | P29: 1 | Q29: =IFERROR(IF(O29="",0,O29*P29),0) -> 0
B30: CFF | D30: =SUMIF(N12:N131,B30,O12:O131) -> 15.98 | J30: 19 | P30: 1 | Q30: =IFERROR(IF(O30="",0,O30*P30),0) -> 0
B31: CFU | D31: =SUMIF(N12:N131,B31,O12:O131) -> 0 | J31: 20 | P31: 1 | Q31: =IFERROR(IF(O31="",0,O31*P31),0) -> 0
B32: CSP | D32: =SUMIF(N12:N131,B32,O12:O131) -> 0 | J32: 21 | P32: 1 | Q32: =IFERROR(IF(O32="",0,O32*P32),0) -> 0
B33: Discover | D33: =SUMIF(N12:N131,B33,O12:O131) -> 41.25 | J33: 22 | P33: 1 | Q33: =IFERROR(IF(O33="",0,O33*P33),0) -> 0
B34: Citi | D34: =SUMIF(N12:N131,B34,O12:O131) -> 0 | J34: 23 | P34: 1 | Q34: =IFERROR(IF(O34="",0,O34*P34),0) -> 0
B35: Capital One | D35: =SUMIF(N12:N131,B35,O12:O131) -> 21.99 | J35: 24 | P35: 1 | Q35: =IFERROR(IF(O35="",0,O35*P35),0) -> 0
B36: WF | D36: =SUMIF(N12:N131,B36,O12:O131) -> 0 | J36: 25 | P36: 1 | Q36: =IFERROR(IF(O36="",0,O36*P36),0) -> 0
B37: Amazon Card | D37: =SUMIF(N12:N131,B37,O12:O131) -> 7.65 | J37: 26 | P37: 1 | Q37: =IFERROR(IF(O37="",0,O37*P37),0) -> 0
B38: Robinhood | D38: =SUMIF(N12:N131,B38,O12:O131) -> 125 | J38: 27 | P38: 1 | Q38: =IFERROR(IF(O38="",0,O38*P38),0) -> 0
B39: Cash | D39: =SUMIF(N12:N131,B39,O12:O131) -> 65 | J39: 28 | P39: 1 | Q39: =IFERROR(IF(O39="",0,O39*P39),0) -> 0
B40: Other | D40: =SUMIF(N12:N131,B40,O12:O131) -> 0 | J40: 29 | P40: 1 | Q40: =IFERROR(IF(O40="",0,O40*P40),0) -> 0
B41: TOTAL CC CHARGES | D41: =SUM(D30:D40) -> 276.87 | J41: 30 | P41: 1 | Q41: =IFERROR(IF(O41="",0,O41*P41),0) -> 0
J42: 31 | P42: 1 | Q42: =IFERROR(IF(O42="",0,O42*P42),0) -> 0
B43: 📈 INVESTMENTS | J43: 32 | P43: 1 | Q43: =IFERROR(IF(O43="",0,O43*P43),0) -> 0
B44: Account | D44: Added This Month $ | F44: Invested $ | J44: 33 | P44: 1 | Q44: =IFERROR(IF(O44="",0,O44*P44),0) -> 0
B45: Robinhood Brokerage | D45: 0 | F45: ='Feb 2027'!F45+D45 -> 300 | J45: 34 | P45: 1 | Q45: =IFERROR(IF(O45="",0,O45*P45),0) -> 0
B46: Vanguard IRA | D46: 0 | J46: 35 | P46: 1 | Q46: =IFERROR(IF(O46="",0,O46*P46),0) -> 0
B47: 🏦 Ally Savings Buckets | J47: 36 | P47: 1 | Q47: =IFERROR(IF(O47="",0,O47*P47),0) -> 0
B48: Bucket | D48: Added This Month $ | F48: Balance $ | J48: 37 | P48: 1 | Q48: =IFERROR(IF(O48="",0,O48*P48),0) -> 0
B49: Wants | D49: 120 | F49: ='Feb 2027'!F49+D49 -> 4440 | J49: 38 | P49: 1 | Q49: =IFERROR(IF(O49="",0,O49*P49),0) -> 0
B50: Vacation | D50: 200 | F50: ='Feb 2027'!F50+D50 -> 9050 | J50: 39 | P50: 1 | Q50: =IFERROR(IF(O50="",0,O50*P50),0) -> 0
B51: Car Fund | D51: 400 | F51: ='Feb 2027'!F51+D51 -> 12800 | J51: 40 | P51: 1 | Q51: =IFERROR(IF(O51="",0,O51*P51),0) -> 0
B52: Emergency Fund | D52: 140 | F52: ='Feb 2027'!F52+D52 -> 7166.75 | J52: 41 | P52: 1 | Q52: =IFERROR(IF(O52="",0,O52*P52),0) -> 0
B53: Ally Total | D53: =SUM(D49:D52) -> 860 | F53: =SUM(F49:F52) -> 33456.75 | J53: 42 | P53: 1 | Q53: =IFERROR(IF(O53="",0,O53*P53),0) -> 0
B54: Total Invested (excl. Ally) | D54: =D45+D46 -> 0 | J54: 43 | P54: 1 | Q54: =IFERROR(IF(O54="",0,O54*P54),0) -> 0
J55: 44 | P55: 1 | Q55: =IFERROR(IF(O55="",0,O55*P55),0) -> 0
B56: 📈 MONTHLY SUMMARY | J56: 45 | P56: 1 | Q56: =IFERROR(IF(O56="",0,O56*P56),0) -> 0
B57: Total Monthly Income | D57: =H8 -> 24016.47 | J57: 46 | P57: 1 | Q57: =IFERROR(IF(O57="",0,O57*P57),0) -> 0
B58: Your Base Rent Share | D58: =D7*H7 -> 1110.7 | J58: 47 | P58: 1 | Q58: =IFERROR(IF(O58="",0,O58*P58),0) -> 0
B59: You Covered (partner's share ↓ your rent) | D59: =SUMPRODUCT((N12:N131<>"")*O12:O131*(1-P12:P131)) -> 20.625 | J59: 48 | P59: 1 | Q59: =IFERROR(IF(O59="",0,O59*P59),0) -> 0
B60: Your Rent After Adjustment | D60: =MAX(D7*H7-SUMPRODUCT((N12:N131<>"")*O12:O131*(1-P12:P131))+SUMPRODUCT((N12:N131="")*(O12:O131>0)*Q12:Q131),0) -> 1175.075 | J60: 49 | P60: 1 | Q60: =IFERROR(IF(O60="",0,O60*P60),0) -> 0
J61: 50 | P61: 1 | Q61: =IFERROR(IF(O61="",0,O61*P61),0) -> 0
B62: Total CC Charges | D62: =D41 -> 276.87 | J62: 51 | P62: 1 | Q62: =IFERROR(IF(O62="",0,O62*P62),0) -> 0
B63: Total Invested (excl. Ally) | D63: =D45+D46 -> 0 | J63: 52 | P63: 1 | Q63: =IFERROR(IF(O63="",0,O63*P63),0) -> 0
B64: TOTAL GOING OUT | D64: =D60+D62+D63 -> 1451.945 | J64: 53 | P64: 1 | Q64: =IFERROR(IF(O64="",0,O64*P64),0) -> 0
B65: 💵 MONEY LEFT OVER | D65: =H8-D64 -> 22564.525 | J65: 54 | P65: 1 | Q65: =IFERROR(IF(O65="",0,O65*P65),0) -> 0
J66: 55 | P66: 1 | Q66: =IFERROR(IF(O66="",0,O66*P66),0) -> 0
B67: 🔁 PARTNER BALANCE | J67: 56 | P67: 1 | Q67: =IFERROR(IF(O67="",0,O67*P67),0) -> 0
B68: Sharon Base Rent Share | D68: =D7*(1-H7) -> 1110.7 | J68: 57 | P68: 1 | Q68: =IFERROR(IF(O68="",0,O68*P68),0) -> 0
B69: She Covered (your share ↑ her rent) | D69: =SUMPRODUCT((N12:N131="")*(O12:O131>0)*Q12:Q131) -> 85 | J69: 58 | P69: 1 | Q69: =IFERROR(IF(O69="",0,O69*P69),0) -> 0
B70: You Covered (partner's share ↓ your rent) | D70: =SUMPRODUCT((N12:N131<>"")*O12:O131*(1-P12:P131)) -> 20.625 | J70: 59 | P70: 1 | Q70: =IFERROR(IF(O70="",0,O70*P70),0) -> 0
B71: Sharon's Total Rent This Month | D71: =MAX(D7*(1-H7)+SUMPRODUCT((N12:N131<>"")*O12:O131*(1-P12:P131))-SUMPRODUCT((N12:N131="")*(O12:O131>0)*Q12:Q131),0) -> 1046.325 | J71: 60 | P71: 1 | Q71: =IFERROR(IF(O71="",0,O71*P71),0) -> 0
B72: You Owe Sharon (if she overpaid) | D72: =MAX(SUMPRODUCT((N12:N131="")*(O12:O131>0)*Q12:Q131)-D7*(1-H7),0) -> 0 | J72: 61 | P72: 1 | Q72: =IFERROR(IF(O72="",0,O72*P72),0) -> 0
J73: 62 | P73: 1 | Q73: =IFERROR(IF(O73="",0,O73*P73),0) -> 0
J74: 63 | P74: 1 | Q74: =IFERROR(IF(O74="",0,O74*P74),0) -> 0
J75: 64 | P75: 1 | Q75: =IFERROR(IF(O75="",0,O75*P75),0) -> 0
J76: 65 | P76: 1 | Q76: =IFERROR(IF(O76="",0,O76*P76),0) -> 0
J77: 66 | P77: 1 | Q77: =IFERROR(IF(O77="",0,O77*P77),0) -> 0
J78: 67 | P78: 1 | Q78: =IFERROR(IF(O78="",0,O78*P78),0) -> 0
J79: 68 | P79: 1 | Q79: =IFERROR(IF(O79="",0,O79*P79),0) -> 0
J80: 69 | P80: 1 | Q80: =IFERROR(IF(O80="",0,O80*P80),0) -> 0
J81: 70 | P81: 1 | Q81: =IFERROR(IF(O81="",0,O81*P81),0) -> 0
J82: 71 | P82: 1 | Q82: =IFERROR(IF(O82="",0,O82*P82),0) -> 0
J83: 72 | P83: 1 | Q83: =IFERROR(IF(O83="",0,O83*P83),0) -> 0
J84: 73 | P84: 1 | Q84: =IFERROR(IF(O84="",0,O84*P84),0) -> 0
... J130: 119 | P130: 1 | Q130: =IFERROR(IF(O130="",0,O130*P130),0) -> 0
J131: 120 | P131: 1 | Q131: =IFERROR(IF(O132="",0,O132*P132),0) -> 0
L132: LOG TOTALS | O132: =SUM(O12:O131) -> 446.87 | Q132: =SUM(Q12:Q131) -> 341.245

Sheet Apr 2027
B2: 💰 Apr 2027 — Expense Tracker
B3: LEFT: summaries auto-update | RIGHT: log every transaction | Blue cells = enter data
B5: ⚙️ SETTINGS
B6: Paycheck #1 (mid-mo) | D6: 2500 | F6: Paycheck #2 (end-mo) | H6: 2500
B7: Full Monthly Rent | D7: 2221.4 | F7: Your Rent Split % | H7: 0.5
B8: Monthly Savings Goal | D8: 500 | F8: Total Monthly Income | H8: =D6+H6+D9 -> 24016.47
B9: Carried Over (prior month) | D9: ='Mar 2027'!D65 -> 19016.47
B10: 📊 CATEGORY SUMMARY | J10: 📋 EXPENSE LOG — Enter every transaction here
B11: Category | D11: Your Share $ | E11: % Income | F11: Budget $ | G11: vs Budget | J11: # | K11: Date | L11: Description | M11: Category | N11: Credit Card | O11: Total $ | P11: Split % | Q11: Your Share $ | R11: Notes / Memo | S11: Recurring?
B12: Groceries | D12: =SUMIF(M12:M131,B12,Q12:Q131) -> 0 | E12: =IFERROR(D12/(H8),0) -> 0 | F12: 300 | G12: =IF(D12=0,"",D12-F12) | J12: 1 | K12: 46478 | L12: Car Insurance | M12: Gas / Transport | N12: Cash | O12: 65 | P12: 1 | Q12: =IFERROR(IF(O12="",0,O12*P12),0) -> 65 | R12: Auto-pay | S12: Y
B13: Utilities | D13: =SUMIF(M12:M131,B13,Q12:Q131) -> 105.625 | E13: =IFERROR(D13/(H8),0) -> 0.0043980235 | F13: 50 | G13: =IF(D13=0,"",D13-F13) -> 55.625 | J13: 2 | K13: 46478 | L13: Stronghold | M13: Health | N13: Robinhood | O13: 105 | P13: 1 | Q13: =IFERROR(IF(O13="",0,O13*P13),0) -> 105 | R13: Auto-pay | S13: Y
B14: Gas / Transport | D14: =SUMIF(M12:M131,B14,Q12:Q131) -> 65 | E14: =IFERROR(D14/(H8),0) -> 0.002706476 | F14: 200 | G14: =IF(D14=0,"",D14-F14) -> -135 | J14: 3 | K14: 46478 | L14: Spectrum Internet | M14: Utilities | N14: Discover | O14: 41.25 | P14: 0.5 | Q14: =IFERROR(IF(O14="",0,O14*P14),0) -> 20.625 | R14: Auto-pay | S14: Y
B15: Dining / Takeout | D15: =SUMIF(M12:M131,B15,Q12:Q131) -> 0 | E15: =IFERROR(D15/(H8),0) -> 0 | F15: 300 | G15: =IF(D15=0,"",D15-F15) | J15: 4 | K15: 46478 | L15: Amazon Prime | M15: Subscriptions | N15: Amazon Card | O15: 7.65 | P15: 1 | Q15: =IFERROR(IF(O15="",0,O15*P15),0) -> 7.65 | R15: Auto-pay | S15: Y
B16: Entertainment | D16: =SUMIF(M12:M131,B16,Q12:Q131) -> 0 | E16: =IFERROR(D16/(H8),0) -> 0 | F16: 150 | G16: =IF(D16=0,"",D16-F16) | J16: 5 | K16: 46478 | L16: Spotify | M16: Subscriptions | N16: Capital One | O16: 21.99 | P16: 1 | Q16: =IFERROR(IF(O16="",0,O16*P16),0) -> 21.99 | R16: Auto-pay | S16: Y
B17: Health | D17: =SUMIF(M12:M131,B17,Q12:Q131) -> 105 | E17: =IFERROR(D17/(H8),0) -> 0.0043719997 | F17: 200 | G17: =IF(D17=0,"",D17-F17) -> -95 | J17: 6 | K17: 46478 | L17: Electricity | M17: Utilities | O17: 170 | P17: 0.5 | Q17: =IFERROR(IF(O17="",0,O17*P17),0) -> 85 | R17: She pays | S17: Y
B18: Shopping | D18: =SUMIF(M12:M131,B18,Q12:Q131) -> 0 | E18: =IFERROR(D18/(H8),0) -> 0 | F18: 200 | G18: =IF(D18=0,"",D18-F18) | J18: 7 | K18: 46478 | L18: Twitch Sub | M18: Subscriptions | N18: CFF | O18: 5.99 | P18: 1 | Q18: =IFERROR(IF(O18="",0,O18*P18),0) -> 5.99 | R18: Auto-pay | S18: Y
B19: Subscriptions | D19: =SUMIF(M12:M131,B19,Q12:Q131) -> 65.62 | E19: =IFERROR(D19/(H8),0) -> 0.0027322916 | F19: 100 | G19: =IF(D19=0,"",D19-F19) -> -34.38 | J19: 8 | K19: 46478 | L19: Claude AI | M19: Subscriptions | N19: Robinhood | O19: 20 | P19: 1 | Q19: =IFERROR(IF(O19="",0,O19*P19),0) -> 20 | R19: Auto-pay | S19: Y
B20: Cash | D20: =SUMIF(M12:M131,B20,Q12:Q131) -> 0 | E20: =IFERROR(D20/(H8),0) -> 0 | F20: 100 | G20: =IF(D20=0,"",D20-F20) | J20: 9 | K20: 46478 | L20: Discord | M20: Subscriptions | N20: CFF | O20: 9.99 | P20: 1 | Q20: =IFERROR(IF(O20="",0,O20*P20),0) -> 9.99 | R20: Auto-pay | S20: Y
B21: Personal / Misc | D21: =SUMIF(M12:M131,B21,Q12:Q131) -> 0 | E21: =IFERROR(D21/(H8),0) -> 0 | F21: 50 | G21: =IF(D21=0,"",D21-F21) | J21: 10 | P21: 1 | Q21: =IFERROR(IF(O21="",0,O21*P21),0) -> 0
B22: Other | D22: =SUMIF(M12:M131,B22,Q12:Q131) -> 0 | E22: =IFERROR(D22/(H8),0) -> 0 | F22: 50 | G22: =IF(D22=0,"",D22-F22) | J22: 11 | P22: 1 | Q22: =IFERROR(IF(O22="",0,O22*P22),0) -> 0
B23: Travel | D23: =SUMIF($M$12:$M$131,B23,$Q$12:$Q$131) -> 0 | E23: =IFERROR(D23/(H8),0) -> 0 | J23: 12 | P23: 1 | Q23: =IFERROR(IF(O23="",0,O23*P23),0) -> 0
B24: Adjusted Rent | D24: =D60 -> 1175.075 | E24: =IFERROR(D24/(H8),0) -> 0.048927882 | J24: 13 | P24: 1 | Q24: =IFERROR(IF(O24="",0,O24*P24),0) -> 0
B25: Investment | D25: =D63 -> 0 | E25: =IFERROR(D25/(H8),0) -> 0 | J25: 14 | P25: 1 | Q25: =IFERROR(IF(O25="",0,O25*P25),0) -> 0
B26: TOTAL Going Out | D26: =D64 -> 1451.945 | E26: =IFERROR(D26/(H8),0) -> 0.06045622 | J26: 15 | P26: 1 | Q26: =IFERROR(IF(O26="",0,O26*P26),0) -> 0
B27: 💵 Money Left Over | D27: =D65 -> 22564.525 | E27: =IFERROR(D27/(H8),0) -> 0.93954378 | J27: 16 | P27: 1 | Q27: =IFERROR(IF(O27="",0,O27*P27),0) -> 0
J28: 17 | P28: 1 | Q28: =IFERROR(IF(O28="",0,O28*P28),0) -> 0
B29: Card | D29: Total This Month $ | J29: 18 | P29: 1 | Q29: =IFERROR(IF(O29="",0,O29*P29),0) -> 0
B30: CFF | D30: =SUMIF(N12:N131,B30,O12:O131) -> 15.98 | J30: 19 | P30: 1 | Q30: =IFERROR(IF(O30="",0,O30*P30),0) -> 0
B31: CFU | D31: =SUMIF(N12:N131,B31,O12:O131) -> 0 | J31: 20 | P31: 1 | Q31: =IFERROR(IF(O31="",0,O31*P31),0) -> 0
B32: CSP | D32: =SUMIF(N12:N131,B32,O12:O131) -> 0 | J32: 21 | P32: 1 | Q32: =IFERROR(IF(O32="",0,O32*P32),0) -> 0
B33: Discover | D33: =SUMIF(N12:N131,B33,O12:O131) -> 41.25 | J33: 22 | P33: 1 | Q33: =IFERROR(IF(O33="",0,O33*P33),0) -> 0
B34: Citi | D34: =SUMIF(N12:N131,B34,O12:O131) -> 0 | J34: 23 | P34: 1 | Q34: =IFERROR(IF(O34="",0,O34*P34),0) -> 0
B35: Capital One | D35: =SUMIF(N12:N131,B35,O12:O131) -> 21.99 | J35: 24 | P35: 1 | Q35: =IFERROR(IF(O35="",0,O35*P35),0) -> 0
B36: WF | D36: =SUMIF(N12:N131,B36,O12:O131) -> 0 | J36: 25 | P36: 1 | Q36: =IFERROR(IF(O36="",0,O36*P36),0) -> 0
B37: Amazon Card | D37: =SUMIF(N12:N131,B37,O12:O131) -> 7.65 | J37: 26 | P37: 1 | Q37: =IFERROR(IF(O37="",0,O37*P37),0) -> 0
B38: Robinhood | D38: =SUMIF(N12:N131,B38,O12:O131) -> 125 | J38: 27 | P38: 1 | Q38: =IFERROR(IF(O38="",0,O38*P38),0) -> 0
B39: Cash | D39: =SUMIF(N12:N131,B39,O12:O131) -> 65 | J39: 28 | P39: 1 | Q39: =IFERROR(IF(O39="",0,O39*P39),0) -> 0
B40: Other | D40: =SUMIF(N12:N131,B40,O12:O131) -> 0 | J40: 29 | P40: 1 | Q40: =IFERROR(IF(O40="",0,O40*P40),0) -> 0
B41: TOTAL CC CHARGES | D41: =SUM(D30:D40) -> 276.87 | J41: 30 | P41: 1 | Q41: =IFERROR(IF(O41="",0,O41*P41),0) -> 0
J42: 31 | P42: 1 | Q42: =IFERROR(IF(O42="",0,O42*P42),0) -> 0
B43: 📈 INVESTMENTS | J43: 32 | P43: 1 | Q43: =IFERROR(IF(O43="",0,O43*P43),0) -> 0
B44: Account | D44: Added This Month $ | F44: Invested $ | J44: 33 | P44: 1 | Q44: =IFERROR(IF(O44="",0,O44*P44),0) -> 0
B45: Robinhood Brokerage | D45: 0 | F45: ='Mar 2027'!F45+D45 -> 300 | J45: 34 | P45: 1 | Q45: =IFERROR(IF(O45="",0,O45*P45),0) -> 0
B46: Vanguard IRA | D46: 0 | J46: 35 | P46: 1 | Q46: =IFERROR(IF(O46="",0,O46*P46),0) -> 0
B47: 🏦 Ally Savings Buckets | J47: 36 | P47: 1 | Q47: =IFERROR(IF(O47="",0,O47*P47),0) -> 0
B48: Bucket | D48: Added This Month $ | F48: Balance $ | J48: 37 | P48: 1 | Q48: =IFERROR(IF(O48="",0,O48*P48),0) -> 0
B49: Wants | D49: 120 | F49: ='Mar 2027'!F49+D49 -> 4440 | J49: 38 | P49: 1 | Q49: =IFERROR(IF(O49="",0,O49*P49),0) -> 0
B50: Vacation | D50: 200 | F50: ='Mar 2027'!F50+D50 -> 9050 | J50: 39 | P50: 1 | Q50: =IFERROR(IF(O50="",0,O50*P50),0) -> 0
B51: Car Fund | D51: 400 | F51: ='Mar 2027'!F51+D51 -> 12800 | J51: 40 | P51: 1 | Q51: =IFERROR(IF(O51="",0,O51*P51),0) -> 0
B52: Emergency Fund | D52: 140 | F52: ='Mar 2027'!F52+D52 -> 7166.75 | J52: 41 | P52: 1 | Q52: =IFERROR(IF(O52="",0,O52*P52),0) -> 0
B53: Ally Total | D53: =SUM(D49:D52) -> 860 | F53: =SUM(F49:F52) -> 33456.75 | J53: 42 | P53: 1 | Q53: =IFERROR(IF(O53="",0,O53*P53),0) -> 0
B54: Total Invested (excl. Ally) | D54: =D45+D46 -> 0 | J54: 43 | P54: 1 | Q54: =IFERROR(IF(O54="",0,O54*P54),0) -> 0
J55: 44 | P55: 1 | Q55: =IFERROR(IF(O55="",0,O55*P55),0) -> 0
B56: 📈 MONTHLY SUMMARY | J56: 45 | P56: 1 | Q56: =IFERROR(IF(O56="",0,O56*P56),0) -> 0
B57: Total Monthly Income | D57: =H8 -> 24016.47 | J57: 46 | P57: 1 | Q57: =IFERROR(IF(O57="",0,O57*P57),0) -> 0
B58: Your Base Rent Share | D58: =D7*H7 -> 1110.7 | J58: 47 | P58: 1 | Q58: =IFERROR(IF(O58="",0,O58*P58),0) -> 0
B59: You Covered (partner's share ↓ your rent) | D59: =SUMPRODUCT((N12:N131<>"")*O12:O131*(1-P12:P131)) -> 20.625 | J59: 48 | P59: 1 | Q59: =IFERROR(IF(O59="",0,O59*P59),0) -> 0
B60: Your Rent After Adjustment | D60: =MAX(D7*H7-SUMPRODUCT((N12:N131<>"")*O12:O131*(1-P12:P131))+SUMPRODUCT((N12:N131="")*(O12:O131>0)*Q12:Q131),0) -> 1175.075 | J60: 49 | P60: 1 | Q60: =IFERROR(IF(O60="",0,O60*P60),0) -> 0
J61: 50 | P61: 1 | Q61: =IFERROR(IF(O61="",0,O61*P61),0) -> 0
B62: Total CC Charges | D62: =D41 -> 276.87 | J62: 51 | P62: 1 | Q62: =IFERROR(IF(O62="",0,O62*P62),0) -> 0
B63: Total Invested (excl. Ally) | D63: =D45+D46 -> 0 | J63: 52 | P63: 1 | Q63: =IFERROR(IF(O63="",0,O63*P63),0) -> 0
B64: TOTAL GOING OUT | D64: =D60+D62+D63 -> 1451.945 | J64: 53 | P64: 1 | Q64: =IFERROR(IF(O64="",0,O64*P64),0) -> 0
B65: 💵 MONEY LEFT OVER | D65: =H8-D64 -> 22564.525 | J65: 54 | P65: 1 | Q65: =IFERROR(IF(O65="",0,O65*P65),0) -> 0
J66: 55 | P66: 1 | Q66: =IFERROR(IF(O66="",0,O66*P66),0) -> 0
B67: 🔁 PARTNER BALANCE | J67: 56 | P67: 1 | Q67: =IFERROR(IF(O67="",0,O67*P67),0) -> 0
B68: Sharon Base Rent Share | D68: =D7*(1-H7) -> 1110.7 | J68: 57 | P68: 1 | Q68: =IFERROR(IF(O68="",0,O68*P68),0) -> 0
B69: She Covered (your share ↑ her rent) | D69: =SUMPRODUCT((N12:N131="")*(O12:O131>0)*Q12:Q131) -> 85 | J69: 58 | P69: 1 | Q69: =IFERROR(IF(O69="",0,O69*P69),0) -> 0
B70: You Covered (partner's share ↓ your rent) | D70: =SUMPRODUCT((N12:N131<>"")*O12:O131*(1-P12:P131)) -> 20.625 | J70: 59 | P70: 1 | Q70: =IFERROR(IF(O70="",0,O70*P70),0) -> 0
B71: Sharon's Total Rent This Month | D71: =MAX(D7*(1-H7)+SUMPRODUCT((N12:N131<>"")*O12:O131*(1-P12:P131))-SUMPRODUCT((N12:N131="")*(O12:O131>0)*Q12:Q131),0) -> 1046.325 | J71: 60 | P71: 1 | Q71: =IFERROR(IF(O71="",0,O71*P71),0) -> 0
B72: You Owe Sharon (if she overpaid) | D72: =MAX(SUMPRODUCT((N12:N131="")*(O12:O131>0)*Q12:Q131)-D7*(1-H7),0) -> 0 | J72: 61 | P72: 1 | Q72: =IFERROR(IF(O72="",0,O72*P72),0) -> 0
J73: 62 | P73: 1 | Q73: =IFERROR(IF(O73="",0,O73*P73),0) -> 0
J74: 63 | P74: 1 | Q74: =IFERROR(IF(O74="",0,O74*P74),0) -> 0
J75: 64 | P75: 1 | Q75: =IFERROR(IF(O75="",0,O75*P75),0) -> 0
J76: 65 | P76: 1 | Q76: =IFERROR(IF(O76="",0,O76*P76),0) -> 0
J77: 66 | P77: 1 | Q77: =IFERROR(IF(O77="",0,O77*P77),0) -> 0
J78: 67 | P78: 1 | Q78: =IFERROR(IF(O78="",0,O78*P78),0) -> 0
J79: 68 | P79: 1 | Q79: =IFERROR(IF(O79="",0,O79*P79),0) -> 0
J80: 69 | P80: 1 | Q80: =IFERROR(IF(O80="",0,O80*P80),0) -> 0
J81: 70 | P81: 1 | Q81: =IFERROR(IF(O81="",0,O81*P81),0) -> 0
J82: 71 | P82: 1 | Q82: =IFERROR(IF(O82="",0,O82*P82),0) -> 0
J83: 72 | P83: 1 | Q83: =IFERROR(IF(O83="",0,O83*P83),0) -> 0
J84: 73 | P84: 1 | Q84: =IFERROR(IF(O84="",0,O84*P84),0) -> 0
... J130: 119 | P130: 1 | Q130: =IFERROR(IF(O130="",0,O130*P130),0) -> 0
J131: 120 | P131: 1 | Q131: =IFERROR(IF(O132="",0,O132*P132),0) -> 0
L132: LOG TOTALS | O132: =SUM(O12:O131) -> 446.87 | Q132: =SUM(Q12:Q131) -> 341.245

Sheet May 2027
B2: 💰 May 2027 — Expense Tracker
B3: LEFT: summaries auto-update | RIGHT: log every transaction | Blue cells = enter data
B5: ⚙️ SETTINGS
B6: Paycheck #1 (mid-mo) | D6: 2500 | F6: Paycheck #2 (end-mo) | H6: 2500
B7: Full Monthly Rent | D7: 2221.4 | F7: Your Rent Split % | H7: 0.5
B8: Monthly Savings Goal | D8: 500 | F8: Total Monthly Income | H8: =D6+H6+D9 -> 24016.47
B9: Carried Over (prior month) | D9: ='Apr 2027'!D65 -> 19016.47
B10: 📊 CATEGORY SUMMARY | J10: 📋 EXPENSE LOG — Enter every transaction here
B11: Category | D11: Your Share $ | E11: % Income | F11: Budget $ | G11: vs Budget | J11: # | K11: Date | L11: Description | M11: Category | N11: Credit Card | O11: Total $ | P11: Split % | Q11: Your Share $ | R11: Notes / Memo | S11: Recurring?
B12: Groceries | D12: =SUMIF(M12:M131,B12,Q12:Q131) -> 0 | E12: =IFERROR(D12/(H8),0) -> 0 | F12: 300 | G12: =IF(D12=0,"",D12-F12) | J12: 1 | K12: 46508 | L12: Car Insurance | M12: Gas / Transport | N12: Cash | O12: 65 | P12: 1 | Q12: =IFERROR(IF(O12="",0,O12*P12),0) -> 65 | R12: Auto-pay | S12: Y
B13: Utilities | D13: =SUMIF(M12:M131,B13,Q12:Q131) -> 105.625 | E13: =IFERROR(D13/(H8),0) -> 0.0043980235 | F13: 50 | G13: =IF(D13=0,"",D13-F13) -> 55.625 | J13: 2 | K13: 46508 | L13: Stronghold | M13: Health | N13: Robinhood | O13: 105 | P13: 1 | Q13: =IFERROR(IF(O13="",0,O13*P13),0) -> 105 | R13: Auto-pay | S13: Y
B14: Gas / Transport | D14: =SUMIF(M12:M131,B14,Q12:Q131) -> 65 | E14: =IFERROR(D14/(H8),0) -> 0.002706476 | F14: 200 | G14: =IF(D14=0,"",D14-F14) -> -135 | J14: 3 | K14: 46508 | L14: Spectrum Internet | M14: Utilities | N14: Discover | O14: 41.25 | P14: 0.5 | Q14: =IFERROR(IF(O14="",0,O14*P14),0) -> 20.625 | R14: Auto-pay | S14: Y
B15: Dining / Takeout | D15: =SUMIF(M12:M131,B15,Q12:Q131) -> 0 | E15: =IFERROR(D15/(H8),0) -> 0 | F15: 300 | G15: =IF(D15=0,"",D15-F15) | J15: 4 | K15: 46508 | L15: Amazon Prime | M15: Subscriptions | N15: Amazon Card | O15: 7.65 | P15: 1 | Q15: =IFERROR(IF(O15="",0,O15*P15),0) -> 7.65 | R15: Auto-pay | S15: Y
B16: Entertainment | D16: =SUMIF(M12:M131,B16,Q12:Q131) -> 0 | E16: =IFERROR(D16/(H8),0) -> 0 | F16: 150 | G16: =IF(D16=0,"",D16-F16) | J16: 5 | K16: 46508 | L16: Spotify | M16: Subscriptions | N16: Capital One | O16: 21.99 | P16: 1 | Q16: =IFERROR(IF(O16="",0,O16*P16),0) -> 21.99 | R16: Auto-pay | S16: Y
B17: Health | D17: =SUMIF(M12:M131,B17,Q12:Q131) -> 105 | E17: =IFERROR(D17/(H8),0) -> 0.0043719997 | F17: 200 | G17: =IF(D17=0,"",D17-F17) -> -95 | J17: 6 | K17: 46508 | L17: Electricity | M17: Utilities | O17: 170 | P17: 0.5 | Q17: =IFERROR(IF(O17="",0,O17*P17),0) -> 85 | R17: She pays | S17: Y
B18: Shopping | D18: =SUMIF(M12:M131,B18,Q12:Q131) -> 0 | E18: =IFERROR(D18/(H8),0) -> 0 | F18: 200 | G18: =IF(D18=0,"",D18-F18) | J18: 7 | K18: 46508 | L18: Twitch Sub | M18: Subscriptions | N18: CFF | O18: 5.99 | P18: 1 | Q18: =IFERROR(IF(O18="",0,O18*P18),0) -> 5.99 | R18: Auto-pay | S18: Y
B19: Subscriptions | D19: =SUMIF(M12:M131,B19,Q12:Q131) -> 65.62 | E19: =IFERROR(D19/(H8),0) -> 0.0027322916 | F19: 100 | G19: =IF(D19=0,"",D19-F19) -> -34.38 | J19: 8 | K19: 46508 | L19: Claude AI | M19: Subscriptions | N19: Robinhood | O19: 20 | P19: 1 | Q19: =IFERROR(IF(O19="",0,O19*P19),0) -> 20 | R19: Auto-pay | S19: Y
B20: Cash | D20: =SUMIF(M12:M131,B20,Q12:Q131) -> 0 | E20: =IFERROR(D20/(H8),0) -> 0 | F20: 100 | G20: =IF(D20=0,"",D20-F20) | J20: 9 | K20: 46508 | L20: Discord | M20: Subscriptions | N20: CFF | O20: 9.99 | P20: 1 | Q20: =IFERROR(IF(O20="",0,O20*P20),0) -> 9.99 | R20: Auto-pay | S20: Y
B21: Personal / Misc | D21: =SUMIF(M12:M131,B21,Q12:Q131) -> 0 | E21: =IFERROR(D21/(H8),0) -> 0 | F21: 50 | G21: =IF(D21=0,"",D21-F21) | J21: 10 | P21: 1 | Q21: =IFERROR(IF(O21="",0,O21*P21),0) -> 0
B22: Other | D22: =SUMIF(M12:M131,B22,Q12:Q131) -> 0 | E22: =IFERROR(D22/(H8),0) -> 0 | F22: 50 | G22: =IF(D22=0,"",D22-F22) | J22: 11 | P22: 1 | Q22: =IFERROR(IF(O22="",0,O22*P22),0) -> 0
B23: Travel | D23: =SUMIF($M$12:$M$131,B23,$Q$12:$Q$131) -> 0 | E23: =IFERROR(D23/(H8),0) -> 0 | J23: 12 | P23: 1 | Q23: =IFERROR(IF(O23="",0,O23*P23),0) -> 0
B24: Adjusted Rent | D24: =D60 -> 1175.075 | E24: =IFERROR(D24/(H8),0) -> 0.048927882 | J24: 13 | P24: 1 | Q24: =IFERROR(IF(O24="",0,O24*P24),0) -> 0
B25: Investment | D25: =D63 -> 0 | E25: =IFERROR(D25/(H8),0) -> 0 | J25: 14 | P25: 1 | Q25: =IFERROR(IF(O25="",0,O25*P25),0) -> 0
B26: TOTAL Going Out | D26: =D64 -> 1451.945 | E26: =IFERROR(D26/(H8),0) -> 0.06045622 | J26: 15 | P26: 1 | Q26: =IFERROR(IF(O26="",0,O26*P26),0) -> 0
B27: 💵 Money Left Over | D27: =D65 -> 22564.525 | E27: =IFERROR(D27/(H8),0) -> 0.93954378 | J27: 16 | P27: 1 | Q27: =IFERROR(IF(O27="",0,O27*P27),0) -> 0
J28: 17 | P28: 1 | Q28: =IFERROR(IF(O28="",0,O28*P28),0) -> 0
B29: Card | D29: Total This Month $ | J29: 18 | P29: 1 | Q29: =IFERROR(IF(O29="",0,O29*P29),0) -> 0
B30: CFF | D30: =SUMIF(N12:N131,B30,O12:O131) -> 15.98 | J30: 19 | P30: 1 | Q30: =IFERROR(IF(O30="",0,O30*P30),0) -> 0
B31: CFU | D31: =SUMIF(N12:N131,B31,O12:O131) -> 0 | J31: 20 | P31: 1 | Q31: =IFERROR(IF(O31="",0,O31*P31),0) -> 0
B32: CSP | D32: =SUMIF(N12:N131,B32,O12:O131) -> 0 | J32: 21 | P32: 1 | Q32: =IFERROR(IF(O32="",0,O32*P32),0) -> 0
B33: Discover | D33: =SUMIF(N12:N131,B33,O12:O131) -> 41.25 | J33: 22 | P33: 1 | Q33: =IFERROR(IF(O33="",0,O33*P33),0) -> 0
B34: Citi | D34: =SUMIF(N12:N131,B34,O12:O131) -> 0 | J34: 23 | P34: 1 | Q34: =IFERROR(IF(O34="",0,O34*P34),0) -> 0
B35: Capital One | D35: =SUMIF(N12:N131,B35,O12:O131) -> 21.99 | J35: 24 | P35: 1 | Q35: =IFERROR(IF(O35="",0,O35*P35),0) -> 0
B36: WF | D36: =SUMIF(N12:N131,B36,O12:O131) -> 0 | J36: 25 | P36: 1 | Q36: =IFERROR(IF(O36="",0,O36*P36),0) -> 0
B37: Amazon Card | D37: =SUMIF(N12:N131,B37,O12:O131) -> 7.65 | J37: 26 | P37: 1 | Q37: =IFERROR(IF(O37="",0,O37*P37),0) -> 0
B38: Robinhood | D38: =SUMIF(N12:N131,B38,O12:O131) -> 125 | J38: 27 | P38: 1 | Q38: =IFERROR(IF(O38="",0,O38*P38),0) -> 0
B39: Cash | D39: =SUMIF(N12:N131,B39,O12:O131) -> 65 | J39: 28 | P39: 1 | Q39: =IFERROR(IF(O39="",0,O39*P39),0) -> 0
B40: Other | D40: =SUMIF(N12:N131,B40,O12:O131) -> 0 | J40: 29 | P40: 1 | Q40: =IFERROR(IF(O40="",0,O40*P40),0) -> 0
B41: TOTAL CC CHARGES | D41: =SUM(D30:D40) -> 276.87 | J41: 30 | P41: 1 | Q41: =IFERROR(IF(O41="",0,O41*P41),0) -> 0
J42: 31 | P42: 1 | Q42: =IFERROR(IF(O42="",0,O42*P42),0) -> 0
B43: 📈 INVESTMENTS | J43: 32 | P43: 1 | Q43: =IFERROR(IF(O43="",0,O43*P43),0) -> 0
B44: Account | D44: Added This Month $ | F44: Invested $ | J44: 33 | P44: 1 | Q44: =IFERROR(IF(O44="",0,O44*P44),0) -> 0
B45: Robinhood Brokerage | D45: 0 | F45: ='Apr 2027'!F45+D45 -> 300 | J45: 34 | P45: 1 | Q45: =IFERROR(IF(O45="",0,O45*P45),0) -> 0
B46: Vanguard IRA | D46: 0 | J46: 35 | P46: 1 | Q46: =IFERROR(IF(O46="",0,O46*P46),0) -> 0
B47: 🏦 Ally Savings Buckets | J47: 36 | P47: 1 | Q47: =IFERROR(IF(O47="",0,O47*P47),0) -> 0
B48: Bucket | D48: Added This Month $ | F48: Balance $ | J48: 37 | P48: 1 | Q48: =IFERROR(IF(O48="",0,O48*P48),0) -> 0
B49: Wants | D49: 120 | F49: ='Apr 2027'!F49+D49 -> 4440 | J49: 38 | P49: 1 | Q49: =IFERROR(IF(O49="",0,O49*P49),0) -> 0
B50: Vacation | D50: 200 | F50: ='Apr 2027'!F50+D50 -> 9050 | J50: 39 | P50: 1 | Q50: =IFERROR(IF(O50="",0,O50*P50),0) -> 0
B51: Car Fund | D51: 400 | F51: ='Apr 2027'!F51+D51 -> 12800 | J51: 40 | P51: 1 | Q51: =IFERROR(IF(O51="",0,O51*P51),0) -> 0
B52: Emergency Fund | D52: 140 | F52: ='Apr 2027'!F52+D52 -> 7166.75 | J52: 41 | P52: 1 | Q52: =IFERROR(IF(O52="",0,O52*P52),0) -> 0
B53: Ally Total | D53: =SUM(D49:D52) -> 860 | F53: =SUM(F49:F52) -> 33456.75 | J53: 42 | P53: 1 | Q53: =IFERROR(IF(O53="",0,O53*P53),0) -> 0
B54: Total Invested (excl. Ally) | D54: =D45+D46 -> 0 | J54: 43 | P54: 1 | Q54: =IFERROR(IF(O54="",0,O54*P54),0) -> 0
J55: 44 | P55: 1 | Q55: =IFERROR(IF(O55="",0,O55*P55),0) -> 0
B56: 📈 MONTHLY SUMMARY | J56: 45 | P56: 1 | Q56: =IFERROR(IF(O56="",0,O56*P56),0) -> 0
B57: Total Monthly Income | D57: =H8 -> 24016.47 | J57: 46 | P57: 1 | Q57: =IFERROR(IF(O57="",0,O57*P57),0) -> 0
B58: Your Base Rent Share | D58: =D7*H7 -> 1110.7 | J58: 47 | P58: 1 | Q58: =IFERROR(IF(O58="",0,O58*P58),0) -> 0
B59: You Covered (partner's share ↓ your rent) | D59: =SUMPRODUCT((N12:N131<>"")*O12:O131*(1-P12:P131)) -> 20.625 | J59: 48 | P59: 1 | Q59: =IFERROR(IF(O59="",0,O59*P59),0) -> 0
B60: Your Rent After Adjustment | D60: =MAX(D7*H7-SUMPRODUCT((N12:N131<>"")*O12:O131*(1-P12:P131))+SUMPRODUCT((N12:N131="")*(O12:O131>0)*Q12:Q131),0) -> 1175.075 | J60: 49 | P60: 1 | Q60: =IFERROR(IF(O60="",0,O60*P60),0) -> 0
J61: 50 | P61: 1 | Q61: =IFERROR(IF(O61="",0,O61*P61),0) -> 0
B62: Total CC Charges | D62: =D41 -> 276.87 | J62: 51 | P62: 1 | Q62: =IFERROR(IF(O62="",0,O62*P62),0) -> 0
B63: Total Invested (excl. Ally) | D63: =D45+D46 -> 0 | J63: 52 | P63: 1 | Q63: =IFERROR(IF(O63="",0,O63*P63),0) -> 0
B64: TOTAL GOING OUT | D64: =D60+D62+D63 -> 1451.945 | J64: 53 | P64: 1 | Q64: =IFERROR(IF(O64="",0,O64*P64),0) -> 0
B65: 💵 MONEY LEFT OVER | D65: =H8-D64 -> 22564.525 | J65: 54 | P65: 1 | Q65: =IFERROR(IF(O65="",0,O65*P65),0) -> 0
J66: 55 | P66: 1 | Q66: =IFERROR(IF(O66="",0,O66*P66),0) -> 0
B67: 🔁 PARTNER BALANCE | J67: 56 | P67: 1 | Q67: =IFERROR(IF(O67="",0,O67*P67),0) -> 0
B68: Sharon Base Rent Share | D68: =D7*(1-H7) -> 1110.7 | J68: 57 | P68: 1 | Q68: =IFERROR(IF(O68="",0,O68*P68),0) -> 0
B69: She Covered (your share ↑ her rent) | D69: =SUMPRODUCT((N12:N131="")*(O12:O131>0)*Q12:Q131) -> 85 | J69: 58 | P69: 1 | Q69: =IFERROR(IF(O69="",0,O69*P69),0) -> 0
B70: You Covered (partner's share ↓ your rent) | D70: =SUMPRODUCT((N12:N131<>"")*O12:O131*(1-P12:P131)) -> 20.625 | J70: 59 | P70: 1 | Q70: =IFERROR(IF(O70="",0,O70*P70),0) -> 0
B71: Sharon's Total Rent This Month | D71: =MAX(D7*(1-H7)+SUMPRODUCT((N12:N131<>"")*O12:O131*(1-P12:P131))-SUMPRODUCT((N12:N131="")*(O12:O131>0)*Q12:Q131),0) -> 1046.325 | J71: 60 | P71: 1 | Q71: =IFERROR(IF(O71="",0,O71*P71),0) -> 0
B72: You Owe Sharon (if she overpaid) | D72: =MAX(SUMPRODUCT((N12:N131="")*(O12:O131>0)*Q12:Q131)-D7*(1-H7),0) -> 0 | J72: 61 | P72: 1 | Q72: =IFERROR(IF(O72="",0,O72*P72),0) -> 0
J73: 62 | P73: 1 | Q73: =IFERROR(IF(O73="",0,O73*P73),0) -> 0
J74: 63 | P74: 1 | Q74: =IFERROR(IF(O74="",0,O74*P74),0) -> 0
J75: 64 | P75: 1 | Q75: =IFERROR(IF(O75="",0,O75*P75),0) -> 0
J76: 65 | P76: 1 | Q76: =IFERROR(IF(O76="",0,O76*P76),0) -> 0
J77: 66 | P77: 1 | Q77: =IFERROR(IF(O77="",0,O77*P77),0) -> 0
J78: 67 | P78: 1 | Q78: =IFERROR(IF(O78="",0,O78*P78),0) -> 0
J79: 68 | P79: 1 | Q79: =IFERROR(IF(O79="",0,O79*P79),0) -> 0
J80: 69 | P80: 1 | Q80: =IFERROR(IF(O80="",0,O80*P80),0) -> 0
J81: 70 | P81: 1 | Q81: =IFERROR(IF(O81="",0,O81*P81),0) -> 0
J82: 71 | P82: 1 | Q82: =IFERROR(IF(O82="",0,O82*P82),0) -> 0
J83: 72 | P83: 1 | Q83: =IFERROR(IF(O83="",0,O83*P83),0) -> 0
J84: 73 | P84: 1 | Q84: =IFERROR(IF(O84="",0,O84*P84),0) -> 0
... J130: 119 | P130: 1 | Q130: =IFERROR(IF(O130="",0,O130*P130),0) -> 0
J131: 120 | P131: 1 | Q131: =IFERROR(IF(O132="",0,O132*P132),0) -> 0
L132: LOG TOTALS | O132: =SUM(O12:O131) -> 446.87 | Q132: =SUM(Q12:Q131) -> 341.245

Sheet Jun 2027
B2: 💰 Jun 2027 — Expense Tracker
B3: LEFT: summaries auto-update | RIGHT: log every transaction | Blue cells = enter data
B5: ⚙️ SETTINGS
B6: Paycheck #1 (mid-mo) | D6: 2500 | F6: Paycheck #2 (end-mo) | H6: 2500
B7: Full Monthly Rent | D7: 2221.4 | F7: Your Rent Split % | H7: 0.5
B8: Monthly Savings Goal | D8: 500 | F8: Total Monthly Income | H8: =D6+H6+D9 -> 24016.47
B9: Carried Over (prior month) | D9: ='May 2027'!D65 -> 19016.47
B10: 📊 CATEGORY SUMMARY | J10: 📋 EXPENSE LOG — Enter every transaction here
B11: Category | D11: Your Share $ | E11: % Income | F11: Budget $ | G11: vs Budget | J11: # | K11: Date | L11: Description | M11: Category | N11: Credit Card | O11: Total $ | P11: Split % | Q11: Your Share $ | R11: Notes / Memo | S11: Recurring?
B12: Groceries | D12: =SUMIF(M12:M131,B12,Q12:Q131) -> 0 | E12: =IFERROR(D12/(H8),0) -> 0 | F12: 300 | G12: =IF(D12=0,"",D12-F12) | J12: 1 | K12: 46539 | L12: Car Insurance | M12: Gas / Transport | N12: Cash | O12: 65 | P12: 1 | Q12: =IFERROR(IF(O12="",0,O12*P12),0) -> 65 | R12: Auto-pay | S12: Y
B13: Utilities | D13: =SUMIF(M12:M131,B13,Q12:Q131) -> 105.625 | E13: =IFERROR(D13/(H8),0) -> 0.0043980235 | F13: 50 | G13: =IF(D13=0,"",D13-F13) -> 55.625 | J13: 2 | K13: 46539 | L13: Stronghold | M13: Health | N13: Robinhood | O13: 105 | P13: 1 | Q13: =IFERROR(IF(O13="",0,O13*P13),0) -> 105 | R13: Auto-pay | S13: Y
B14: Gas / Transport | D14: =SUMIF(M12:M131,B14,Q12:Q131) -> 65 | E14: =IFERROR(D14/(H8),0) -> 0.002706476 | F14: 200 | G14: =IF(D14=0,"",D14-F14) -> -135 | J14: 3 | K14: 46539 | L14: Spectrum Internet | M14: Utilities | N14: Discover | O14: 41.25 | P14: 0.5 | Q14: =IFERROR(IF(O14="",0,O14*P14),0) -> 20.625 | R14: Auto-pay | S14: Y
B15: Dining / Takeout | D15: =SUMIF(M12:M131,B15,Q12:Q131) -> 0 | E15: =IFERROR(D15/(H8),0) -> 0 | F15: 300 | G15: =IF(D15=0,"",D15-F15) | J15: 4 | K15: 46539 | L15: Amazon Prime | M15: Subscriptions | N15: Amazon Card | O15: 7.65 | P15: 1 | Q15: =IFERROR(IF(O15="",0,O15*P15),0) -> 7.65 | R15: Auto-pay | S15: Y
B16: Entertainment | D16: =SUMIF(M12:M131,B16,Q12:Q131) -> 0 | E16: =IFERROR(D16/(H8),0) -> 0 | F16: 150 | G16: =IF(D16=0,"",D16-F16) | J16: 5 | K16: 46539 | L16: Spotify | M16: Subscriptions | N16: Capital One | O16: 21.99 | P16: 1 | Q16: =IFERROR(IF(O16="",0,O16*P16),0) -> 21.99 | R16: Auto-pay | S16: Y
B17: Health | D17: =SUMIF(M12:M131,B17,Q12:Q131) -> 105 | E17: =IFERROR(D17/(H8),0) -> 0.0043719997 | F17: 200 | G17: =IF(D17=0,"",D17-F17) -> -95 | J17: 6 | K17: 46539 | L17: Electricity | M17: Utilities | O17: 170 | P17: 0.5 | Q17: =IFERROR(IF(O17="",0,O17*P17),0) -> 85 | R17: She pays | S17: Y
B18: Shopping | D18: =SUMIF(M12:M131,B18,Q12:Q131) -> 0 | E18: =IFERROR(D18/(H8),0) -> 0 | F18: 200 | G18: =IF(D18=0,"",D18-F18) | J18: 7 | K18: 46539 | L18: Twitch Sub | M18: Subscriptions | N18: CFF | O18: 5.99 | P18: 1 | Q18: =IFERROR(IF(O18="",0,O18*P18),0) -> 5.99 | R18: Auto-pay | S18: Y
B19: Subscriptions | D19: =SUMIF(M12:M131,B19,Q12:Q131) -> 65.62 | E19: =IFERROR(D19/(H8),0) -> 0.0027322916 | F19: 100 | G19: =IF(D19=0,"",D19-F19) -> -34.38 | J19: 8 | K19: 46539 | L19: Claude AI | M19: Subscriptions | N19: Robinhood | O19: 20 | P19: 1 | Q19: =IFERROR(IF(O19="",0,O19*P19),0) -> 20 | R19: Auto-pay | S19: Y
B20: Cash | D20: =SUMIF(M12:M131,B20,Q12:Q131) -> 0 | E20: =IFERROR(D20/(H8),0) -> 0 | F20: 100 | G20: =IF(D20=0,"",D20-F20) | J20: 9 | K20: 46539 | L20: Discord | M20: Subscriptions | N20: CFF | O20: 9.99 | P20: 1 | Q20: =IFERROR(IF(O20="",0,O20*P20),0) -> 9.99 | R20: Auto-pay | S20: Y
B21: Personal / Misc | D21: =SUMIF(M12:M131,B21,Q12:Q131) -> 0 | E21: =IFERROR(D21/(H8),0) -> 0 | F21: 50 | G21: =IF(D21=0,"",D21-F21) | J21: 10 | P21: 1 | Q21: =IFERROR(IF(O21="",0,O21*P21),0) -> 0
B22: Other | D22: =SUMIF(M12:M131,B22,Q12:Q131) -> 0 | E22: =IFERROR(D22/(H8),0) -> 0 | F22: 50 | G22: =IF(D22=0,"",D22-F22) | J22: 11 | P22: 1 | Q22: =IFERROR(IF(O22="",0,O22*P22),0) -> 0
B23: Travel | D23: =SUMIF($M$12:$M$131,B23,$Q$12:$Q$131) -> 0 | E23: =IFERROR(D23/(H8),0) -> 0 | J23: 12 | P23: 1 | Q23: =IFERROR(IF(O23="",0,O23*P23),0) -> 0
B24: Adjusted Rent | D24: =D60 -> 1175.075 | E24: =IFERROR(D24/(H8),0) -> 0.048927882 | J24: 13 | P24: 1 | Q24: =IFERROR(IF(O24="",0,O24*P24),0) -> 0
B25: Investment | D25: =D63 -> 0 | E25: =IFERROR(D25/(H8),0) -> 0 | J25: 14 | P25: 1 | Q25: =IFERROR(IF(O25="",0,O25*P25),0) -> 0
B26: TOTAL Going Out | D26: =D64 -> 1451.945 | E26: =IFERROR(D26/(H8),0) -> 0.06045622 | J26: 15 | P26: 1 | Q26: =IFERROR(IF(O26="",0,O26*P26),0) -> 0
B27: 💵 Money Left Over | D27: =D65 -> 22564.525 | E27: =IFERROR(D27/(H8),0) -> 0.93954378 | J27: 16 | P27: 1 | Q27: =IFERROR(IF(O27="",0,O27*P27),0) -> 0
J28: 17 | P28: 1 | Q28: =IFERROR(IF(O28="",0,O28*P28),0) -> 0
B29: Card | D29: Total This Month $ | J29: 18 | P29: 1 | Q29: =IFERROR(IF(O29="",0,O29*P29),0) -> 0
B30: CFF | D30: =SUMIF(N12:N131,B30,O12:O131) -> 15.98 | J30: 19 | P30: 1 | Q30: =IFERROR(IF(O30="",0,O30*P30),0) -> 0
B31: CFU | D31: =SUMIF(N12:N131,B31,O12:O131) -> 0 | J31: 20 | P31: 1 | Q31: =IFERROR(IF(O31="",0,O31*P31),0) -> 0
B32: CSP | D32: =SUMIF(N12:N131,B32,O12:O131) -> 0 | J32: 21 | P32: 1 | Q32: =IFERROR(IF(O32="",0,O32*P32),0) -> 0
B33: Discover | D33: =SUMIF(N12:N131,B33,O12:O131) -> 41.25 | J33: 22 | P33: 1 | Q33: =IFERROR(IF(O33="",0,O33*P33),0) -> 0
B34: Citi | D34: =SUMIF(N12:N131,B34,O12:O131) -> 0 | J34: 23 | P34: 1 | Q34: =IFERROR(IF(O34="",0,O34*P34),0) -> 0
B35: Capital One | D35: =SUMIF(N12:N131,B35,O12:O131) -> 21.99 | J35: 24 | P35: 1 | Q35: =IFERROR(IF(O35="",0,O35*P35),0) -> 0
B36: WF | D36: =SUMIF(N12:N131,B36,O12:O131) -> 0 | J36: 25 | P36: 1 | Q36: =IFERROR(IF(O36="",0,O36*P36),0) -> 0
B37: Amazon Card | D37: =SUMIF(N12:N131,B37,O12:O131) -> 7.65 | J37: 26 | P37: 1 | Q37: =IFERROR(IF(O37="",0,O37*P37),0) -> 0
B38: Robinhood | D38: =SUMIF(N12:N131,B38,O12:O131) -> 125 | J38: 27 | P38: 1 | Q38: =IFERROR(IF(O38="",0,O38*P38),0) -> 0
B39: Cash | D39: =SUMIF(N12:N131,B39,O12:O131) -> 65 | J39: 28 | P39: 1 | Q39: =IFERROR(IF(O39="",0,O39*P39),0) -> 0
B40: Other | D40: =SUMIF(N12:N131,B40,O12:O131) -> 0 | J40: 29 | P40: 1 | Q40: =IFERROR(IF(O40="",0,O40*P40),0) -> 0
B41: TOTAL CC CHARGES | D41: =SUM(D30:D40) -> 276.87 | J41: 30 | P41: 1 | Q41: =IFERROR(IF(O41="",0,O41*P41),0) -> 0
J42: 31 | P42: 1 | Q42: =IFERROR(IF(O42="",0,O42*P42),0) -> 0
B43: 📈 INVESTMENTS | J43: 32 | P43: 1 | Q43: =IFERROR(IF(O43="",0,O43*P43),0) -> 0
B44: Account | D44: Added This Month $ | F44: Invested $ | J44: 33 | P44: 1 | Q44: =IFERROR(IF(O44="",0,O44*P44),0) -> 0
B45: Robinhood Brokerage | D45: 0 | F45: ='May 2027'!F45+D45 -> 300 | J45: 34 | P45: 1 | Q45: =IFERROR(IF(O45="",0,O45*P45),0) -> 0
B46: Vanguard IRA | D46: 0 | J46: 35 | P46: 1 | Q46: =IFERROR(IF(O46="",0,O46*P46),0) -> 0
B47: 🏦 Ally Savings Buckets | J47: 36 | P47: 1 | Q47: =IFERROR(IF(O47="",0,O47*P47),0) -> 0
B48: Bucket | D48: Added This Month $ | F48: Balance $ | J48: 37 | P48: 1 | Q48: =IFERROR(IF(O48="",0,O48*P48),0) -> 0
B49: Wants | D49: 120 | F49: ='May 2027'!F49+D49 -> 4440 | J49: 38 | P49: 1 | Q49: =IFERROR(IF(O49="",0,O49*P49),0) -> 0
B50: Vacation | D50: 200 | F50: ='May 2027'!F50+D50 -> 9050 | J50: 39 | P50: 1 | Q50: =IFERROR(IF(O50="",0,O50*P50),0) -> 0
B51: Car Fund | D51: 400 | F51: ='May 2027'!F51+D51 -> 12800 | J51: 40 | P51: 1 | Q51: =IFERROR(IF(O51="",0,O51*P51),0) -> 0
B52: Emergency Fund | D52: 140 | F52: ='May 2027'!F52+D52 -> 7166.75 | J52: 41 | P52: 1 | Q52: =IFERROR(IF(O52="",0,O52*P52),0) -> 0
B53: Ally Total | D53: =SUM(D49:D52) -> 860 | F53: =SUM(F49:F52) -> 33456.75 | J53: 42 | P53: 1 | Q53: =IFERROR(IF(O53="",0,O53*P53),0) -> 0
B54: Total Invested (excl. Ally) | D54: =D45+D46 -> 0 | J54: 43 | P54: 1 | Q54: =IFERROR(IF(O54="",0,O54*P54),0) -> 0
J55: 44 | P55: 1 | Q55: =IFERROR(IF(O55="",0,O55*P55),0) -> 0
B56: 📈 MONTHLY SUMMARY | J56: 45 | P56: 1 | Q56: =IFERROR(IF(O56="",0,O56*P56),0) -> 0
B57: Total Monthly Income | D57: =H8 -> 24016.47 | J57: 46 | P57: 1 | Q57: =IFERROR(IF(O57="",0,O57*P57),0) -> 0
B58: Your Base Rent Share | D58: =D7*H7 -> 1110.7 | J58: 47 | P58: 1 | Q58: =IFERROR(IF(O58="",0,O58*P58),0) -> 0
B59: You Covered (partner's share ↓ your rent) | D59: =SUMPRODUCT((N12:N131<>"")*O12:O131*(1-P12:P131)) -> 20.625 | J59: 48 | P59: 1 | Q59: =IFERROR(IF(O59="",0,O59*P59),0) -> 0
B60: Your Rent After Adjustment | D60: =MAX(D7*H7-SUMPRODUCT((N12:N131<>"")*O12:O131*(1-P12:P131))+SUMPRODUCT((N12:N131="")*(O12:O131>0)*Q12:Q131),0) -> 1175.075 | J60: 49 | P60: 1 | Q60: =IFERROR(IF(O60="",0,O60*P60),0) -> 0
J61: 50 | P61: 1 | Q61: =IFERROR(IF(O61="",0,O61*P61),0) -> 0
B62: Total CC Charges | D62: =D41 -> 276.87 | J62: 51 | P62: 1 | Q62: =IFERROR(IF(O62="",0,O62*P62),0) -> 0
B63: Total Invested (excl. Ally) | D63: =D45+D46 -> 0 | J63: 52 | P63: 1 | Q63: =IFERROR(IF(O63="",0,O63*P63),0) -> 0
B64: TOTAL GOING OUT | D64: =D60+D62+D63 -> 1451.945 | J64: 53 | P64: 1 | Q64: =IFERROR(IF(O64="",0,O64*P64),0) -> 0
B65: 💵 MONEY LEFT OVER | D65: =H8-D64 -> 22564.525 | J65: 54 | P65: 1 | Q65: =IFERROR(IF(O65="",0,O65*P65),0) -> 0
J66: 55 | P66: 1 | Q66: =IFERROR(IF(O66="",0,O66*P66),0) -> 0
B67: 🔁 PARTNER BALANCE | J67: 56 | P67: 1 | Q67: =IFERROR(IF(O67="",0,O67*P67),0) -> 0
B68: Sharon Base Rent Share | D68: =D7*(1-H7) -> 1110.7 | J68: 57 | P68: 1 | Q68: =IFERROR(IF(O68="",0,O68*P68),0) -> 0
B69: She Covered (your share ↑ her rent) | D69: =SUMPRODUCT((N12:N131="")*(O12:O131>0)*Q12:Q131) -> 85 | J69: 58 | P69: 1 | Q69: =IFERROR(IF(O69="",0,O69*P69),0) -> 0
B70: You Covered (partner's share ↓ your rent) | D70: =SUMPRODUCT((N12:N131<>"")*O12:O131*(1-P12:P131)) -> 20.625 | J70: 59 | P70: 1 | Q70: =IFERROR(IF(O70="",0,O70*P70),0) -> 0
B71: Sharon's Total Rent This Month | D71: =MAX(D7*(1-H7)+SUMPRODUCT((N12:N131<>"")*O12:O131*(1-P12:P131))-SUMPRODUCT((N12:N131="")*(O12:O131>0)*Q12:Q131),0) -> 1046.325 | J71: 60 | P71: 1 | Q71: =IFERROR(IF(O71="",0,O71*P71),0) -> 0
B72: You Owe Sharon (if she overpaid) | D72: =MAX(SUMPRODUCT((N12:N131="")*(O12:O131>0)*Q12:Q131)-D7*(1-H7),0) -> 0 | J72: 61 | P72: 1 | Q72: =IFERROR(IF(O72="",0,O72*P72),0) -> 0
J73: 62 | P73: 1 | Q73: =IFERROR(IF(O73="",0,O73*P73),0) -> 0
J74: 63 | P74: 1 | Q74: =IFERROR(IF(O74="",0,O74*P74),0) -> 0
J75: 64 | P75: 1 | Q75: =IFERROR(IF(O75="",0,O75*P75),0) -> 0
J76: 65 | P76: 1 | Q76: =IFERROR(IF(O76="",0,O76*P76),0) -> 0
J77: 66 | P77: 1 | Q77: =IFERROR(IF(O77="",0,O77*P77),0) -> 0
J78: 67 | P78: 1 | Q78: =IFERROR(IF(O78="",0,O78*P78),0) -> 0
J79: 68 | P79: 1 | Q79: =IFERROR(IF(O79="",0,O79*P79),0) -> 0
J80: 69 | P80: 1 | Q80: =IFERROR(IF(O80="",0,O80*P80),0) -> 0
J81: 70 | P81: 1 | Q81: =IFERROR(IF(O81="",0,O81*P81),0) -> 0
J82: 71 | P82: 1 | Q82: =IFERROR(IF(O82="",0,O82*P82),0) -> 0
J83: 72 | P83: 1 | Q83: =IFERROR(IF(O83="",0,O83*P83),0) -> 0
J84: 73 | P84: 1 | Q84: =IFERROR(IF(O84="",0,O84*P84),0) -> 0
... J130: 119 | P130: 1 | Q130: =IFERROR(IF(O130="",0,O130*P130),0) -> 0
J131: 120 | P131: 1 | Q131: =IFERROR(IF(O132="",0,O132*P132),0) -> 0
L132: LOG TOTALS | O132: =SUM(O12:O131) -> 446.87 | Q132: =SUM(Q12:Q131) -> 341.245

Sheet Jul 2027
B2: 💰 Jul 2027 — Expense Tracker
B3: LEFT: summaries auto-update | RIGHT: log every transaction | Blue cells = enter data
B5: ⚙️ SETTINGS
B6: Paycheck #1 (mid-mo) | D6: 2500 | F6: Paycheck #2 (end-mo) | H6: 2500
B7: Full Monthly Rent | D7: 2221.4 | F7: Your Rent Split % | H7: 0.5
B8: Monthly Savings Goal | D8: 500 | F8: Total Monthly Income | H8: =D6+H6+D9 -> 24016.47
B9: Carried Over (prior month) | D9: ='Jun 2027'!D65 -> 19016.47
B10: 📊 CATEGORY SUMMARY | J10: 📋 EXPENSE LOG — Enter every transaction here
B11: Category | D11: Your Share $ | E11: % Income | F11: Budget $ | G11: vs Budget | J11: # | K11: Date | L11: Description | M11: Category | N11: Credit Card | O11: Total $ | P11: Split % | Q11: Your Share $ | R11: Notes / Memo | S11: Recurring?
B12: Groceries | D12: =SUMIF(M12:M131,B12,Q12:Q131) -> 0 | E12: =IFERROR(D12/(H8),0) -> 0 | F12: 300 | G12: =IF(D12=0,"",D12-F12) | J12: 1 | K12: 46569 | L12: Car Insurance | M12: Gas / Transport | N12: Cash | O12: 65 | P12: 1 | Q12: =IFERROR(IF(O12="",0,O12*P12),0) -> 65 | R12: Auto-pay | S12: Y
B13: Utilities | D13: =SUMIF(M12:M131,B13,Q12:Q131) -> 105.625 | E13: =IFERROR(D13/(H8),0) -> 0.0043980235 | F13: 50 | G13: =IF(D13=0,"",D13-F13) -> 55.625 | J13: 2 | K13: 46569 | L13: Stronghold | M13: Health | N13: Robinhood | O13: 105 | P13: 1 | Q13: =IFERROR(IF(O13="",0,O13*P13),0) -> 105 | R13: Auto-pay | S13: Y
B14: Gas / Transport | D14: =SUMIF(M12:M131,B14,Q12:Q131) -> 65 | E14: =IFERROR(D14/(H8),0) -> 0.002706476 | F14: 200 | G14: =IF(D14=0,"",D14-F14) -> -135 | J14: 3 | K14: 46569 | L14: Spectrum Internet | M14: Utilities | N14: Discover | O14: 41.25 | P14: 0.5 | Q14: =IFERROR(IF(O14="",0,O14*P14),0) -> 20.625 | R14: Auto-pay | S14: Y
B15: Dining / Takeout | D15: =SUMIF(M12:M131,B15,Q12:Q131) -> 0 | E15: =IFERROR(D15/(H8),0) -> 0 | F15: 300 | G15: =IF(D15=0,"",D15-F15) | J15: 4 | K15: 46569 | L15: Amazon Prime | M15: Subscriptions | N15: Amazon Card | O15: 7.65 | P15: 1 | Q15: =IFERROR(IF(O15="",0,O15*P15),0) -> 7.65 | R15: Auto-pay | S15: Y
B16: Entertainment | D16: =SUMIF(M12:M131,B16,Q12:Q131) -> 0 | E16: =IFERROR(D16/(H8),0) -> 0 | F16: 150 | G16: =IF(D16=0,"",D16-F16) | J16: 5 | K16: 46569 | L16: Spotify | M16: Subscriptions | N16: Capital One | O16: 21.99 | P16: 1 | Q16: =IFERROR(IF(O16="",0,O16*P16),0) -> 21.99 | R16: Auto-pay | S16: Y
B17: Health | D17: =SUMIF(M12:M131,B17,Q12:Q131) -> 105 | E17: =IFERROR(D17/(H8),0) -> 0.0043719997 | F17: 200 | G17: =IF(D17=0,"",D17-F17) -> -95 | J17: 6 | K17: 46569 | L17: Electricity | M17: Utilities | O17: 170 | P17: 0.5 | Q17: =IFERROR(IF(O17="",0,O17*P17),0) -> 85 | R17: She pays | S17: Y
B18: Shopping | D18: =SUMIF(M12:M131,B18,Q12:Q131) -> 0 | E18: =IFERROR(D18/(H8),0) -> 0 | F18: 200 | G18: =IF(D18=0,"",D18-F18) | J18: 7 | K18: 46569 | L18: Twitch Sub | M18: Subscriptions | N18: CFF | O18: 5.99 | P18: 1 | Q18: =IFERROR(IF(O18="",0,O18*P18),0) -> 5.99 | R18: Auto-pay | S18: Y
B19: Subscriptions | D19: =SUMIF(M12:M131,B19,Q12:Q131) -> 65.62 | E19: =IFERROR(D19/(H8),0) -> 0.0027322916 | F19: 100 | G19: =IF(D19=0,"",D19-F19) -> -34.38 | J19: 8 | K19: 46569 | L19: Claude AI | M19: Subscriptions | N19: Robinhood | O19: 20 | P19: 1 | Q19: =IFERROR(IF(O19="",0,O19*P19),0) -> 20 | R19: Auto-pay | S19: Y
B20: Cash | D20: =SUMIF(M12:M131,B20,Q12:Q131) -> 0 | E20: =IFERROR(D20/(H8),0) -> 0 | F20: 100 | G20: =IF(D20=0,"",D20-F20) | J20: 9 | K20: 46569 | L20: Discord | M20: Subscriptions | N20: CFF | O20: 9.99 | P20: 1 | Q20: =IFERROR(IF(O20="",0,O20*P20),0) -> 9.99 | R20: Auto-pay | S20: Y
B21: Personal / Misc | D21: =SUMIF(M12:M131,B21,Q12:Q131) -> 0 | E21: =IFERROR(D21/(H8),0) -> 0 | F21: 50 | G21: =IF(D21=0,"",D21-F21) | J21: 10 | P21: 1 | Q21: =IFERROR(IF(O21="",0,O21*P21),0) -> 0
B22: Other | D22: =SUMIF(M12:M131,B22,Q12:Q131) -> 0 | E22: =IFERROR(D22/(H8),0) -> 0 | F22: 50 | G22: =IF(D22=0,"",D22-F22) | J22: 11 | P22: 1 | Q22: =IFERROR(IF(O22="",0,O22*P22),0) -> 0
B23: Travel | D23: =SUMIF($M$12:$M$131,B23,$Q$12:$Q$131) -> 0 | E23: =IFERROR(D23/(H8),0) -> 0 | J23: 12 | P23: 1 | Q23: =IFERROR(IF(O23="",0,O23*P23),0) -> 0
B24: Adjusted Rent | D24: =D60 -> 1175.075 | E24: =IFERROR(D24/(H8),0) -> 0.048927882 | J24: 13 | P24: 1 | Q24: =IFERROR(IF(O24="",0,O24*P24),0) -> 0
B25: Investment | D25: =D63 -> 0 | E25: =IFERROR(D25/(H8),0) -> 0 | J25: 14 | P25: 1 | Q25: =IFERROR(IF(O25="",0,O25*P25),0) -> 0
B26: TOTAL Going Out | D26: =D64 -> 1451.945 | E26: =IFERROR(D26/(H8),0) -> 0.06045622 | J26: 15 | P26: 1 | Q26: =IFERROR(IF(O26="",0,O26*P26),0) -> 0
B27: 💵 Money Left Over | D27: =D65 -> 22564.525 | E27: =IFERROR(D27/(H8),0) -> 0.93954378 | J27: 16 | P27: 1 | Q27: =IFERROR(IF(O27="",0,O27*P27),0) -> 0
J28: 17 | P28: 1 | Q28: =IFERROR(IF(O28="",0,O28*P28),0) -> 0
B29: Card | D29: Total This Month $ | J29: 18 | P29: 1 | Q29: =IFERROR(IF(O29="",0,O29*P29),0) -> 0
B30: CFF | D30: =SUMIF(N12:N131,B30,O12:O131) -> 15.98 | J30: 19 | P30: 1 | Q30: =IFERROR(IF(O30="",0,O30*P30),0) -> 0
B31: CFU | D31: =SUMIF(N12:N131,B31,O12:O131) -> 0 | J31: 20 | P31: 1 | Q31: =IFERROR(IF(O31="",0,O31*P31),0) -> 0
B32: CSP | D32: =SUMIF(N12:N131,B32,O12:O131) -> 0 | J32: 21 | P32: 1 | Q32: =IFERROR(IF(O32="",0,O32*P32),0) -> 0
B33: Discover | D33: =SUMIF(N12:N131,B33,O12:O131) -> 41.25 | J33: 22 | P33: 1 | Q33: =IFERROR(IF(O33="",0,O33*P33),0) -> 0
B34: Citi | D34: =SUMIF(N12:N131,B34,O12:O131) -> 0 | J34: 23 | P34: 1 | Q34: =IFERROR(IF(O34="",0,O34*P34),0) -> 0
B35: Capital One | D35: =SUMIF(N12:N131,B35,O12:O131) -> 21.99 | J35: 24 | P35: 1 | Q35: =IFERROR(IF(O35="",0,O35*P35),0) -> 0
B36: WF | D36: =SUMIF(N12:N131,B36,O12:O131) -> 0 | J36: 25 | P36: 1 | Q36: =IFERROR(IF(O36="",0,O36*P36),0) -> 0
B37: Amazon Card | D37: =SUMIF(N12:N131,B37,O12:O131) -> 7.65 | J37: 26 | P37: 1 | Q37: =IFERROR(IF(O37="",0,O37*P37),0) -> 0
B38: Robinhood | D38: =SUMIF(N12:N131,B38,O12:O131) -> 125 | J38: 27 | P38: 1 | Q38: =IFERROR(IF(O38="",0,O38*P38),0) -> 0
B39: Cash | D39: =SUMIF(N12:N131,B39,O12:O131) -> 65 | J39: 28 | P39: 1 | Q39: =IFERROR(IF(O39="",0,O39*P39),0) -> 0
B40: Other | D40: =SUMIF(N12:N131,B40,O12:O131) -> 0 | J40: 29 | P40: 1 | Q40: =IFERROR(IF(O40="",0,O40*P40),0) -> 0
B41: TOTAL CC CHARGES | D41: =SUM(D30:D40) -> 276.87 | J41: 30 | P41: 1 | Q41: =IFERROR(IF(O41="",0,O41*P41),0) -> 0
J42: 31 | P42: 1 | Q42: =IFERROR(IF(O42="",0,O42*P42),0) -> 0
B43: 📈 INVESTMENTS | J43: 32 | P43: 1 | Q43: =IFERROR(IF(O43="",0,O43*P43),0) -> 0
B44: Account | D44: Added This Month $ | F44: Invested $ | J44: 33 | P44: 1 | Q44: =IFERROR(IF(O44="",0,O44*P44),0) -> 0
B45: Robinhood Brokerage | D45: 0 | F45: ='Jun 2027'!F45+D45 -> 300 | J45: 34 | P45: 1 | Q45: =IFERROR(IF(O45="",0,O45*P45),0) -> 0
B46: Vanguard IRA | D46: 0 | J46: 35 | P46: 1 | Q46: =IFERROR(IF(O46="",0,O46*P46),0) -> 0
B47: 🏦 Ally Savings Buckets | J47: 36 | P47: 1 | Q47: =IFERROR(IF(O47="",0,O47*P47),0) -> 0
B48: Bucket | D48: Added This Month $ | F48: Balance $ | J48: 37 | P48: 1 | Q48: =IFERROR(IF(O48="",0,O48*P48),0) -> 0
B49: Wants | D49: 120 | F49: ='Jun 2027'!F49+D49 -> 4440 | J49: 38 | P49: 1 | Q49: =IFERROR(IF(O49="",0,O49*P49),0) -> 0
B50: Vacation | D50: 200 | F50: ='Jun 2027'!F50+D50 -> 9050 | J50: 39 | P50: 1 | Q50: =IFERROR(IF(O50="",0,O50*P50),0) -> 0
B51: Car Fund | D51: 400 | F51: ='Jun 2027'!F51+D51 -> 12800 | J51: 40 | P51: 1 | Q51: =IFERROR(IF(O51="",0,O51*P51),0) -> 0
B52: Emergency Fund | D52: 140 | F52: ='Jun 2027'!F52+D52 -> 7166.75 | J52: 41 | P52: 1 | Q52: =IFERROR(IF(O52="",0,O52*P52),0) -> 0
B53: Ally Total | D53: =SUM(D49:D52) -> 860 | F53: =SUM(F49:F52) -> 33456.75 | J53: 42 | P53: 1 | Q53: =IFERROR(IF(O53="",0,O53*P53),0) -> 0
B54: Total Invested (excl. Ally) | D54: =D45+D46 -> 0 | J54: 43 | P54: 1 | Q54: =IFERROR(IF(O54="",0,O54*P54),0) -> 0
J55: 44 | P55: 1 | Q55: =IFERROR(IF(O55="",0,O55*P55),0) -> 0
B56: 📈 MONTHLY SUMMARY | J56: 45 | P56: 1 | Q56: =IFERROR(IF(O56="",0,O56*P56),0) -> 0
B57: Total Monthly Income | D57: =H8 -> 24016.47 | J57: 46 | P57: 1 | Q57: =IFERROR(IF(O57="",0,O57*P57),0) -> 0
B58: Your Base Rent Share | D58: =D7*H7 -> 1110.7 | J58: 47 | P58: 1 | Q58: =IFERROR(IF(O58="",0,O58*P58),0) -> 0
B59: You Covered (partner's share ↓ your rent) | D59: =SUMPRODUCT((N12:N131<>"")*O12:O131*(1-P12:P131)) -> 20.625 | J59: 48 | P59: 1 | Q59: =IFERROR(IF(O59="",0,O59*P59),0) -> 0
B60: Your Rent After Adjustment | D60: =MAX(D7*H7-SUMPRODUCT((N12:N131<>"")*O12:O131*(1-P12:P131))+SUMPRODUCT((N12:N131="")*(O12:O131>0)*Q12:Q131),0) -> 1175.075 | J60: 49 | P60: 1 | Q60: =IFERROR(IF(O60="",0,O60*P60),0) -> 0
J61: 50 | P61: 1 | Q61: =IFERROR(IF(O61="",0,O61*P61),0) -> 0
B62: Total CC Charges | D62: =D41 -> 276.87 | J62: 51 | P62: 1 | Q62: =IFERROR(IF(O62="",0,O62*P62),0) -> 0
B63: Total Invested (excl. Ally) | D63: =D45+D46 -> 0 | J63: 52 | P63: 1 | Q63: =IFERROR(IF(O63="",0,O63*P63),0) -> 0
B64: TOTAL GOING OUT | D64: =D60+D62+D63 -> 1451.945 | J64: 53 | P64: 1 | Q64: =IFERROR(IF(O64="",0,O64*P64),0) -> 0
B65: 💵 MONEY LEFT OVER | D65: =H8-D64 -> 22564.525 | J65: 54 | P65: 1 | Q65: =IFERROR(IF(O65="",0,O65*P65),0) -> 0
J66: 55 | P66: 1 | Q66: =IFERROR(IF(O66="",0,O66*P66),0) -> 0
B67: 🔁 PARTNER BALANCE | J67: 56 | P67: 1 | Q67: =IFERROR(IF(O67="",0,O67*P67),0) -> 0
B68: Sharon Base Rent Share | D68: =D7*(1-H7) -> 1110.7 | J68: 57 | P68: 1 | Q68: =IFERROR(IF(O68="",0,O68*P68),0) -> 0
B69: She Covered (your share ↑ her rent) | D69: =SUMPRODUCT((N12:N131="")*(O12:O131>0)*Q12:Q131) -> 85 | J69: 58 | P69: 1 | Q69: =IFERROR(IF(O69="",0,O69*P69),0) -> 0
B70: You Covered (partner's share ↓ your rent) | D70: =SUMPRODUCT((N12:N131<>"")*O12:O131*(1-P12:P131)) -> 20.625 | J70: 59 | P70: 1 | Q70: =IFERROR(IF(O70="",0,O70*P70),0) -> 0
B71: Sharon's Total Rent This Month | D71: =MAX(D7*(1-H7)+SUMPRODUCT((N12:N131<>"")*O12:O131*(1-P12:P131))-SUMPRODUCT((N12:N131="")*(O12:O131>0)*Q12:Q131),0) -> 1046.325 | J71: 60 | P71: 1 | Q71: =IFERROR(IF(O71="",0,O71*P71),0) -> 0
B72: You Owe Sharon (if she overpaid) | D72: =MAX(SUMPRODUCT((N12:N131="")*(O12:O131>0)*Q12:Q131)-D7*(1-H7),0) -> 0 | J72: 61 | P72: 1 | Q72: =IFERROR(IF(O72="",0,O72*P72),0) -> 0
J73: 62 | P73: 1 | Q73: =IFERROR(IF(O73="",0,O73*P73),0) -> 0
J74: 63 | P74: 1 | Q74: =IFERROR(IF(O74="",0,O74*P74),0) -> 0
J75: 64 | P75: 1 | Q75: =IFERROR(IF(O75="",0,O75*P75),0) -> 0
J76: 65 | P76: 1 | Q76: =IFERROR(IF(O76="",0,O76*P76),0) -> 0
J77: 66 | P77: 1 | Q77: =IFERROR(IF(O77="",0,O77*P77),0) -> 0
J78: 67 | P78: 1 | Q78: =IFERROR(IF(O78="",0,O78*P78),0) -> 0
J79: 68 | P79: 1 | Q79: =IFERROR(IF(O79="",0,O79*P79),0) -> 0
J80: 69 | P80: 1 | Q80: =IFERROR(IF(O80="",0,O80*P80),0) -> 0
J81: 70 | P81: 1 | Q81: =IFERROR(IF(O81="",0,O81*P81),0) -> 0
J82: 71 | P82: 1 | Q82: =IFERROR(IF(O82="",0,O82*P82),0) -> 0
